Workbook
Name CPIyear: 'Bundled Price (Nominal)'!$F$1

Sheet TableofContents
B2: Table of Contents
B4: Worksheet | C4: Description
B5: Case Assumptions | C5: Summary of key assumptions
B6: Dashboard | C6: Summary charts
B7: NEM Demand | C7: Summary of NEM underlying demand forecast
B8: NEM Generation | C8: Summary of NEM generation by state and technology
B9: NEM Capacity | C9: Summary of NEM capacity by state and technology type
B10: NEM Emissions | C10: Summary of NEM emissions by state and technology type
B11: NEM Interconnector | C11: Summary of NEM interconnector capacity and flows
B12: Gas Prices | C12: Summary of NEM gas prices by state
B13: Coal Prices | C13: Summary of NEM coal prices by power station
B14: Annual Black Price | C14: Summary of NEM annual time and dispatch weighted price by state
B15: Quarterly Black Price | C15: Summary of NEM quarterly time and dispatch weighted price by state
... B18: Bundled Price (Nominal) | C18: Summary of NEM bundled PV and wind dispatch weighted price by state (Nominal)

Sheet Case Assumptions
B2: Grattan Reference Case
B3: Assumption | C3: Parameter | D3: Grattan Reference Case
B4: Policy | C4: Renewable Energy Target | D4: State Government targets and expanded Capacity Investment Scheme drive emissions reductions to 2030. The CIS targets are delayed, expected to be met by 2033.
C5: Large Scale Renewable Energy Target (LRET) | D5: Implemented until 2030.
C6: Victorian Renewable Energy Target (VRET) | D6: 1st stage of VRET/QRET included 2nd stage of VRET, 40% renewables by 2025 included. 65% by 2030. 95% by 2035 included but not met. 2.6 GW storage by 2030, 6.3 GW by 2035. Offshore wind targets delayed by 2 years: 2 GW by 2034, 4GW by 2037 & 9 GW by 2042.
C7: Victoria Solar Homes Program | D7: Implemented
C8: Queensland Renewable Energy Target (QRET) | D8: Not included.
C9: New South Wales Electricity Plan (NRET) | D9: Implemented through lower WACCs on renewable plant: -Solar PV 4.1% -Wind 4.6%
C10: Snowy Hydro Expansion | D10: Implemented in 2030
C11: South Australian Energy Security Target (EST) | D11: Implemented
B12: Demand | C12: EV Growth | D12: AEMO ESOO 2024 (Central)
C13: Rooftop PV and PVNSG | D13: AEMO ESOO 2024 (Central)
C14: Embedded Storage | D14: AEMO ESOO 2024 (Central)
C15: Demand growth | D15: AEMO ESOO 2024 (Central)
B16: Fuel prices | C16: Gas Prices | D16: ACCC LNG Netback forward curve until 2027, converging to AEMO 2024 GSOO (Step Change) by 2032.
C17: Coal Prices | D17: AEMO Draft 2025 IASR (Step Change) until 2028, converging to AEMO 2024 ISP (Step Change) from 2029.
C18: Green Hydrogen Prices | D18: AEMO ISP 2024 (Step Change)
B19: Technology costs | C19: Renewable technology costs | D19: GenCost 2023-24 (Global NZE post 2050) renewable technology cost assumption
B20: Methodology | C20: New entrant pricing capable of delivering firm load | D20: Thermal technologies (gas, coal) and renewable technologies (wind, solar)
C21: Renewable Energy database update (list of committed and existing plants) | D21: Updated
C22: Demand profiles | D22: Historical 2019 demand profile, adjusted for PV and EV demand (from AEMO)
B23: Note that overlaying the above, Jacobs' has updated our database of renewable projects and incorporated market announcements.

Sheet Dashboard
B2: Dashboard
B4: NEM Demand | V4: NEM Emissions
B6: Total NEM Demand | GWh | L6: Total NEM Demand | GWh | V6: Generation Emissions Intensity | tonnes CO2e/MWh
B30: NEM Capacity & Generation
B32: Queensland Cumulative Capacity | MW | L32: Queensland Capacity Change | MW | V32: Queensland Generation | GWh
B56: New South Wales Cumulative Capacity | MW | L56: New South Wales Capacity Change | MW | V56: New South Wales Generation | GWh
B80: Victoria Cumulative Capacity | MW | L80: Victoria Capacity Change | MW | V80: Victoria Generation | GWh
B105: Tasmania Cumulative Capacity | MW | L105: Tasmania Capacity Change | MW | V105: Tasmania Generation | GWh
B129: South Australia Cumulative Capacity | MW | L129: South Australia Capacity Change | MW | V129: South Australia Generation | GWh
B152: Total NEM Cumulative Capacity | MW | L152: Total NEM Capacity Change | MW | V152: Total NEM Generation | GWh
B175: Total NEM Thermal Cumulative Capacity | MW | L175: Total NEM Thermal Capacity Change | MW | V175: Total NEM Thermal Generation | GWh
B198: Total NEM Coal Cumulative Capacity | MW | L198: Total NEM Coal Capacity Change | MW | V198: Total NEM Coal Generation | GWh
B222: Total NEM Gas Cumulative Capacity | MW | L222: Total NEM Gas Capacity Change | MW | V222: Total NEM Gas Generation | GWh
B246: Total NEM Renewable Cumulative Capacity | MW | L246: Total NEM Renewable Capacity Change | MW | V246: Total NEM Renewable Generation | GWh
B270: NEM Gas & Coal Prices
B272: Gas Price Regions | $/GJ | L272: Black Coal Average Price | $/GJ
B295: NEM Black Price
B297: Time Weighted Average Price | $/MWh | L297: Peak /Off-peak ratio | $/MWh
B320: Annual TWP and DWP
B322: Queensland | $/MWh | L322: New South Wales | $/MWh | V322: Victoria | $/MWh
B345: South Australia | $/MWh | L345: Tasmania | $/MWh
B369: Bundled Prices
B371: Generic PV Bundled Price | $/MWh | L371: Generic Wind Bundled Price | $/MWh | V371: Green Price (LGC, EIS) | $/MWh
B394: NEM Interconnector
B396: Firm Capacity Change | MW | L396: Net imports from other regions | TWh
B419: Anticipated Capacity Levels
B421: Anticipated capacity levels of wind and solar by 2030, Base scenario | L421: Anticipated capacity levels of wind and solar by 2040, Base scenario | V421: Anticipated capacity levels of wind and solar by 2050, Base scenario | AF421: Anticipated capacity levels of wind and solar by 2060, Base scenario

Sheet NEM Demand
A1: Underlying Demand
A2: Financial Year | C2: 2025 | D2: 2026 | E2: 2027 | F2: 2028 | G2: 2029 | H2: 2030 | I2: 2031 | J2: 2032 | K2: 2033 | L2: 2034 | M2: 2035 | N2: 2036 | O2: 2037 | P2: 2038 | Q2: 2039 | R2: 2040 | S2: 2041 | T2: 2042 | U2: 2043 | V2: 2044 | W2: 2045 | X2: 2046 | Y2: 2047 | Z2: 2048 | AA2: 2049 | AB2: 2050 | AC2: 2051 | AD2: 2052 | AE2: 2053 | AF2: 2054 | AG2: 2055 | AH2: 2056 | AI2: 2057 | AJ2: 2058 | AK2: 2059 | AL2: 2060
A3: Queensland
A4: Peak demand | B4: MW | C4: 10225.287 | D4: 10380.09 | E4: 10562.856 | F4: 10754.788 | G4: 10863.821 | H4: 11024.257 | I4: 11157.574 | J4: 11322.516 | K4: 11466.499 | L4: 11449.327 | M4: 11907.169 | N4: 12425.023 | O4: 12768.42 | P4: 13042.447 | Q4: 13344.379 | R4: 13890.575 | S4: 14024.716 | T4: 14647.798 | U4: 14895.047 | V4: 15307.034 | W4: 15619.466 | X4: 16064.77 | Y4: 16275.678 | Z4: 16208.017 | AA4: 16666.662 | AB4: 16786.316 | AC4: 17169.044 | AD4: 17729.366 | AE4: 18316.615 | AF4: 18669.515 | AG4: 19029.213 | AH4: 19580.897 | AI4: 20046.946 | AJ4: 20512.994 | AK4: 20979.043 | AL4: 21445.092
A5: Energy | B5: GWh | C5: 60617.128 | D5: 62212.666 | E5: 63816.374 | F5: 65317.668 | G5: 66750.828 | H5: 69399.232 | I5: 72107.442 | J5: 75789.438 | K5: 79683.746 | L5: 82281.186 | M5: 85656.614 | N5: 89201.834 | O5: 92038.823 | P5: 94255 | Q5: 97046.925 | R5: 101231.96 | S5: 102962.74 | T5: 107442.48 | U5: 110005.47 | V5: 113565.88 | W5: 116348.68 | X5: 119909 | Y5: 122273.87 | Z5: 123207.59 | AA5: 126953.75 | AB5: 128972.97 | AC5: 132309.21 | AD5: 136596.28 | AE5: 140867.88 | AF5: 143927.54 | AG5: 146987.2 | AH5: 149395.35 | AI5: 152995.54 | AJ5: 156700.68 | AK5: 160088.75 | AL5: 163598.16
A6: Load factor | B6: % | C6: 0.67673049 | D6: 0.68418505 | E6: 0.68967848 | F6: 0.69330563 | G6: 0.70140679 | H6: 0.71862321 | I6: 0.73774491 | J6: 0.76412014 | K6: 0.79329517 | L6: 0.82038269 | M6: 0.82119877 | N6: 0.81954441 | O6: 0.82286727 | P6: 0.82497582 | Q6: 0.83019346 | R6: 0.8319425 | S6: 0.83807309 | T6: 0.83733562 | U6: 0.84307906 | V6: 0.84694014 | W6: 0.85033715 | X6: 0.85206586 | Y6: 0.85761123 | Z6: 0.86776766 | AA6: 0.86954648 | AB6: 0.87708 | AC6: 0.87971067 | AD6: 0.87951155 | AE6: 0.87793555 | AF6: 0.8800488 | AG6: 0.88176847 | AH6: 0.87096438 | AI6: 0.87121722 | AJ6: 0.87204262 | AK6: 0.87110607 | AL6: 0.87085611
A7: New South Wales
A8: Peak demand | B8: MW | C8: 13293.547 | D8: 13436.44 | E8: 13605.254 | F8: 13767.481 | G8: 13781.289 | H8: 13852.645 | I8: 14053.381 | J8: 14116.247 | K8: 14156.698 | L8: 14138.764 | M8: 14457.492 | N8: 14843.863 | O8: 15226.102 | P8: 15531.568 | Q8: 15902.745 | R8: 16275.971 | S8: 16750.603 | T8: 17114.621 | U8: 17469.625 | V8: 17872.855 | W8: 18125.73 | X8: 18402.051 | Y8: 18724.164 | Z8: 19182.96 | AA8: 19553.093 | AB8: 19947.625 | AC8: 20358.785 | AD8: 21172.332 | AE8: 21569.512 | AF8: 21966.692 | AG8: 22371.166 | AH8: 22275.29 | AI8: 22685.431 | AJ8: 23103.102 | AK8: 23528.443 | AL8: 23961.595
A9: Energy | B9: GWh | C9: 74571.728 | D9: 75939.882 | E9: 77699.645 | F9: 79554.881 | G9: 81404.488 | H9: 83251.665 | I9: 85461.158 | J9: 87009.874 | K9: 87767.35 | L9: 89742.846 | M9: 91073.068 | N9: 93117.444 | O9: 95595.685 | P9: 98047.425 | Q9: 100006.73 | R9: 102387.52 | S9: 104781.45 | T9: 107825.81 | U9: 110160.68 | V9: 112437.73 | W9: 115024.11 | X9: 116646.09 | Y9: 118418.45 | Z9: 120484.53 | AA9: 123427.33 | AB9: 125801.41 | AC9: 128332.01 | AD9: 130969.25 | AE9: 136187.46 | AF9: 138735.04 | AG9: 141330.27 | AH9: 143634.68 | AI9: 146838.71 | AJ9: 149997.76 | AK9: 153076.69 | AL9: 156204.39
A10: Load factor | B10: % | C10: 0.64036743 | D10: 0.64518105 | E10: 0.65194095 | F10: 0.65964191 | G10: 0.67430193 | H10: 0.68605053 | I10: 0.69419879 | J10: 0.70363136 | K10: 0.70772887 | L10: 0.72457659 | M10: 0.71910596 | N10: 0.71611044 | O10: 0.71671328 | P10: 0.72063737 | Q10: 0.71788193 | R10: 0.71811832 | S10: 0.7140849 | T10: 0.71920273 | U10: 0.71984491 | V10: 0.71814811 | W10: 0.72441806 | X10: 0.72360212 | Y10: 0.72195954 | Z10: 0.71698748 | AA10: 0.72059584 | AB10: 0.71992991 | AC10: 0.7195799 | AD10: 0.7061493 | AE10: 0.72076337 | AF10: 0.72097033 | AG10: 0.721178 | AH10: 0.73609153 | AI10: 0.73890642 | AJ10: 0.74115725 | AK10: 0.74269716 | AL10: 0.74417215
A11: Victoria
A12: Peak demand | B12: MW | C12: 9593.713 | D12: 9697.0622 | E12: 9915.9267 | F12: 10027.401 | G12: 10166.539 | H12: 10269.01 | I12: 10316.968 | J12: 10421.2 | K12: 10507.946 | L12: 10579.767 | M12: 10905.479 | N12: 11279.722 | O12: 11631.936 | P12: 11947.877 | Q12: 12241.6 | R12: 12505.079 | S12: 12819.509 | T12: 13095.376 | U12: 13424.149 | V12: 13825.816 | W12: 14063.115 | X12: 14258.298 | Y12: 14506.598 | Z12: 14777.684 | AA12: 15053.976 | AB12: 15287.736 | AC12: 15499.527 | AD12: 15717.028 | AE12: 15894.075 | AF12: 16071.123 | AG12: 16250.143 | AH12: 15779.001 | AI12: 15954.767 | AJ12: 16132.491 | AK12: 16312.194 | AL12: 16493.899
A13: Energy | B13: GWh | C13: 47542.448 | D13: 48833.868 | E13: 50498.711 | F13: 52041.766 | G13: 53377.498 | H13: 54867.739 | I13: 56416.785 | J13: 59320.649 | K13: 63441.548 | L13: 66264.654 | M13: 68545.22 | N13: 70655.474 | O13: 73080.159 | P13: 75362.118 | Q13: 77409.066 | R13: 79312.064 | S13: 81019.121 | T13: 83056.278 | U13: 84843.593 | V13: 86973.677 | W13: 89576.036 | X13: 91113.476 | Y13: 92378.045 | Z13: 93986.756 | AA13: 95743.09 | AB13: 97533.158 | AC13: 99047.668 | AD13: 100419.84 | AE13: 101829 | AF13: 102976.08 | AG13: 104136.07 | AH13: 106121.17 | AI13: 107589.02 | AJ13: 108980.72 | AK13: 110344.01 | AL13: 111721.39
A14: Load factor | B14: % | C14: 0.56570591 | D14: 0.57487952 | E14: 0.58135697 | F14: 0.59246066 | G14: 0.59935066 | H14: 0.60993618 | I14: 0.62424077 | J14: 0.64980648 | K14: 0.68921042 | L14: 0.7149929 | M14: 0.71751061 | N14: 0.71506133 | O14: 0.71720508 | P14: 0.72004267 | Q14: 0.72185429 | R14: 0.72401688 | S14: 0.72145962 | T14: 0.7240197 | U14: 0.72148647 | V14: 0.71811328 | W14: 0.72712017 | X14: 0.72947568 | Y14: 0.72694085 | Z14: 0.7260327 | AA14: 0.72602592 | AB14: 0.72829109 | AC14: 0.72949394 | AD14: 0.72936515 | AE14: 0.73136154 | AF14: 0.7314523 | AG14: 0.73154307 | AH14: 0.76774752 | AI14: 0.76979198 | AJ14: 0.77115935 | AK14: 0.77220443 | AL14: 0.77323032
A15: South Australia
A16: Peak demand | B16: MW | C16: 2987.8326 | D16: 3047.4371 | E16: 3116.3992 | F16: 3175.5042 | G16: 3191.0635 | H16: 3200.5643 | I16: 3246.7036 | J16: 3285.0795 | K16: 3294.9293 | L16: 3312.4013 | M16: 3423.6983 | N16: 3554.9372 | O16: 3725.1185 | P16: 3824.1638 | Q16: 3923.5996 | R16: 4010.5316 | S16: 4118.0216 | T16: 4232.9815 | U16: 4388.0644 | V16: 4501.392 | W16: 4539.9853 | X16: 4637.5834 | Y16: 4662.8835 | Z16: 4771.0117 | AA16: 4877.5605 | AB16: 4904.5282 | AC16: 4949.1349 | AD16: 5166.7022 | AE16: 5237.4298 | AF16: 5308.1573 | AG16: 5379.84 | AH16: 5119.6008 | AI16: 5188.7371 | AJ16: 5258.8071 | AK16: 5329.8234 | AL16: 5401.7986
A17: Energy | B17: GWh | C17: 15529.38 | D17: 16285.83 | E17: 17389.273 | F17: 18040.493 | G17: 18362.566 | H17: 18591.601 | I17: 19054.735 | J17: 19409.812 | K17: 19748.992 | L17: 20570.345 | M17: 20893.528 | N17: 21595.553 | O17: 22423.364 | P17: 23496.811 | Q17: 24121.556 | R17: 24748.764 | S17: 25297.102 | T17: 25975.113 | U17: 26700.242 | V17: 27678.454 | W17: 28393.286 | X17: 28636.72 | Y17: 29252.337 | Z17: 29411.921 | AA17: 30093.958 | AB17: 30766.032 | AC17: 30936.136 | AD17: 31217.5 | AE17: 32589.843 | AF17: 33035.968 | AG17: 33488.201 | AH17: 33928.831 | AI17: 34508.248 | AJ17: 35130.789 | AK17: 35694.507 | AL17: 36284.332
A18: Load factor | B18: % | C18: 0.5933265 | D18: 0.61005787 | E18: 0.63697772 | F18: 0.64853229 | G18: 0.65689177 | H18: 0.66311084 | I18: 0.66997125 | J18: 0.67448351 | K18: 0.68421839 | L18: 0.70891557 | M18: 0.69664606 | N18: 0.69347096 | O18: 0.68715794 | P18: 0.70140416 | Q18: 0.70180512 | R18: 0.7044456 | S18: 0.70125835 | T18: 0.70049812 | U18: 0.69460532 | V18: 0.70192529 | W18: 0.71393244 | X18: 0.70489987 | Y18: 0.71614653 | Z18: 0.70373444 | AA18: 0.70432409 | AB18: 0.7160942 | AC18: 0.71356357 | AD18: 0.68973233 | AE18: 0.71032965 | AF18: 0.71045922 | AG18: 0.7105888 | AH18: 0.75653443 | AI18: 0.75920163 | AJ18: 0.76259956 | AK18: 0.76451228 | AL18: 0.76679034
A19: Tasmania
A20: Peak demand | B20: MW | C20: 1705.9414 | D20: 1723.9666 | E20: 1731.0859 | F20: 1732.3077 | G20: 1735.8649 | H20: 1738.6747 | I20: 1758.2769 | J20: 1798.6386 | K20: 1837.4416 | L20: 1859.6274 | M20: 1877.5479 | N20: 2017.3805 | O20: 2233.3403 | P20: 2163.1665 | Q20: 2150.5753 | R20: 2304.6764 | S20: 2160.3493 | T20: 2277.1083 | U20: 2271.8379 | V20: 2239.1482 | W20: 2173.6873 | X20: 2210.0201 | Y20: 2375.9225 | Z20: 2286.3596 | AA20: 2391.3119 | AB20: 2388.1528 | AC20: 2371.8535 | AD20: 2348.0257 | AE20: 2334.5307 | AF20: 2321.0356 | AG20: 2307.6186 | AH20: 2294.2791 | AI20: 2281.0167 | AJ20: 2267.831 | AK20: 2254.7215 | AL20: 2241.6878
A21: Energy | B21: GWh | C21: 11317.477 | D21: 11407.532 | E21: 11574.83 | F21: 11556.518 | G21: 11599.737 | H21: 12230.88 | I21: 13406.586 | J21: 13927.507 | K21: 15259.308 | L21: 16744.13 | M21: 15747.572 | N21: 15899.325 | O21: 17083.446 | P21: 18912.222 | Q21: 18317.981 | R21: 18211.358 | S21: 19516.306 | T21: 18294.125 | U21: 19282.856 | V21: 19238.225 | W21: 18961.404 | X21: 18407.073 | Y21: 18714.744 | Z21: 20119.627 | AA21: 19361.197 | AB21: 20249.947 | AC21: 20223.195 | AD21: 20085.171 | AE21: 19883.394 | AF21: 19769.116 | AG21: 20432.661 | AH21: 20610.443 | AI21: 20613.431 | AJ21: 20552.768 | AK21: 20715.898 | AL21: 20713.154
A22: Load factor | B22: % | C22: 0.75732345 | D22: 0.75536826 | E22: 0.76329411 | F22: 0.76154899 | G22: 0.76283063 | H22: 0.80303646 | I22: 0.87041594 | J22: 0.88394526 | K22: 0.94801936 | L22: 1.0278566 | M22: 0.95745522 | N22: 0.89967732 | O22: 0.87320553 | P22: 0.9980413 | Q22: 0.97234155 | R22: 0.90204513 | S22: 1.0312633 | T22: 0.9171151 | U22: 0.96892442 | V22: 0.9807946 | W22: 0.99579359 | X22: 0.95078955 | Y22: 0.89918182 | Z22: 1.0045494 | AA22: 0.92425513 | AB22: 0.96796059 | AC22: 0.97332482 | AD22: 0.97649174 | AE22: 0.97226987 | AF22: 0.97230236 | AG22: 1.0107804 | AH22: 1.0255031 | AI22: 1.0316151 | AJ22: 1.0345596 | AK22: 1.048834 | AL22: 1.0547924
A23: NEM
A24: Energy | B24: GWh | C24: 209578.16 | D24: 214679.78 | E24: 220978.83 | F24: 226511.33 | G24: 231495.12 | H24: 238341.12 | I24: 246446.71 | J24: 255457.28 | K24: 265900.95 | L24: 275603.16 | M24: 281916 | N24: 290469.63 | O24: 300221.48 | P24: 310073.58 | Q24: 316902.26 | R24: 325891.67 | S24: 333576.72 | T24: 342593.8 | U24: 350992.84 | V24: 359893.96 | W24: 368303.51 | X24: 374712.36 | Y24: 381037.45 | Z24: 387210.42 | AA24: 395579.32 | AB24: 403323.52 | AC24: 410848.22 | AD24: 419288.04 | AE24: 431357.58 | AF24: 438443.74 | AG24: 446374.4 | AH24: 453690.47 | AI24: 462544.95 | AJ24: 471362.71 | AK24: 479919.86 | AL24: 488521.43
A25: Growth rate | B25: % | C25: 0.0072346122 | D25: 0.024342305 | E25: 0.029341637 | F25: 0.025036299 | G25: 0.022002394 | H25: 0.029572978 | I25: 0.034008354 | J25: 0.036561958 | K25: 0.040882238 | L25: 0.036488081 | M25: 0.022905547 | N25: 0.030341052 | O25: 0.033572691 | P25: 0.032816102 | Q25: 0.022022784 | R25: 0.028366495 | S25: 0.023581609 | T25: 0.027031528 | U25: 0.024516026 | V25: 0.025359825 | W25: 0.023366747 | X25: 0.017400992 | Y25: 0.016879857 | Z25: 0.016200442 | AA25: 0.021613314 | AB25: 0.019576856 | AC25: 0.018656716 | AD25: 0.020542431 | AE25: 0.028785804 | AF25: 0.01642757 | AG25: 0.018088215 | AH25: 0.016389988 | AI25: 0.019516568 | AJ25: 0.019063567 | AK25: 0.018154072 | AL25: 0.017922925
A26: System load factor | B26: % | C26: 0.75372384 | D26: 0.76618619 | E26: 0.77421443 | F26: 0.78411426 | G26: 0.79807808 | H26: 0.80912165 | I26: 0.83114123 | J26: 0.8484616 | K26: 0.886578 | L26: 0.9192152 | M26: 0.91332569 | N26: 0.91511141 | O26: 0.90777228 | P26: 0.89385849 | Q26: 0.87040747 | R26: 0.87753817 | S26: 0.86682176 | T26: 0.85659226 | U26: 0.83977383 | V26: 0.85511827 | W26: 0.84607846 | X26: 0.85648255 | Y26: 0.86821352 | Z26: 0.86400965 | AA26: 0.86409932 | AB26: 0.87477897 | AC26: 0.88029667 | AD26: 0.87990247 | AE26: 0.87220816 | AF26: 0.87596184 | AG26: 0.89158875 | AH26: 0.8948903 | AI26: 0.88482343 | AJ26: 0.87863799 | AK26: 0.87426141 | AL26: 0.87250602

Sheet NEM Capacity
A1: Capacity
A2: Financial Year | C2: 2025 | D2: 2026 | E2: 2027 | F2: 2028 | G2: 2029 | H2: 2030 | I2: 2031 | J2: 2032 | K2: 2033 | L2: 2034 | M2: 2035 | N2: 2036 | O2: 2037 | P2: 2038 | Q2: 2039 | R2: 2040 | S2: 2041 | T2: 2042 | U2: 2043 | V2: 2044 | W2: 2045 | X2: 2046 | Y2: 2047 | Z2: 2048 | AA2: 2049 | AB2: 2050 | AC2: 2051 | AD2: 2052 | AE2: 2053 | AF2: 2054 | AG2: 2055 | AH2: 2056 | AI2: 2057 | AJ2: 2058 | AK2: 2059 | AL2: 2060
A3: Queensland South
A4: Black Coal | B4: MW | C4: 3182.34 | D4: 3182.34 | E4: 3182.34 | F4: 3182.34 | G4: 3182.34 | H4: 3182.34 | I4: 3182.34 | J4: 3182.34 | K4: 3182.34 | L4: 3182.34 | M4: 3182.34 | N4: 2538.34 | O4: 1477.92 | P4: 1477.92 | Q4: 1477.92 | R4: 1477.92 | S4: 1477.92 | T4: 800.88 | U4: 800.88 | V4: 800.88 | W4: 800.88 | X4: 800.88 | Y4: 800.88 | Z4: 800.88 | AA4: 800.88 | AB4: 800.88 | AC4: 0 | AD4: 0 | AE4: 0 | AF4: 0 | AG4: 0 | AH4: 0 | AI4: 0 | AJ4: 0 | AK4: 0 | AL4: 0
A5: Brown Coal | B5: MW | C5: 0 | D5: 0 | E5: 0 | F5: 0 | G5: 0 | H5: 0 | I5: 0 | J5: 0 | K5: 0 | L5: 0 | M5: 0 | N5: 0 | O5: 0 | P5: 0 | Q5: 0 | R5: 0 | S5: 0 | T5: 0 | U5: 0 | V5: 0 | W5: 0 | X5: 0 | Y5: 0 | Z5: 0 | AA5: 0 | AB5: 0 | AC5: 0 | AD5: 0 | AE5: 0 | AF5: 0 | AG5: 0 | AH5: 0 | AI5: 0 | AJ5: 0 | AK5: 0 | AL5: 0
A6: Hydrogen ready | B6: MW | C6: 0 | D6: 0 | E6: 0 | F6: 0 | G6: 482.8 | H6: 482.8 | I6: 482.8 | J6: 482.8 | K6: 482.8 | L6: 482.8 | M6: 862.8 | N6: 862.8 | O6: 862.8 | P6: 862.8 | Q6: 862.8 | R6: 862.8 | S6: 862.8 | T6: 862.8 | U6: 1036 | V6: 1036 | W6: 1036 | X6: 1036 | Y6: 1036 | Z6: 1582.2 | AA6: 1746.9 | AB6: 1746.9 | AC6: 1911.6 | AD6: 1911.6 | AE6: 1911.6 | AF6: 1911.6 | AG6: 1911.6 | AH6: 1911.6 | AI6: 1911.6 | AJ6: 1911.6 | AK6: 1911.6 | AL6: 1911.6
A7: Gas GT | B7: MW | C7: 1423.86 | D7: 1423.86 | E7: 1423.86 | F7: 1423.86 | G7: 1390.03 | H7: 1356.2 | I7: 1356.2 | J7: 1356.2 | K7: 1356.2 | L7: 1356.2 | M7: 1356.2 | N7: 1356.2 | O7: 1356.2 | P7: 1356.2 | Q7: 1356.2 | R7: 1356.2 | S7: 1356.2 | T7: 1356.2 | U7: 1356.2 | V7: 1356.2 | W7: 1356.2 | X7: 1356.2 | Y7: 839.78 | Z7: 839.78 | AA7: 839.78 | AB7: 839.78 | AC7: 501.48 | AD7: 501.48 | AE7: 501.48 | AF7: 501.48 | AG7: 501.48 | AH7: 501.48 | AI7: 0 | AJ7: 0 | AK7: 0 | AL7: 0
A8: Gas CCGT & Cogen | B8: MW | C8: 1117.42 | D8: 1117.42 | E8: 1117.42 | F8: 758.52 | G8: 758.52 | H8: 758.52 | I8: 758.52 | J8: 758.52 | K8: 758.52 | L8: 758.52 | M8: 758.52 | N8: 758.52 | O8: 758.52 | P8: 758.52 | Q8: 758.52 | R8: 758.52 | S8: 617.4 | T8: 617.4 | U8: 617.4 | V8: 617.4 | W8: 617.4 | X8: 0 | Y8: 0 | Z8: 0 | AA8: 0 | AB8: 0 | AC8: 0 | AD8: 0 | AE8: 0 | AF8: 0 | AG8: 0 | AH8: 0 | AI8: 0 | AJ8: 0 | AK8: 0 | AL8: 0
A9: Gas CC CCS | B9: MW | C9: 0 | D9: 0 | E9: 0 | F9: 0 | G9: 0 | H9: 0 | I9: 0 | J9: 0 | K9: 0 | L9: 0 | M9: 0 | N9: 0 | O9: 0 | P9: 0 | Q9: 0 | R9: 0 | S9: 0 | T9: 0 | U9: 0 | V9: 0 | W9: 0 | X9: 0 | Y9: 0 | Z9: 0 | AA9: 0 | AB9: 0 | AC9: 0 | AD9: 0 | AE9: 0 | AF9: 0 | AG9: 0 | AH9: 0 | AI9: 0 | AJ9: 0 | AK9: 0 | AL9: 0
A10: Gas Steam | B10: MW | C10: 0 | D10: 0 | E10: 0 | F10: 0 | G10: 0 | H10: 0 | I10: 0 | J10: 0 | K10: 0 | L10: 0 | M10: 0 | N10: 0 | O10: 0 | P10: 0 | Q10: 0 | R10: 0 | S10: 0 | T10: 0 | U10: 0 | V10: 0 | W10: 0 | X10: 0 | Y10: 0 | Z10: 0 | AA10: 0 | AB10: 0 | AC10: 0 | AD10: 0 | AE10: 0 | AF10: 0 | AG10: 0 | AH10: 0 | AI10: 0 | AJ10: 0 | AK10: 0 | AL10: 0
A11: Distillate | B11: MW | C11: 0 | D11: 0 | E11: 0 | F11: 0 | G11: 0 | H11: 0 | I11: 0 | J11: 0 | K11: 0 | L11: 0 | M11: 0 | N11: 0 | O11: 0 | P11: 0 | Q11: 0 | R11: 0 | S11: 0 | T11: 0 | U11: 0 | V11: 0 | W11: 0 | X11: 0 | Y11: 0 | Z11: 0 | AA11: 0 | AB11: 0 | AC11: 0 | AD11: 0 | AE11: 0 | AF11: 0 | AG11: 0 | AH11: 0 | AI11: 0 | AJ11: 0 | AK11: 0 | AL11: 0
A12: Hydro | B12: MW | C12: 54.495 | D12: 54.495 | E12: 54.495 | F12: 54.495 | G12: 54.495 | H12: 54.495 | I12: 54.495 | J12: 54.495 | K12: 54.495 | L12: 54.495 | M12: 54.495 | N12: 54.495 | O12: 54.495 | P12: 54.495 | Q12: 54.495 | R12: 54.495 | S12: 54.495 | T12: 54.495 | U12: 54.495 | V12: 54.495 | W12: 54.495 | X12: 54.495 | Y12: 54.495 | Z12: 54.495 | AA12: 54.495 | AB12: 54.495 | AC12: 54.495 | AD12: 54.495 | AE12: 54.495 | AF12: 54.495 | AG12: 54.495 | AH12: 54.495 | AI12: 54.495 | AJ12: 54.495 | AK12: 54.495 | AL12: 54.495
A13: Wind | B13: MW | C13: 1864.99 | D13: 1864.99 | E13: 1864.99 | F13: 1864.99 | G13: 1864.99 | H13: 1864.99 | I13: 1864.99 | J13: 1864.99 | K13: 1864.99 | L13: 1864.99 | M13: 1864.99 | N13: 1864.99 | O13: 1864.99 | P13: 1864.99 | Q13: 1864.99 | R13: 1864.99 | S13: 1864.99 | T13: 1864.99 | U13: 2064.99 | V13: 2296.99 | W13: 2496.99 | X13: 2496.99 | Y13: 2496.99 | Z13: 2496.99 | AA13: 2496.99 | AB13: 2696.99 | AC13: 2896.99 | AD13: 2896.99 | AE13: 2896.99 | AF13: 2896.99 | AG13: 2896.99 | AH13: 2896.99 | AI13: 2896.99 | AJ13: 2896.99 | AK13: 3296.99 | AL13: 3296.99
A14: Biomass | B14: MW | C14: 384.45 | D14: 384.45 | E14: 384.45 | F14: 384.45 | G14: 384.45 | H14: 384.45 | I14: 384.45 | J14: 384.45 | K14: 384.45 | L14: 384.45 | M14: 384.45 | N14: 384.45 | O14: 384.45 | P14: 384.45 | Q14: 384.45 | R14: 384.45 | S14: 384.45 | T14: 384.45 | U14: 384.45 | V14: 384.45 | W14: 384.45 | X14: 384.45 | Y14: 384.45 | Z14: 384.45 | AA14: 384.45 | AB14: 384.45 | AC14: 384.45 | AD14: 384.45 | AE14: 384.45 | AF14: 384.45 | AG14: 384.45 | AH14: 384.45 | AI14: 384.45 | AJ14: 384.45 | AK14: 384.45 | AL14: 384.45
A15: Solar | B15: MW | C15: 2163.77 | D15: 3040.49 | E15: 3991.29 | F15: 3991.29 | G15: 4241.29 | H15: 4241.29 | I15: 4241.29 | J15: 4241.29 | K15: 4241.29 | L15: 4241.29 | M15: 4391.29 | N15: 4391.29 | O15: 5611.29 | P15: 6311.29 | Q15: 6311.29 | R15: 7361.29 | S15: 7561.29 | T15: 7561.29 | U15: 7561.29 | V15: 7561.29 | W15: 7811.29 | X15: 8611.29 | Y15: 9611.29 | Z15: 9611.29 | AA15: 9611.29 | AB15: 10161.29 | AC15: 11211.29 | AD15: 11911.29 | AE15: 12111.29 | AF15: 12111.29 | AG15: 12111.29 | AH15: 12111.29 | AI15: 12111.29 | AJ15: 12511.29 | AK15: 12711.29 | AL15: 12911.29
... A22: Total | B22: MW | C22: 16629.9 | D22: 18574.129 | E22: 20009.486 | F22: 20750.558 | G22: 22358.762 | H22: 22990.909 | I22: 25540.472 | J22: 27285.025 | K22: 28085.836 | L22: 28644.217 | M22: 29705.799 | N22: 29601.496 | O22: 30410.731 | P22: 31816.838 | Q22: 32523.153 | R22: 34226.167 | S22: 34929.191 | T22: 34977.538 | U22: 36130.181 | V22: 37122.739 | W22: 38277.175 | X22: 39200.931 | Y22: 40449.227 | Z22: 41719.507 | AA22: 42604.208 | AB22: 44026.311 | AC22: 44845.472 | AD22: 46159.274 | AE22: 46963.545 | AF22: 47574.09 | AG22: 48189.876 | AH22: 48799.532 | AI22: 48905.505 | AJ22: 49913.64 | AK22: 51120.572 | AL22: 51936.45
A23: Queensland North
A24: Black Coal | B24: MW | C24: 0 | D24: 0 | E24: 0 | F24: 0 | G24: 0 | H24: 0 | I24: 0 | J24: 0 | K24: 0 | L24: 0 | M24: 0 | N24: 0 | O24: 0 | P24: 0 | Q24: 0 | R24: 0 | S24: 0 | T24: 0 | U24: 0 | V24: 0 | W24: 0 | X24: 0 | Y24: 0 | Z24: 0 | AA24: 0 | AB24: 0 | AC24: 0 | AD24: 0 | AE24: 0 | AF24: 0 | AG24: 0 | AH24: 0 | AI24: 0 | AJ24: 0 | AK24: 0 | AL24: 0
A25: Brown Coal | B25: MW | C25: 0 | D25: 0 | E25: 0 | F25: 0 | G25: 0 | H25: 0 | I25: 0 | J25: 0 | K25: 0 | L25: 0 | M25: 0 | N25: 0 | O25: 0 | P25: 0 | Q25: 0 | R25: 0 | S25: 0 | T25: 0 | U25: 0 | V25: 0 | W25: 0 | X25: 0 | Y25: 0 | Z25: 0 | AA25: 0 | AB25: 0 | AC25: 0 | AD25: 0 | AE25: 0 | AF25: 0 | AG25: 0 | AH25: 0 | AI25: 0 | AJ25: 0 | AK25: 0 | AL25: 0
A26: Hydrogen ready | B26: MW | C26: 0 | D26: 0 | E26: 0 | F26: 0 | G26: 0 | H26: 0 | I26: 0 | J26: 0 | K26: 0 | L26: 0 | M26: 0 | N26: 0 | O26: 0 | P26: 0 | Q26: 0 | R26: 193.12 | S26: 193.12 | T26: 193.12 | U26: 193.12 | V26: 358.92 | W26: 358.92 | X26: 358.92 | Y26: 358.92 | Z26: 358.92 | AA26: 358.92 | AB26: 358.92 | AC26: 358.92 | AD26: 358.92 | AE26: 358.92 | AF26: 358.92 | AG26: 358.92 | AH26: 358.92 | AI26: 358.92 | AJ26: 358.92 | AK26: 358.92 | AL26: 358.92
A27: Gas GT | B27: MW | C27: 416.91 | D27: 416.91 | E27: 416.91 | F27: 416.91 | G27: 416.91 | H27: 416.91 | I27: 416.91 | J27: 416.91 | K27: 126.37 | L27: 126.37 | M27: 126.37 | N27: 126.37 | O27: 126.37 | P27: 126.37 | Q27: 126.37 | R27: 126.37 | S27: 126.37 | T27: 126.37 | U27: 126.37 | V27: 126.37 | W27: 0 | X27: 0 | Y27: 0 | Z27: 0 | AA27: 0 | AB27: 0 | AC27: 0 | AD27: 0 | AE27: 0 | AF27: 0 | AG27: 0 | AH27: 0 | AI27: 0 | AJ27: 0 | AK27: 0 | AL27: 0
A28: Gas CCGT & Cogen | B28: MW | C28: 235.71 | D28: 235.71 | E28: 235.71 | F28: 235.71 | G28: 235.71 | H28: 235.71 | I28: 235.71 | J28: 235.71 | K28: 235.71 | L28: 235.71 | M28: 235.71 | N28: 235.71 | O28: 235.71 | P28: 235.71 | Q28: 235.71 | R28: 235.71 | S28: 235.71 | T28: 235.71 | U28: 235.71 | V28: 235.71 | W28: 235.71 | X28: 235.71 | Y28: 0 | Z28: 0 | AA28: 0 | AB28: 0 | AC28: 0 | AD28: 0 | AE28: 0 | AF28: 0 | AG28: 0 | AH28: 0 | AI28: 0 | AJ28: 0 | AK28: 0 | AL28: 0
A29: Gas CC CCS | B29: MW | C29: 0 | D29: 0 | E29: 0 | F29: 0 | G29: 0 | H29: 0 | I29: 0 | J29: 0 | K29: 0 | L29: 0 | M29: 0 | N29: 0 | O29: 0 | P29: 0 | Q29: 0 | R29: 0 | S29: 0 | T29: 0 | U29: 0 | V29: 0 | W29: 0 | X29: 0 | Y29: 0 | Z29: 0 | AA29: 0 | AB29: 0 | AC29: 0 | AD29: 0 | AE29: 0 | AF29: 0 | AG29: 0 | AH29: 0 | AI29: 0 | AJ29: 0 | AK29: 0 | AL29: 0
A30: Gas Steam | B30: MW | C30: 0 | D30: 0 | E30: 0 | F30: 0 | G30: 0 | H30: 0 | I30: 0 | J30: 0 | K30: 0 | L30: 0 | M30: 0 | N30: 0 | O30: 0 | P30: 0 | Q30: 0 | R30: 0 | S30: 0 | T30: 0 | U30: 0 | V30: 0 | W30: 0 | X30: 0 | Y30: 0 | Z30: 0 | AA30: 0 | AB30: 0 | AC30: 0 | AD30: 0 | AE30: 0 | AF30: 0 | AG30: 0 | AH30: 0 | AI30: 0 | AJ30: 0 | AK30: 0 | AL30: 0
A31: Distillate | B31: MW | C31: 0 | D31: 0 | E31: 0 | F31: 0 | G31: 0 | H31: 0 | I31: 0 | J31: 0 | K31: 0 | L31: 0 | M31: 0 | N31: 0 | O31: 0 | P31: 0 | Q31: 0 | R31: 0 | S31: 0 | T31: 0 | U31: 0 | V31: 0 | W31: 0 | X31: 0 | Y31: 0 | Z31: 0 | AA31: 0 | AB31: 0 | AC31: 0 | AD31: 0 | AE31: 0 | AF31: 0 | AG31: 0 | AH31: 0 | AI31: 0 | AJ31: 0 | AK31: 0 | AL31: 0
A32: Hydro | B32: MW | C32: 202.495 | D32: 202.495 | E32: 202.495 | F32: 202.495 | G32: 202.495 | H32: 202.495 | I32: 202.495 | J32: 202.495 | K32: 202.495 | L32: 202.495 | M32: 202.495 | N32: 202.495 | O32: 202.495 | P32: 202.495 | Q32: 202.495 | R32: 202.495 | S32: 202.495 | T32: 202.495 | U32: 202.495 | V32: 202.495 | W32: 202.495 | X32: 202.495 | Y32: 202.495 | Z32: 202.495 | AA32: 202.495 | AB32: 202.495 | AC32: 202.495 | AD32: 202.495 | AE32: 202.495 | AF32: 202.495 | AG32: 202.495 | AH32: 202.495 | AI32: 202.495 | AJ32: 202.495 | AK32: 202.495 | AL32: 202.495
A33: Wind | B33: MW | C33: 401.65 | D33: 401.65 | E33: 401.65 | F33: 474.75 | G33: 882.75 | H33: 882.75 | I33: 882.75 | J33: 882.75 | K33: 882.75 | L33: 1282.75 | M33: 1882.75 | N33: 2082.75 | O33: 2082.75 | P33: 2482.75 | Q33: 2482.75 | R33: 2882.75 | S33: 3682.75 | T33: 3682.75 | U33: 4282.75 | V33: 4282.75 | W33: 4482.75 | X33: 4482.75 | Y33: 4682.75 | Z33: 4682.75 | AA33: 4682.75 | AB33: 4682.75 | AC33: 4882.75 | AD33: 4882.75 | AE33: 4882.75 | AF33: 5282.75 | AG33: 5282.75 | AH33: 5282.75 | AI33: 5282.75 | AJ33: 6282.75 | AK33: 6682.75 | AL33: 6682.75
A34: Biomass | B34: MW | C34: 58.7125 | D34: 58.7125 | E34: 58.7125 | F34: 58.7125 | G34: 58.7125 | H34: 58.7125 | I34: 58.7125 | J34: 58.7125 | K34: 58.7125 | L34: 58.7125 | M34: 58.7125 | N34: 58.7125 | O34: 58.7125 | P34: 58.7125 | Q34: 58.7125 | R34: 58.7125 | S34: 58.7125 | T34: 58.7125 | U34: 58.7125 | V34: 58.7125 | W34: 58.7125 | X34: 58.7125 | Y34: 58.7125 | Z34: 58.7125 | AA34: 58.7125 | AB34: 58.7125 | AC34: 58.7125 | AD34: 58.7125 | AE34: 58.7125 | AF34: 58.7125 | AG34: 58.7125 | AH34: 58.7125 | AI34: 58.7125 | AJ34: 58.7125 | AK34: 58.7125 | AL34: 58.7125
A35: Solar | B35: MW | C35: 513.24 | D35: 513.24 | E35: 513.24 | F35: 727.04 | G35: 877.04 | H35: 877.04 | I35: 877.04 | J35: 877.04 | K35: 877.04 | L35: 877.04 | M35: 877.04 | N35: 877.04 | O35: 877.04 | P35: 987.04 | Q35: 987.04 | R35: 987.04 | S35: 987.04 | T35: 987.04 | U35: 987.04 | V35: 987.04 | W35: 987.04 | X35: 1387.04 | Y35: 1387.04 | Z35: 1387.04 | AA35: 1387.04 | AB35: 1587.04 | AC35: 1787.04 | AD35: 1787.04 | AE35: 2187.04 | AF35: 2187.04 | AG35: 2837.04 | AH35: 2837.04 | AI35: 2837.04 | AJ35: 2837.04 | AK35: 2837.04 | AL35: 2837.04
... A42: Total | B42: MW | C42: 2835.9158 | D42: 3198.9124 | E42: 3321.4015 | F42: 4190.6412 | G42: 5011.462 | H42: 5127.423 | I42: 5275.1321 | J42: 6174.6375 | K42: 6047.3173 | L42: 6592.6024 | M42: 7332.8141 | N42: 7676.1704 | O42: 7847.221 | P42: 8542.8043 | Q42: 8730.281 | R42: 9500.018 | S42: 10453.62 | T42: 10627.131 | U42: 11413.668 | V42: 11760.946 | W42: 12001.982 | X42: 12578.628 | Y42: 12725.182 | Z42: 12897.821 | AA42: 13070.463 | AB42: 13431.872 | AC42: 13961.267 | AD42: 14108.16 | AE42: 14652.578 | AF42: 15198.267 | AG42: 15994.939 | AH42: 16139.728 | AI42: 16283.625 | AJ42: 17427.367 | AK42: 17970.463 | AL42: 18115.457
A43: Queensland Central
A44: Black Coal | B44: MW | C44: 4300.8 | D44: 4300.8 | E44: 4300.8 | F44: 4300.8 | G44: 4300.8 | H44: 4300.8 | I44: 3663.8 | J44: 3663.8 | K44: 3663.8 | L44: 3663.8 | M44: 2118.2 | N44: 2118.2 | O44: 2118.2 | P44: 2118.2 | Q44: 2118.2 | R44: 2118.2 | S44: 2118.2 | T44: 2118.2 | U44: 1786.05 | V44: 1453.9 | W44: 1121.75 | X44: 789.6 | Y44: 789.6 | Z44: 789.6 | AA44: 789.6 | AB44: 789.6 | AC44: 0 | AD44: 0 | AE44: 0 | AF44: 0 | AG44: 0 | AH44: 0 | AI44: 0 | AJ44: 0 | AK44: 0 | AL44: 0
A45: Brown Coal | B45: MW | C45: 0 | D45: 0 | E45: 0 | F45: 0 | G45: 0 | H45: 0 | I45: 0 | J45: 0 | K45: 0 | L45: 0 | M45: 0 | N45: 0 | O45: 0 | P45: 0 | Q45: 0 | R45: 0 | S45: 0 | T45: 0 | U45: 0 | V45: 0 | W45: 0 | X45: 0 | Y45: 0 | Z45: 0 | AA45: 0 | AB45: 0 | AC45: 0 | AD45: 0 | AE45: 0 | AF45: 0 | AG45: 0 | AH45: 0 | AI45: 0 | AJ45: 0 | AK45: 0 | AL45: 0
A46: Hydrogen ready | B46: MW | C46: 0 | D46: 0 | E46: 0 | F46: 0 | G46: 380 | H46: 380 | I46: 380 | J46: 380 | K46: 380 | L46: 380 | M46: 380 | N46: 760 | O46: 1306.2 | P46: 1789 | Q46: 1789 | R46: 1789 | S46: 1789 | T46: 1789 | U46: 1789 | V46: 1789 | W46: 1789 | X46: 1789 | Y46: 2210.6 | Z46: 2590.6 | AA46: 2590.6 | AB46: 2590.6 | AC46: 2590.6 | AD46: 2590.6 | AE46: 2590.6 | AF46: 2590.6 | AG46: 2590.6 | AH46: 2590.6 | AI46: 2590.6 | AJ46: 2590.6 | AK46: 2590.6 | AL46: 2590.6
A47: Gas GT | B47: MW | C47: 82.42 | D47: 82.42 | E47: 82.42 | F47: 82.42 | G47: 82.42 | H47: 82.42 | I47: 82.42 | J47: 82.42 | K47: 82.42 | L47: 82.42 | M47: 45.6 | N47: 45.6 | O47: 45.6 | P47: 45.6 | Q47: 45.6 | R47: 45.6 | S47: 45.6 | T47: 45.6 | U47: 45.6 | V47: 45.6 | W47: 45.6 | X47: 45.6 | Y47: 45.6 | Z47: 45.6 | AA47: 45.6 | AB47: 45.6 | AC47: 45.6 | AD47: 45.6 | AE47: 45.6 | AF47: 45.6 | AG47: 45.6 | AH47: 45.6 | AI47: 45.6 | AJ47: 45.6 | AK47: 45.6 | AL47: 45.6
A48: Gas CCGT & Cogen | B48: MW | C48: 156.8 | D48: 156.8 | E48: 156.8 | F48: 156.8 | G48: 156.8 | H48: 156.8 | I48: 156.8 | J48: 156.8 | K48: 156.8 | L48: 156.8 | M48: 156.8 | N48: 156.8 | O48: 206.8 | P48: 206.8 | Q48: 206.8 | R48: 206.8 | S48: 206.8 | T48: 206.8 | U48: 206.8 | V48: 206.8 | W48: 206.8 | X48: 206.8 | Y48: 206.8 | Z48: 206.8 | AA48: 206.8 | AB48: 206.8 | AC48: 206.8 | AD48: 206.8 | AE48: 206.8 | AF48: 206.8 | AG48: 206.8 | AH48: 206.8 | AI48: 206.8 | AJ48: 206.8 | AK48: 206.8 | AL48: 206.8
A49: Gas CC CCS | B49: MW | C49: 0 | D49: 0 | E49: 0 | F49: 0 | G49: 0 | H49: 0 | I49: 0 | J49: 0 | K49: 0 | L49: 0 | M49: 0 | N49: 0 | O49: 0 | P49: 0 | Q49: 0 | R49: 0 | S49: 0 | T49: 0 | U49: 0 | V49: 0 | W49: 0 | X49: 0 | Y49: 0 | Z49: 0 | AA49: 0 | AB49: 0 | AC49: 0 | AD49: 0 | AE49: 0 | AF49: 0 | AG49: 0 | AH49: 0 | AI49: 0 | AJ49: 0 | AK49: 0 | AL49: 0
A50: Gas Steam | B50: MW | C50: 0 | D50: 0 | E50: 0 | F50: 0 | G50: 0 | H50: 0 | I50: 0 | J50: 0 | K50: 0 | L50: 0 | M50: 0 | N50: 0 | O50: 0 | P50: 0 | Q50: 0 | R50: 0 | S50: 0 | T50: 0 | U50: 0 | V50: 0 | W50: 0 | X50: 0 | Y50: 0 | Z50: 0 | AA50: 0 | AB50: 0 | AC50: 0 | AD50: 0 | AE50: 0 | AF50: 0 | AG50: 0 | AH50: 0 | AI50: 0 | AJ50: 0 | AK50: 0 | AL50: 0
A51: Distillate | B51: MW | C51: 0 | D51: 0 | E51: 0 | F51: 0 | G51: 0 | H51: 0 | I51: 0 | J51: 0 | K51: 0 | L51: 0 | M51: 0 | N51: 0 | O51: 0 | P51: 0 | Q51: 0 | R51: 0 | S51: 0 | T51: 0 | U51: 0 | V51: 0 | W51: 0 | X51: 0 | Y51: 0 | Z51: 0 | AA51: 0 | AB51: 0 | AC51: 0 | AD51: 0 | AE51: 0 | AF51: 0 | AG51: 0 | AH51: 0 | AI51: 0 | AJ51: 0 | AK51: 0 | AL51: 0
A52: Hydro | B52: MW | C52: 0 | D52: 0 | E52: 0 | F52: 0 | G52: 0 | H52: 0 | I52: 0 | J52: 0 | K52: 0 | L52: 0 | M52: 0 | N52: 0 | O52: 0 | P52: 0 | Q52: 0 | R52: 0 | S52: 0 | T52: 0 | U52: 0 | V52: 0 | W52: 0 | X52: 0 | Y52: 0 | Z52: 0 | AA52: 0 | AB52: 0 | AC52: 0 | AD52: 0 | AE52: 0 | AF52: 0 | AG52: 0 | AH52: 0 | AI52: 0 | AJ52: 0 | AK52: 0 | AL52: 0
A53: Wind | B53: MW | C53: 450 | D53: 450 | E53: 450 | F53: 735.2 | G53: 735.2 | H53: 735.2 | I53: 735.2 | J53: 735.2 | K53: 735.2 | L53: 885.2 | M53: 1235.2 | N53: 1435.2 | O53: 2035.2 | P53: 2035.2 | Q53: 2035.2 | R53: 2435.2 | S53: 3035.2 | T53: 3635.2 | U53: 4835.2 | V53: 5235.2 | W53: 5435.2 | X53: 5435.2 | Y53: 5435.2 | Z53: 5635.2 | AA53: 5635.2 | AB53: 6035.2 | AC53: 6435.2 | AD53: 6435.2 | AE53: 6635.2 | AF53: 6635.2 | AG53: 7035.2 | AH53: 7035.2 | AI53: 7435.2 | AJ53: 7835.2 | AK53: 8035.2 | AL53: 8035.2
A54: Biomass | B54: MW | C54: 89.3825 | D54: 89.3825 | E54: 89.3825 | F54: 89.3825 | G54: 89.3825 | H54: 89.3825 | I54: 89.3825 | J54: 89.3825 | K54: 89.3825 | L54: 89.3825 | M54: 89.3825 | N54: 89.3825 | O54: 89.3825 | P54: 89.3825 | Q54: 89.3825 | R54: 89.3825 | S54: 89.3825 | T54: 89.3825 | U54: 89.3825 | V54: 89.3825 | W54: 89.3825 | X54: 89.3825 | Y54: 89.3825 | Z54: 89.3825 | AA54: 89.3825 | AB54: 89.3825 | AC54: 89.3825 | AD54: 89.3825 | AE54: 89.3825 | AF54: 89.3825 | AG54: 89.3825 | AH54: 89.3825 | AI54: 89.3825 | AJ54: 89.3825 | AK54: 89.3825 | AL54: 89.3825
A55: Solar | B55: MW | C55: 870.782 | D55: 870.782 | E55: 1238.782 | F55: 1438.782 | G55: 1438.782 | H55: 1438.782 | I55: 1438.782 | J55: 1438.782 | K55: 1438.782 | L55: 1438.782 | M55: 1543.782 | N55: 1543.782 | O55: 1919.782 | P55: 2119.782 | Q55: 2119.782 | R55: 2672.782 | S55: 4672.782 | T55: 5072.782 | U55: 5072.782 | V55: 5272.782 | W55: 5472.782 | X55: 5472.782 | Y55: 5672.782 | Z55: 5672.782 | AA55: 6472.782 | AB55: 6472.782 | AC55: 7672.782 | AD55: 8072.782 | AE55: 8472.782 | AF55: 8972.782 | AG55: 9572.782 | AH55: 9572.782 | AI55: 9572.782 | AJ55: 10172.782 | AK55: 10172.782 | AL55: 10372.782
... A62: Total | B62: MW | C62: 8037.2013 | D62: 8240.906 | E62: 9007.7593 | F62: 10130.648 | G62: 10710.483 | H62: 10914.455 | I62: 10538.883 | J62: 10801.924 | K62: 11088.384 | L62: 11507.927 | M62: 10641.114 | N62: 11487.96 | O62: 16218.455 | P62: 17247.164 | Q62: 17596.883 | R62: 18879.742 | S62: 21767.995 | T62: 23093.197 | U62: 24310.668 | V62: 24919.281 | W62: 25302.29 | X62: 25302.538 | Y62: 26267.258 | Z62: 27172.739 | AA62: 28298.096 | AB62: 29002.784 | AC62: 30059.047 | AD62: 30737.493 | AE62: 31611.717 | AF62: 32388.703 | AG62: 33667.923 | AH62: 33944.104 | AI62: 34619.054 | AJ62: 35894.136 | AK62: 36368.445 | AL62: 36846.696
A63: Queensland
A64: Black Coal | B64: MW | C64: 7483.14 | D64: 7483.14 | E64: 7483.14 | F64: 7483.14 | G64: 7483.14 | H64: 7483.14 | I64: 6846.14 | J64: 6846.14 | K64: 6846.14 | L64: 6846.14 | M64: 5300.54 | N64: 4656.54 | O64: 3596.12 | P64: 3596.12 | Q64: 3596.12 | R64: 3596.12 | S64: 3596.12 | T64: 2919.08 | U64: 2586.93 | V64: 2254.78 | W64: 1922.63 | X64: 1590.48 | Y64: 1590.48 | Z64: 1590.48 | AA64: 1590.48 | AB64: 1590.48 | AC64: 0 | AD64: 0 | AE64: 0 | AF64: 0 | AG64: 0 | AH64: 0 | AI64: 0 | AJ64: 0 | AK64: 0 | AL64: 0
A65: Brown Coal | B65: MW | C65: 0 | D65: 0 | E65: 0 | F65: 0 | G65: 0 | H65: 0 | I65: 0 | J65: 0 | K65: 0 | L65: 0 | M65: 0 | N65: 0 | O65: 0 | P65: 0 | Q65: 0 | R65: 0 | S65: 0 | T65: 0 | U65: 0 | V65: 0 | W65: 0 | X65: 0 | Y65: 0 | Z65: 0 | AA65: 0 | AB65: 0 | AC65: 0 | AD65: 0 | AE65: 0 | AF65: 0 | AG65: 0 | AH65: 0 | AI65: 0 | AJ65: 0 | AK65: 0 | AL65: 0
A66: Hydrogen ready | B66: MW | C66: 0 | D66: 0 | E66: 0 | F66: 0 | G66: 862.8 | H66: 862.8 | I66: 862.8 | J66: 862.8 | K66: 862.8 | L66: 862.8 | M66: 1242.8 | N66: 1622.8 | O66: 2169 | P66: 2651.8 | Q66: 2651.8 | R66: 2844.92 | S66: 2844.92 | T66: 2844.92 | U66: 3018.12 | V66: 3183.92 | W66: 3183.92 | X66: 3183.92 | Y66: 3605.52 | Z66: 4531.72 | AA66: 4696.42 | AB66: 4696.42 | AC66: 4861.12 | AD66: 4861.12 | AE66: 4861.12 | AF66: 4861.12 | AG66: 4861.12 | AH66: 4861.12 | AI66: 4861.12 | AJ66: 4861.12 | AK66: 4861.12 | AL66: 4861.12
A67: Gas GT | B67: MW | C67: 1923.19 | D67: 1923.19 | E67: 1923.19 | F67: 1923.19 | G67: 1889.36 | H67: 1855.53 | I67: 1855.53 | J67: 1855.53 | K67: 1564.99 | L67: 1564.99 | M67: 1528.17 | N67: 1528.17 | O67: 1528.17 | P67: 1528.17 | Q67: 1528.17 | R67: 1528.17 | S67: 1528.17 | T67: 1528.17 | U67: 1528.17 | V67: 1528.17 | W67: 1401.8 | X67: 1401.8 | Y67: 885.38 | Z67: 885.38 | AA67: 885.38 | AB67: 885.38 | AC67: 547.08 | AD67: 547.08 | AE67: 547.08 | AF67: 547.08 | AG67: 547.08 | AH67: 547.08 | AI67: 45.6 | AJ67: 45.6 | AK67: 45.6 | AL67: 45.6
A68: Gas CCGT & Cogen | B68: MW | C68: 1509.93 | D68: 1509.93 | E68: 1509.93 | F68: 1151.03 | G68: 1151.03 | H68: 1151.03 | I68: 1151.03 | J68: 1151.03 | K68: 1151.03 | L68: 1151.03 | M68: 1151.03 | N68: 1151.03 | O68: 1201.03 | P68: 1201.03 | Q68: 1201.03 | R68: 1201.03 | S68: 1059.91 | T68: 1059.91 | U68: 1059.91 | V68: 1059.91 | W68: 1059.91 | X68: 442.51 | Y68: 206.8 | Z68: 206.8 | AA68: 206.8 | AB68: 206.8 | AC68: 206.8 | AD68: 206.8 | AE68: 206.8 | AF68: 206.8 | AG68: 206.8 | AH68: 206.8 | AI68: 206.8 | AJ68: 206.8 | AK68: 206.8 | AL68: 206.8
A69: Gas CC CCS | B69: MW | C69: 0 | D69: 0 | E69: 0 | F69: 0 | G69: 0 | H69: 0 | I69: 0 | J69: 0 | K69: 0 | L69: 0 | M69: 0 | N69: 0 | O69: 0 | P69: 0 | Q69: 0 | R69: 0 | S69: 0 | T69: 0 | U69: 0 | V69: 0 | W69: 0 | X69: 0 | Y69: 0 | Z69: 0 | AA69: 0 | AB69: 0 | AC69: 0 | AD69: 0 | AE69: 0 | AF69: 0 | AG69: 0 | AH69: 0 | AI69: 0 | AJ69: 0 | AK69: 0 | AL69: 0
A70: Gas Steam | B70: MW | C70: 0 | D70: 0 | E70: 0 | F70: 0 | G70: 0 | H70: 0 | I70: 0 | J70: 0 | K70: 0 | L70: 0 | M70: 0 | N70: 0 | O70: 0 | P70: 0 | Q70: 0 | R70: 0 | S70: 0 | T70: 0 | U70: 0 | V70: 0 | W70: 0 | X70: 0 | Y70: 0 | Z70: 0 | AA70: 0 | AB70: 0 | AC70: 0 | AD70: 0 | AE70: 0 | AF70: 0 | AG70: 0 | AH70: 0 | AI70: 0 | AJ70: 0 | AK70: 0 | AL70: 0
A71: Distillate | B71: MW | C71: 0 | D71: 0 | E71: 0 | F71: 0 | G71: 0 | H71: 0 | I71: 0 | J71: 0 | K71: 0 | L71: 0 | M71: 0 | N71: 0 | O71: 0 | P71: 0 | Q71: 0 | R71: 0 | S71: 0 | T71: 0 | U71: 0 | V71: 0 | W71: 0 | X71: 0 | Y71: 0 | Z71: 0 | AA71: 0 | AB71: 0 | AC71: 0 | AD71: 0 | AE71: 0 | AF71: 0 | AG71: 0 | AH71: 0 | AI71: 0 | AJ71: 0 | AK71: 0 | AL71: 0
A72: Hydro | B72: MW | C72: 256.99 | D72: 256.99 | E72: 256.99 | F72: 256.99 | G72: 256.99 | H72: 256.99 | I72: 256.99 | J72: 256.99 | K72: 256.99 | L72: 256.99 | M72: 256.99 | N72: 256.99 | O72: 256.99 | P72: 256.99 | Q72: 256.99 | R72: 256.99 | S72: 256.99 | T72: 256.99 | U72: 256.99 | V72: 256.99 | W72: 256.99 | X72: 256.99 | Y72: 256.99 | Z72: 256.99 | AA72: 256.99 | AB72: 256.99 | AC72: 256.99 | AD72: 256.99 | AE72: 256.99 | AF72: 256.99 | AG72: 256.99 | AH72: 256.99 | AI72: 256.99 | AJ72: 256.99 | AK72: 256.99 | AL72: 256.99
A73: Wind | B73: MW | C73: 2716.64 | D73: 2716.64 | E73: 2716.64 | F73: 3074.94 | G73: 3482.94 | H73: 3482.94 | I73: 3482.94 | J73: 3482.94 | K73: 3482.94 | L73: 4032.94 | M73: 4982.94 | N73: 5382.94 | O73: 5982.94 | P73: 6382.94 | Q73: 6382.94 | R73: 7182.94 | S73: 8582.94 | T73: 9182.94 | U73: 11182.94 | V73: 11814.94 | W73: 12414.94 | X73: 12414.94 | Y73: 12614.94 | Z73: 12814.94 | AA73: 12814.94 | AB73: 13414.94 | AC73: 14214.94 | AD73: 14214.94 | AE73: 14414.94 | AF73: 14814.94 | AG73: 15214.94 | AH73: 15214.94 | AI73: 15614.94 | AJ73: 17014.94 | AK73: 18014.94 | AL73: 18014.94
A74: Biomass | B74: MW | C74: 532.545 | D74: 532.545 | E74: 532.545 | F74: 532.545 | G74: 532.545 | H74: 532.545 | I74: 532.545 | J74: 532.545 | K74: 532.545 | L74: 532.545 | M74: 532.545 | N74: 532.545 | O74: 532.545 | P74: 532.545 | Q74: 532.545 | R74: 532.545 | S74: 532.545 | T74: 532.545 | U74: 532.545 | V74: 532.545 | W74: 532.545 | X74: 532.545 | Y74: 532.545 | Z74: 532.545 | AA74: 532.545 | AB74: 532.545 | AC74: 532.545 | AD74: 532.545 | AE74: 532.545 | AF74: 532.545 | AG74: 532.545 | AH74: 532.545 | AI74: 532.545 | AJ74: 532.545 | AK74: 532.545 | AL74: 532.545
A75: Solar | B75: MW | C75: 3547.792 | D75: 4424.512 | E75: 5743.312 | F75: 6157.112 | G75: 6557.112 | H75: 6557.112 | I75: 6557.112 | J75: 6557.112 | K75: 6557.112 | L75: 6557.112 | M75: 6812.112 | N75: 6812.112 | O75: 8408.112 | P75: 9418.112 | Q75: 9418.112 | R75: 11021.112 | S75: 13221.112 | T75: 13621.112 | U75: 13621.112 | V75: 13821.112 | W75: 14271.112 | X75: 15471.112 | Y75: 16671.112 | Z75: 16671.112 | AA75: 17471.112 | AB75: 18221.112 | AC75: 20671.112 | AD75: 21771.112 | AE75: 22771.112 | AF75: 23271.112 | AG75: 24521.112 | AH75: 24521.112 | AI75: 24521.112 | AJ75: 25521.112 | AK75: 25721.112 | AL75: 26121.112
... A82: Total | B82: MW | C82: 27503.017 | D82: 30013.947 | E82: 32338.647 | F82: 35071.847 | G82: 38080.707 | H82: 39032.787 | I82: 41354.487 | J82: 44261.587 | K82: 45221.537 | L82: 46744.747 | M82: 47679.727 | N82: 48765.627 | O82: 54476.407 | P82: 57606.807 | Q82: 58850.317 | R82: 62605.927 | S82: 67150.807 | T82: 68697.867 | U82: 71854.517 | V82: 73802.967 | W82: 75581.447 | X82: 77082.097 | Y82: 79441.667 | Z82: 81790.067 | AA82: 83972.767 | AB82: 86460.967 | AC82: 88865.787 | AD82: 91004.927 | AE82: 93227.84 | AF82: 95161.061 | AG82: 97852.739 | AH82: 98883.365 | AI82: 99808.184 | AJ82: 103235.14 | AK82: 105459.48 | AL82: 106898.6
A83: New South Wales
A84: Black Coal | B84: MW | C84: 7772.8 | D84: 6419.2 | E84: 6419.2 | F84: 6419.2 | G84: 5065.6 | H84: 5065.6 | I84: 5065.6 | J84: 3824.8 | K84: 2584 | L84: 1330 | M84: 1330 | N84: 1330 | O84: 1330 | P84: 1330 | Q84: 1330 | R84: 1330 | S84: 0 | T84: 0 | U84: 0 | V84: 0 | W84: 0 | X84: 0 | Y84: 0 | Z84: 0 | AA84: 0 | AB84: 0 | AC84: 0 | AD84: 0 | AE84: 0 | AF84: 0 | AG84: 0 | AH84: 0 | AI84: 0 | AJ84: 0 | AK84: 0 | AL84: 0
A85: Brown Coal | B85: MW | C85: 0 | D85: 0 | E85: 0 | F85: 0 | G85: 0 | H85: 0 | I85: 0 | J85: 0 | K85: 0 | L85: 0 | M85: 0 | N85: 0 | O85: 0 | P85: 0 | Q85: 0 | R85: 0 | S85: 0 | T85: 0 | U85: 0 | V85: 0 | W85: 0 | X85: 0 | Y85: 0 | Z85: 0 | AA85: 0 | AB85: 0 | AC85: 0 | AD85: 0 | AE85: 0 | AF85: 0 | AG85: 0 | AH85: 0 | AI85: 0 | AJ85: 0 | AK85: 0 | AL85: 0
A86: Hydrogen ready | B86: MW | C86: 0 | D86: 0 | E86: 0 | F86: 0 | G86: 0 | H86: 0 | I86: 0 | J86: 0 | K86: 0 | L86: 0 | M86: 827.5 | N86: 1373.7 | O86: 1373.7 | P86: 1373.7 | Q86: 1373.7 | R86: 1373.7 | S86: 1373.7 | T86: 1373.7 | U86: 1373.7 | V86: 1936.3 | W86: 1936.3 | X86: 1936.3 | Y86: 1936.3 | Z86: 2217.6 | AA86: 2217.6 | AB86: 2217.6 | AC86: 2217.6 | AD86: 2217.6 | AE86: 2217.6 | AF86: 2217.6 | AG86: 2217.6 | AH86: 2217.6 | AI86: 2217.6 | AJ86: 2217.6 | AK86: 2217.6 | AL86: 2217.6
A87: Gas GT | B87: MW | C87: 2611.87 | D87: 2611.87 | E87: 2611.87 | F87: 2611.87 | G87: 2611.87 | H87: 2611.87 | I87: 2611.87 | J87: 2611.87 | K87: 2570.08 | L87: 2570.08 | M87: 2389.98 | N87: 2570.08 | O87: 2570.08 | P87: 2570.08 | Q87: 2570.08 | R87: 2570.08 | S87: 2447.08 | T87: 2447.08 | U87: 2728.38 | V87: 2728.38 | W87: 2067.7 | X87: 2067.7 | Y87: 2067.7 | Z87: 2067.7 | AA87: 2067.7 | AB87: 2067.7 | AC87: 2067.7 | AD87: 2067.7 | AE87: 2067.7 | AF87: 2067.7 | AG87: 2067.7 | AH87: 2067.7 | AI87: 2067.7 | AJ87: 2067.7 | AK87: 2067.7 | AL87: 2349
A88: Gas CCGT & Cogen | B88: MW | C88: 421.95 | D88: 421.95 | E88: 421.95 | F88: 421.95 | G88: 421.95 | H88: 421.95 | I88: 421.95 | J88: 968.15 | K88: 968.15 | L88: 968.15 | M88: 968.15 | N88: 968.15 | O88: 968.15 | P88: 858.91 | Q88: 1405.11 | R88: 1405.11 | S88: 1405.11 | T88: 1405.11 | U88: 1405.11 | V88: 1092.4 | W88: 1092.4 | X88: 1092.4 | Y88: 1092.4 | Z88: 1092.4 | AA88: 1092.4 | AB88: 1092.4 | AC88: 1092.4 | AD88: 1092.4 | AE88: 1092.4 | AF88: 1092.4 | AG88: 1092.4 | AH88: 1092.4 | AI88: 1092.4 | AJ88: 1092.4 | AK88: 1092.4 | AL88: 1092.4
A89: Gas CC CCS | B89: MW | C89: 0 | D89: 0 | E89: 0 | F89: 0 | G89: 0 | H89: 0 | I89: 0 | J89: 0 | K89: 0 | L89: 0 | M89: 0 | N89: 0 | O89: 0 | P89: 0 | Q89: 0 | R89: 0 | S89: 0 | T89: 0 | U89: 0 | V89: 0 | W89: 0 | X89: 0 | Y89: 0 | Z89: 0 | AA89: 0 | AB89: 0 | AC89: 0 | AD89: 0 | AE89: 0 | AF89: 0 | AG89: 0 | AH89: 0 | AI89: 0 | AJ89: 0 | AK89: 0 | AL89: 0
A90: Gas Steam | B90: MW | C90: 0 | D90: 0 | E90: 0 | F90: 0 | G90: 0 | H90: 0 | I90: 0 | J90: 0 | K90: 0 | L90: 0 | M90: 0 | N90: 0 | O90: 0 | P90: 0 | Q90: 0 | R90: 0 | S90: 0 | T90: 0 | U90: 0 | V90: 0 | W90: 0 | X90: 0 | Y90: 0 | Z90: 0 | AA90: 0 | AB90: 0 | AC90: 0 | AD90: 0 | AE90: 0 | AF90: 0 | AG90: 0 | AH90: 0 | AI90: 0 | AJ90: 0 | AK90: 0 | AL90: 0
A91: Distillate | B91: MW | C91: 0 | D91: 0 | E91: 0 | F91: 0 | G91: 0 | H91: 0 | I91: 0 | J91: 0 | K91: 0 | L91: 0 | M91: 0 | N91: 0 | O91: 0 | P91: 0 | Q91: 0 | R91: 0 | S91: 0 | T91: 0 | U91: 0 | V91: 0 | W91: 0 | X91: 0 | Y91: 0 | Z91: 0 | AA91: 0 | AB91: 0 | AC91: 0 | AD91: 0 | AE91: 0 | AF91: 0 | AG91: 0 | AH91: 0 | AI91: 0 | AJ91: 0 | AK91: 0 | AL91: 0
A92: Hydro | B92: MW | C92: 869.88 | D92: 869.88 | E92: 869.88 | F92: 869.88 | G92: 869.88 | H92: 869.88 | I92: 869.88 | J92: 869.88 | K92: 869.88 | L92: 869.88 | M92: 869.88 | N92: 869.88 | O92: 869.88 | P92: 869.88 | Q92: 869.88 | R92: 869.88 | S92: 869.88 | T92: 869.88 | U92: 869.88 | V92: 869.88 | W92: 869.88 | X92: 869.88 | Y92: 869.88 | Z92: 869.88 | AA92: 869.88 | AB92: 869.88 | AC92: 869.88 | AD92: 869.88 | AE92: 869.88 | AF92: 869.88 | AG92: 869.88 | AH92: 869.88 | AI92: 869.88 | AJ92: 869.88 | AK92: 869.88 | AL92: 869.88
A93: Wind | B93: MW | C93: 2830.06 | D93: 2830.06 | E93: 3700.76 | F93: 4989.66 | G93: 6259.66 | H93: 7439.66 | I93: 8758.66 | J93: 8988.66 | K93: 8988.66 | L93: 9188.66 | M93: 10188.66 | N93: 10888.66 | O93: 11888.66 | P93: 12688.66 | Q93: 12688.66 | R93: 12688.66 | S93: 13288.66 | T93: 13288.66 | U93: 14188.66 | V93: 14788.66 | W93: 14788.66 | X93: 14788.66 | Y93: 14788.66 | Z93: 14788.66 | AA93: 14788.66 | AB93: 14788.66 | AC93: 15188.66 | AD93: 15188.66 | AE93: 16188.66 | AF93: 16188.66 | AG93: 16588.66 | AH93: 16588.66 | AI93: 16788.66 | AJ93: 16788.66 | AK93: 17388.66 | AL93: 17388.66
A94: Biomass | B94: MW | C94: 194.669 | D94: 194.669 | E94: 194.669 | F94: 194.669 | G94: 194.669 | H94: 194.669 | I94: 194.669 | J94: 194.669 | K94: 194.669 | L94: 194.669 | M94: 194.669 | N94: 194.669 | O94: 194.669 | P94: 199.669 | Q94: 199.669 | R94: 199.669 | S94: 199.669 | T94: 199.669 | U94: 199.669 | V94: 199.669 | W94: 199.669 | X94: 199.669 | Y94: 199.669 | Z94: 199.669 | AA94: 199.669 | AB94: 199.669 | AC94: 199.669 | AD94: 199.669 | AE94: 199.669 | AF94: 199.669 | AG94: 199.669 | AH94: 199.669 | AI94: 199.669 | AJ94: 199.669 | AK94: 199.669 | AL94: 199.669
A95: Solar | B95: MW | C95: 4598.738 | D95: 5997.538 | E95: 6122.538 | F95: 6675.538 | G95: 7430.538 | H95: 7485.538 | I95: 7485.538 | J95: 7485.538 | K95: 7485.538 | L95: 7485.538 | M95: 7485.538 | N95: 7485.538 | O95: 7485.538 | P95: 7485.538 | Q95: 7485.538 | R95: 7685.538 | S95: 8076.538 | T95: 8676.538 | U95: 9056.538 | V95: 9256.538 | W95: 9456.538 | X95: 10256.538 | Y95: 10256.538 | Z95: 10256.538 | AA95: 10456.538 | AB95: 10906.538 | AC95: 10906.538 | AD95: 11506.538 | AE95: 12506.538 | AF95: 12506.538 | AG95: 12706.538 | AH95: 12906.538 | AI95: 13275.538 | AJ95: 13275.538 | AK95: 13675.538 | AL95: 13961.538
... A102: Total | B102: MW | C102: 31329.267 | D102: 33934.367 | E102: 36846.667 | F102: 41117.367 | G102: 43663.367 | H102: 48580.567 | I102: 51693.867 | J102: 52434.467 | K102: 52840.777 | L102: 52982.477 | M102: 55814.177 | N102: 58458.477 | O102: 60889.377 | P102: 63211.937 | Q102: 65337.437 | R102: 67087.437 | S102: 68278.937 | T102: 70482.537 | U102: 74662.237 | V102: 77279.027 | W102: 78794.147 | X102: 81257.647 | Y102: 82952.747 | Z102: 84896.147 | AA102: 86783.147 | AB102: 88797.347 | AC102: 90511.147 | AD102: 92421.847 | AE102: 96323.047 | AF102: 97631.947 | AG102: 99579.221 | AH102: 101166.06 | AI102: 103162.66 | AJ102: 104632.29 | AK102: 107145.24 | AL102: 109270.15
A103: Victoria
A104: Black Coal | B104: MW | C104: 0 | D104: 0 | E104: 0 | F104: 0 | G104: 0 | H104: 0 | I104: 0 | J104: 0 | K104: 0 | L104: 0 | M104: 0 | N104: 0 | O104: 0 | P104: 0 | Q104: 0 | R104: 0 | S104: 0 | T104: 0 | U104: 0 | V104: 0 | W104: 0 | X104: 0 | Y104: 0 | Z104: 0 | AA104: 0 | AB104: 0 | AC104: 0 | AD104: 0 | AE104: 0 | AF104: 0 | AG104: 0 | AH104: 0 | AI104: 0 | AJ104: 0 | AK104: 0 | AL104: 0
A105: Brown Coal | B105: MW | C105: 4390.72 | D105: 4390.72 | E105: 4390.72 | F105: 4390.72 | G105: 4390.72 | H105: 3015.52 | I105: 3015.52 | J105: 3015.52 | K105: 3015.52 | L105: 3015.52 | M105: 2507.74 | N105: 984.4 | O105: 984.4 | P105: 984.4 | Q105: 984.4 | R105: 984.4 | S105: 984.4 | T105: 984.4 | U105: 984.4 | V105: 984.4 | W105: 984.4 | X105: 984.4 | Y105: 984.4 | Z105: 0 | AA105: 0 | AB105: 0 | AC105: 0 | AD105: 0 | AE105: 0 | AF105: 0 | AG105: 0 | AH105: 0 | AI105: 0 | AJ105: 0 | AK105: 0 | AL105: 0
A106: Hydrogen ready | B106: MW | C106: 0 | D106: 0 | E106: 0 | F106: 0 | G106: 0 | H106: 0 | I106: 0 | J106: 0 | K106: 0 | L106: 0 | M106: 0 | N106: 0 | O106: 0 | P106: 0 | Q106: 0 | R106: 0 | S106: 0 | T106: 0 | U106: 0 | V106: 0 | W106: 0 | X106: 0 | Y106: 281.3 | Z106: 281.3 | AA106: 281.3 | AB106: 281.3 | AC106: 281.3 | AD106: 281.3 | AE106: 281.3 | AF106: 281.3 | AG106: 281.3 | AH106: 281.3 | AI106: 718.26 | AJ106: 718.26 | AK106: 718.26 | AL106: 718.26
A107: Gas GT | B107: MW | C107: 1951.22 | D107: 1951.22 | E107: 1951.22 | F107: 1951.22 | G107: 1951.22 | H107: 1791.02 | I107: 1791.02 | J107: 1791.02 | K107: 1791.02 | L107: 1791.02 | M107: 1621.87 | N107: 1452.72 | O107: 1452.72 | P107: 1452.72 | Q107: 1452.72 | R107: 968.14 | S107: 968.14 | T107: 968.14 | U107: 884.56 | V107: 884.56 | W107: 884.56 | X107: 884.56 | Y107: 884.56 | Z107: 334.32 | AA107: 334.32 | AB107: 334.32 | AC107: 334.32 | AD107: 334.32 | AE107: 334.32 | AF107: 334.32 | AG107: 334.32 | AH107: 334.32 | AI107: 334.32 | AJ107: 334.32 | AK107: 334.32 | AL107: 615.62
A108: Gas CCGT & Cogen | B108: MW | C108: 21 | D108: 21 | E108: 21 | F108: 21 | G108: 21 | H108: 21 | I108: 21 | J108: 21 | K108: 21 | L108: 21 | M108: 21 | N108: 21 | O108: 21 | P108: 21 | Q108: 21 | R108: 21 | S108: 21 | T108: 21 | U108: 21 | V108: 21 | W108: 21 | X108: 21 | Y108: 567.2 | Z108: 567.2 | AA108: 567.2 | AB108: 567.2 | AC108: 567.2 | AD108: 567.2 | AE108: 567.2 | AF108: 567.2 | AG108: 567.2 | AH108: 567.2 | AI108: 567.2 | AJ108: 567.2 | AK108: 567.2 | AL108: 567.2
A109: Gas CC CCS | B109: MW | C109: 0 | D109: 0 | E109: 0 | F109: 0 | G109: 0 | H109: 0 | I109: 0 | J109: 0 | K109: 0 | L109: 0 | M109: 0 | N109: 0 | O109: 0 | P109: 0 | Q109: 0 | R109: 0 | S109: 0 | T109: 0 | U109: 0 | V109: 0 | W109: 0 | X109: 0 | Y109: 0 | Z109: 0 | AA109: 0 | AB109: 0 | AC109: 0 | AD109: 0 | AE109: 0 | AF109: 0 | AG109: 0 | AH109: 0 | AI109: 0 | AJ109: 0 | AK109: 0 | AL109: 0
A110: Gas Steam | B110: MW | C110: 484.5 | D110: 484.5 | E110: 484.5 | F110: 484.5 | G110: 484.5 | H110: 484.5 | I110: 484.5 | J110: 484.5 | K110: 484.5 | L110: 484.5 | M110: 484.5 | N110: 484.5 | O110: 484.5 | P110: 484.5 | Q110: 484.5 | R110: 0 | S110: 0 | T110: 0 | U110: 0 | V110: 0 | W110: 0 | X110: 0 | Y110: 0 | Z110: 0 | AA110: 0 | AB110: 0 | AC110: 0 | AD110: 0 | AE110: 0 | AF110: 0 | AG110: 0 | AH110: 0 | AI110: 0 | AJ110: 0 | AK110: 0 | AL110: 0
A111: Distillate | B111: MW | C111: 0 | D111: 0 | E111: 0 | F111: 0 | G111: 0 | H111: 0 | I111: 0 | J111: 0 | K111: 0 | L111: 0 | M111: 0 | N111: 0 | O111: 0 | P111: 0 | Q111: 0 | R111: 0 | S111: 0 | T111: 0 | U111: 0 | V111: 0 | W111: 0 | X111: 0 | Y111: 0 | Z111: 0 | AA111: 0 | AB111: 0 | AC111: 0 | AD111: 0 | AE111: 0 | AF111: 0 | AG111: 0 | AH111: 0 | AI111: 0 | AJ111: 0 | AK111: 0 | AL111: 0
A112: Hydro | B112: MW | C112: 2446.2264 | D112: 2446.2264 | E112: 2446.2264 | F112: 2446.2264 | G112: 2446.2264 | H112: 2446.2264 | I112: 2446.2264 | J112: 2446.2264 | K112: 2446.2264 | L112: 2446.2264 | M112: 2446.2264 | N112: 2446.2264 | O112: 2446.2264 | P112: 2446.2264 | Q112: 2446.2264 | R112: 2446.2264 | S112: 2446.2264 | T112: 2446.2264 | U112: 2446.2264 | V112: 2446.2264 | W112: 2446.2264 | X112: 2446.2264 | Y112: 2446.2264 | Z112: 2446.2264 | AA112: 2446.2264 | AB112: 2446.2264 | AC112: 2446.2264 | AD112: 2446.2264 | AE112: 2446.2264 | AF112: 2446.2264 | AG112: 2446.2264 | AH112: 2446.2264 | AI112: 2446.2264 | AJ112: 2446.2264 | AK112: 2446.2264 | AL112: 2446.2264
A113: Wind | B113: MW | C113: 4689.238 | D113: 5445.638 | E113: 6002.638 | F113: 6434.638 | G113: 7031.838 | H113: 7631.838 | I113: 8331.838 | J113: 9255.038 | K113: 11155.038 | L113: 13755.038 | M113: 15455.038 | N113: 15705.038 | O113: 16955.038 | P113: 18205.038 | Q113: 18705.038 | R113: 19455.038 | S113: 19455.038 | T113: 19455.038 | U113: 19455.038 | V113: 19485.038 | W113: 19485.038 | X113: 19485.038 | Y113: 19485.038 | Z113: 19485.038 | AA113: 19635.038 | AB113: 19644.038 | AC113: 19996.838 | AD113: 19996.838 | AE113: 19996.838 | AF113: 19996.838 | AG113: 19996.838 | AH113: 19996.838 | AI113: 19996.838 | AJ113: 19996.838 | AK113: 19996.838 | AL113: 19996.838
A114: Biomass | B114: MW | C114: 129.1065 | D114: 129.1065 | E114: 129.1065 | F114: 129.1065 | G114: 129.1065 | H114: 129.1065 | I114: 129.1065 | J114: 129.1065 | K114: 129.1065 | L114: 129.1065 | M114: 129.1065 | N114: 129.1065 | O114: 129.1065 | P114: 129.1065 | Q114: 129.1065 | R114: 129.1065 | S114: 129.1065 | T114: 129.1065 | U114: 129.1065 | V114: 129.1065 | W114: 129.1065 | X114: 129.1065 | Y114: 129.1065 | Z114: 129.1065 | AA114: 129.1065 | AB114: 129.1065 | AC114: 129.1065 | AD114: 129.1065 | AE114: 129.1065 | AF114: 129.1065 | AG114: 129.1065 | AH114: 129.1065 | AI114: 129.1065 | AJ114: 129.1065 | AK114: 129.1065 | AL114: 129.1065
A115: Solar | B115: MW | C115: 1494.8669 | D115: 1867.8669 | E115: 2395.7669 | F115: 2395.7669 | G115: 2520.7669 | H115: 2820.7669 | I115: 3060.7929 | J115: 3060.7929 | K115: 3060.7929 | L115: 3068.7929 | M115: 3173.5929 | N115: 3173.5929 | O115: 3173.5929 | P115: 3173.5929 | Q115: 3173.5929 | R115: 3173.5929 | S115: 3173.5929 | T115: 3173.5929 | U115: 3173.5929 | V115: 3173.5929 | W115: 3173.5929 | X115: 3373.5929 | Y115: 3373.5929 | Z115: 3373.5929 | AA115: 3373.5929 | AB115: 3450.6929 | AC115: 3450.6929 | AD115: 3450.6929 | AE115: 3450.6929 | AF115: 3450.6929 | AG115: 3450.6929 | AH115: 3450.6929 | AI115: 3450.6929 | AJ115: 3450.6929 | AK115: 3450.6929 | AL115: 3450.6929
... A122: Total | B122: MW | C122: 22963.878 | D122: 25897.278 | E122: 29431.378 | F122: 30927.378 | G122: 32623.678 | H122: 33759.278 | I122: 36728.804 | J122: 39506.904 | K122: 42555.104 | L122: 47456.104 | M122: 50081.374 | N122: 49769.884 | O122: 52337.584 | P122: 55081.284 | Q122: 57106.984 | R122: 58403.804 | S122: 59872.204 | T122: 61822.804 | U122: 63297.424 | V122: 65262.424 | W122: 66815.024 | X122: 68618.624 | Y122: 71137.324 | Z122: 71216.984 | AA122: 72964.184 | AB122: 74544.483 | AC122: 76203.084 | AD122: 77506.884 | AE122: 78796.783 | AF122: 80099.384 | AG122: 81443.343 | AH122: 82830.028 | AI122: 84697.793 | AJ122: 86174.184 | AK122: 87697.658 | AL122: 89551.07
A123: Tasmania
A124: Black Coal | B124: MW | C124: 0 | D124: 0 | E124: 0 | F124: 0 | G124: 0 | H124: 0 | I124: 0 | J124: 0 | K124: 0 | L124: 0 | M124: 0 | N124: 0 | O124: 0 | P124: 0 | Q124: 0 | R124: 0 | S124: 0 | T124: 0 | U124: 0 | V124: 0 | W124: 0 | X124: 0 | Y124: 0 | Z124: 0 | AA124: 0 | AB124: 0 | AC124: 0 | AD124: 0 | AE124: 0 | AF124: 0 | AG124: 0 | AH124: 0 | AI124: 0 | AJ124: 0 | AK124: 0 | AL124: 0
A125: Brown Coal | B125: MW | C125: 0 | D125: 0 | E125: 0 | F125: 0 | G125: 0 | H125: 0 | I125: 0 | J125: 0 | K125: 0 | L125: 0 | M125: 0 | N125: 0 | O125: 0 | P125: 0 | Q125: 0 | R125: 0 | S125: 0 | T125: 0 | U125: 0 | V125: 0 | W125: 0 | X125: 0 | Y125: 0 | Z125: 0 | AA125: 0 | AB125: 0 | AC125: 0 | AD125: 0 | AE125: 0 | AF125: 0 | AG125: 0 | AH125: 0 | AI125: 0 | AJ125: 0 | AK125: 0 | AL125: 0
A126: Hydrogen ready | B126: MW | C126: 0 | D126: 0 | E126: 0 | F126: 0 | G126: 0 | H126: 0 | I126: 0 | J126: 0 | K126: 0 | L126: 0 | M126: 0 | N126: 0 | O126: 0 | P126: 0 | Q126: 0 | R126: 0 | S126: 0 | T126: 0 | U126: 0 | V126: 0 | W126: 0 | X126: 0 | Y126: 0 | Z126: 0 | AA126: 0 | AB126: 0 | AC126: 0 | AD126: 0 | AE126: 0 | AF126: 0 | AG126: 0 | AH126: 0 | AI126: 0 | AJ126: 0 | AK126: 0 | AL126: 0
A127: Gas GT | B127: MW | C127: 177.11 | D127: 177.11 | E127: 177.11 | F127: 177.11 | G127: 177.11 | H127: 177.11 | I127: 177.11 | J127: 177.11 | K127: 177.11 | L127: 177.11 | M127: 177.11 | N127: 177.11 | O127: 177.11 | P127: 177.11 | Q127: 177.11 | R127: 177.11 | S127: 177.11 | T127: 177.11 | U127: 177.11 | V127: 177.11 | W127: 177.11 | X127: 177.11 | Y127: 177.11 | Z127: 177.11 | AA127: 177.11 | AB127: 177.11 | AC127: 177.11 | AD127: 177.11 | AE127: 177.11 | AF127: 177.11 | AG127: 177.11 | AH127: 177.11 | AI127: 177.11 | AJ127: 177.11 | AK127: 177.11 | AL127: 177.11
A128: Gas CCGT & Cogen | B128: MW | C128: 196.91 | D128: 196.91 | E128: 196.91 | F128: 196.91 | G128: 196.91 | H128: 196.91 | I128: 196.91 | J128: 196.91 | K128: 196.91 | L128: 196.91 | M128: 196.91 | N128: 196.91 | O128: 0 | P128: 0 | Q128: 0 | R128: 0 | S128: 0 | T128: 0 | U128: 0 | V128: 0 | W128: 0 | X128: 0 | Y128: 0 | Z128: 0 | AA128: 0 | AB128: 0 | AC128: 0 | AD128: 0 | AE128: 0 | AF128: 0 | AG128: 0 | AH128: 0 | AI128: 0 | AJ128: 0 | AK128: 0 | AL128: 0
A129: Gas CC CCS | B129: MW | C129: 0 | D129: 0 | E129: 0 | F129: 0 | G129: 0 | H129: 0 | I129: 0 | J129: 0 | K129: 0 | L129: 0 | M129: 0 | N129: 0 | O129: 0 | P129: 0 | Q129: 0 | R129: 0 | S129: 0 | T129: 0 | U129: 0 | V129: 0 | W129: 0 | X129: 0 | Y129: 0 | Z129: 0 | AA129: 0 | AB129: 0 | AC129: 0 | AD129: 0 | AE129: 0 | AF129: 0 | AG129: 0 | AH129: 0 | AI129: 0 | AJ129: 0 | AK129: 0 | AL129: 0
A130: Gas Steam | B130: MW | C130: 0 | D130: 0 | E130: 0 | F130: 0 | G130: 0 | H130: 0 | I130: 0 | J130: 0 | K130: 0 | L130: 0 | M130: 0 | N130: 0 | O130: 0 | P130: 0 | Q130: 0 | R130: 0 | S130: 0 | T130: 0 | U130: 0 | V130: 0 | W130: 0 | X130: 0 | Y130: 0 | Z130: 0 | AA130: 0 | AB130: 0 | AC130: 0 | AD130: 0 | AE130: 0 | AF130: 0 | AG130: 0 | AH130: 0 | AI130: 0 | AJ130: 0 | AK130: 0 | AL130: 0
A131: Distillate | B131: MW | C131: 0 | D131: 0 | E131: 0 | F131: 0 | G131: 0 | H131: 0 | I131: 0 | J131: 0 | K131: 0 | L131: 0 | M131: 0 | N131: 0 | O131: 0 | P131: 0 | Q131: 0 | R131: 0 | S131: 0 | T131: 0 | U131: 0 | V131: 0 | W131: 0 | X131: 0 | Y131: 0 | Z131: 0 | AA131: 0 | AB131: 0 | AC131: 0 | AD131: 0 | AE131: 0 | AF131: 0 | AG131: 0 | AH131: 0 | AI131: 0 | AJ131: 0 | AK131: 0 | AL131: 0
A132: Hydro | B132: MW | C132: 2529.2038 | D132: 2529.2038 | E132: 2529.2038 | F132: 2529.2038 | G132: 2529.2038 | H132: 2529.2038 | I132: 2529.2038 | J132: 2529.2038 | K132: 2529.2038 | L132: 2529.2038 | M132: 2529.2038 | N132: 2529.2038 | O132: 2529.2038 | P132: 2529.2038 | Q132: 2531.2037 | R132: 2531.2037 | S132: 2531.2037 | T132: 2531.2037 | U132: 2531.2037 | V132: 2531.2037 | W132: 2531.2037 | X132: 2531.2037 | Y132: 2531.2037 | Z132: 2531.2037 | AA132: 2531.2037 | AB132: 2531.2037 | AC132: 2531.2037 | AD132: 2531.2037 | AE132: 2531.2037 | AF132: 2531.2037 | AG132: 2531.2037 | AH132: 2531.2037 | AI132: 2531.2037 | AJ132: 2531.2037 | AK132: 2531.2037 | AL132: 2531.2037
A133: Wind | B133: MW | C133: 567.703 | D133: 567.703 | E133: 567.703 | F133: 567.703 | G133: 767.703 | H133: 767.703 | I133: 767.703 | J133: 767.703 | K133: 767.703 | L133: 767.703 | M133: 967.703 | N133: 967.703 | O133: 967.703 | P133: 967.703 | Q133: 967.703 | R133: 967.703 | S133: 967.703 | T133: 967.703 | U133: 967.703 | V133: 967.703 | W133: 967.703 | X133: 967.703 | Y133: 967.703 | Z133: 967.703 | AA133: 967.703 | AB133: 967.703 | AC133: 1167.703 | AD133: 1167.703 | AE133: 1167.703 | AF133: 1167.703 | AG133: 1367.703 | AH133: 1667.703 | AI133: 1667.703 | AJ133: 1667.703 | AK133: 1667.703 | AL133: 1667.703
A134: Biomass | B134: MW | C134: 5.03011 | D134: 5.03011 | E134: 5.03011 | F134: 5.03011 | G134: 5.03011 | H134: 5.03011 | I134: 5.03011 | J134: 5.03011 | K134: 5.03011 | L134: 5.03011 | M134: 5.03011 | N134: 5.03011 | O134: 5.03011 | P134: 5.03011 | Q134: 10.03011 | R134: 10.03011 | S134: 10.03011 | T134: 10.03011 | U134: 10.03011 | V134: 10.03011 | W134: 10.03011 | X134: 10.03011 | Y134: 10.03011 | Z134: 10.03011 | AA134: 10.03011 | AB134: 10.03011 | AC134: 10.03011 | AD134: 10.03011 | AE134: 10.03011 | AF134: 10.03011 | AG134: 10.03011 | AH134: 10.03011 | AI134: 10.03011 | AJ134: 10.03011 | AK134: 10.03011 | AL134: 10.03011
A135: Solar | B135: MW | C135: 0.096 | D135: 0.096 | E135: 0.096 | F135: 0.096 | G135: 0.096 | H135: 0.096 | I135: 0.096 | J135: 0.096 | K135: 0.096 | L135: 0.096 | M135: 0.096 | N135: 0.096 | O135: 0.096 | P135: 0.096 | Q135: 0.096 | R135: 0.096 | S135: 0.096 | T135: 0.096 | U135: 0.096 | V135: 0.096 | W135: 0.096 | X135: 0.096 | Y135: 0.096 | Z135: 0.096 | AA135: 0.096 | AB135: 0.096 | AC135: 0.096 | AD135: 0.096 | AE135: 0.096 | AF135: 0.096 | AG135: 0.096 | AH135: 0.096 | AI135: 0.096 | AJ135: 0.096 | AK135: 0.096 | AL135: 0.096
... A139: Pumped Hydro | B139: MW | C139: 0 | D139: 0 | E139: 0 | F139: 0 | G139: 0 | H139: 0 | I139: 0 | J139: 0 | K139: 0 | L139: 0 | M139: 0 | N139: 0 | O139: 0 | P139: 0 | Q139: 0 | R139: 0 | S139: 0 | T139: 0 | U139: 0 | V139: 0 | W139: 0 | X139: 0 | Y139: 0 | Z139: 0 | AA139: 0 | AB139: 0 | AC139: 0 | AD139: 0 | AE139: 0 | AF139: 0 | AG139: 0 | AH139: 0 | AI139: 0 | AJ139: 0 | AK139: 0 | AL139: 0
...

Sheet NEM Generation
A1: Generation Sent Out
A2: Financial Year | C2: 2025 | D2: 2026 | E2: 2027 | F2: 2028 | G2: 2029 | H2: 2030 | I2: 2031 | J2: 2032 | K2: 2033 | L2: 2034 | M2: 2035 | N2: 2036 | O2: 2037 | P2: 2038 | Q2: 2039 | R2: 2040 | S2: 2041 | T2: 2042 | U2: 2043 | V2: 2044 | W2: 2045 | X2: 2046 | Y2: 2047 | Z2: 2048 | AA2: 2049 | AB2: 2050 | AC2: 2051 | AD2: 2052 | AE2: 2053 | AF2: 2054 | AG2: 2055 | AH2: 2056 | AI2: 2057 | AJ2: 2058 | AK2: 2059 | AL2: 2060
A3: Queensland South
A4: Black Coal | B4: GWh | C4: 18469.25 | D4: 18684.61 | E4: 17857.69 | F4: 16646.08 | G4: 15655.86 | H4: 15586.1 | I4: 16852.05 | J4: 17991.35 | K4: 19117.44 | L4: 19283.56 | M4: 19450.33 | N4: 17698.57 | O4: 12848.64 | P4: 9364.05 | Q4: 9439.3398 | R4: 9331.5701 | S4: 8945.04 | T4: 7060.6299 | U4: 5063.51 | V4: 5075.8301 | W4: 5069.0601 | X4: 4920.4299 | Y4: 4823.72 | Z4: 4921.74 | AA4: 4943.99 | AB4: 4889.6001 | AC4: 1665.5101 | AD4: 0 | AE4: 0 | AF4: 0 | AG4: 0 | AH4: 0 | AI4: 0 | AJ4: 0 | AK4: 0 | AL4: 0
A5: Brown Coal | B5: GWh | C5: 0 | D5: 0 | E5: 0 | F5: 0 | G5: 0 | H5: 0 | I5: 0 | J5: 0 | K5: 0 | L5: 0 | M5: 0 | N5: 0 | O5: 0 | P5: 0 | Q5: 0 | R5: 0 | S5: 0 | T5: 0 | U5: 0 | V5: 0 | W5: 0 | X5: 0 | Y5: 0 | Z5: 0 | AA5: 0 | AB5: 0 | AC5: 0 | AD5: 0 | AE5: 0 | AF5: 0 | AG5: 0 | AH5: 0 | AI5: 0 | AJ5: 0 | AK5: 0 | AL5: 0
A6: Hydrogen ready | B6: GWh | C6: 0 | D6: 0 | E6: 0 | F6: 0 | G6: 634.79999 | H6: 584.90002 | I6: 893.28003 | J6: 1287.36 | K6: 1588 | L6: 1805.59 | M6: 257.04 | N6: 282.69999 | O6: 301.7 | P6: 345.63001 | Q6: 327.82999 | R6: 328.6 | S6: 320.42 | T6: 334.52001 | U6: 260.52001 | V6: 423.31 | W6: 514.64001 | X6: 585.82999 | Y6: 941.85001 | Z6: 1602.08 | AA6: 1965.08 | AB6: 1899.87 | AC6: 2230.41 | AD6: 2854.34 | AE6: 3111.8599 | AF6: 2961.4999 | AG6: 2921.4001 | AH6: 3051.9101 | AI6: 3410.95 | AJ6: 3380.3001 | AK6: 3300.4301 | AL6: 3399.6498
A7: Gas GT | B7: GWh | C7: 3.4899999 | D7: 7.7299998 | E7: 17.79 | F7: 26.85 | G7: 13.72 | H7: 6.8800001 | I7: 12.99 | J7: 37.58 | K7: 61.76 | L7: 97.34 | M7: 484.15001 | N7: 535.3 | O7: 600.18002 | P7: 709.08001 | Q7: 673.04001 | R7: 749.62001 | S7: 774.14002 | T7: 843.98002 | U7: 894.25001 | V7: 980.43001 | W7: 1034.73 | X7: 1351.16 | Y7: 687.59997 | Z7: 730.18997 | AA7: 778.60999 | AB7: 738.12999 | AC7: 754.95002 | AD7: 839.97 | AE7: 834.18999 | AF7: 818.41001 | AG7: 804.89 | AH7: 809.47001 | AI7: 0 | AJ7: 0 | AK7: 0 | AL7: 0
A8: Gas CCGT & Cogen | B8: GWh | C8: 662.80002 | D8: 1044.1 | E8: 1269.17 | F8: 665.29 | G8: 259.82 | H8: 217.59 | I8: 370.91 | J8: 649.07999 | K8: 831.12 | L8: 1015.73 | M8: 2883.2 | N8: 3144.1 | O8: 3452.2 | P8: 3706.7201 | Q8: 3665.67 | R8: 3581.2599 | S8: 2776.3101 | T8: 2888.97 | U8: 3015.6201 | V8: 3073.6399 | W8: 3184.5 | X8: 240.89999 | Y8: 0 | Z8: 0 | AA8: 0 | AB8: 0 | AC8: 0 | AD8: 0 | AE8: 0 | AF8: 0 | AG8: 0 | AH8: 0 | AI8: 0 | AJ8: 0 | AK8: 0 | AL8: 0
A9: Gas CC CCS | B9: GWh | C9: 0 | D9: 0 | E9: 0 | F9: 0 | G9: 0 | H9: 0 | I9: 0 | J9: 0 | K9: 0 | L9: 0 | M9: 0 | N9: 0 | O9: 0 | P9: 0 | Q9: 0 | R9: 0 | S9: 0 | T9: 0 | U9: 0 | V9: 0 | W9: 0 | X9: 0 | Y9: 0 | Z9: 0 | AA9: 0 | AB9: 0 | AC9: 0 | AD9: 0 | AE9: 0 | AF9: 0 | AG9: 0 | AH9: 0 | AI9: 0 | AJ9: 0 | AK9: 0 | AL9: 0
A10: Gas Steam | B10: GWh | C10: 0 | D10: 0 | E10: 0 | F10: 0 | G10: 0 | H10: 0 | I10: 0 | J10: 0 | K10: 0 | L10: 0 | M10: 0 | N10: 0 | O10: 0 | P10: 0 | Q10: 0 | R10: 0 | S10: 0 | T10: 0 | U10: 0 | V10: 0 | W10: 0 | X10: 0 | Y10: 0 | Z10: 0 | AA10: 0 | AB10: 0 | AC10: 0 | AD10: 0 | AE10: 0 | AF10: 0 | AG10: 0 | AH10: 0 | AI10: 0 | AJ10: 0 | AK10: 0 | AL10: 0
A11: Distillate | B11: GWh | C11: 0 | D11: 0 | E11: 0 | F11: 0 | G11: 0 | H11: 0 | I11: 0 | J11: 0 | K11: 0 | L11: 0 | M11: 0 | N11: 0 | O11: 0 | P11: 0 | Q11: 0 | R11: 0 | S11: 0 | T11: 0 | U11: 0 | V11: 0 | W11: 0 | X11: 0 | Y11: 0 | Z11: 0 | AA11: 0 | AB11: 0 | AC11: 0 | AD11: 0 | AE11: 0 | AF11: 0 | AG11: 0 | AH11: 0 | AI11: 0 | AJ11: 0 | AK11: 0 | AL11: 0
A12: Hydro | B12: GWh | C12: 66.220001 | D12: 66.220001 | E12: 66.220001 | F12: 66.220001 | G12: 66.220001 | H12: 66.220001 | I12: 66.220001 | J12: 66.220001 | K12: 66.220001 | L12: 66.220001 | M12: 66.220001 | N12: 66.220001 | O12: 66.220001 | P12: 66.220001 | Q12: 66.220001 | R12: 66.220001 | S12: 66.220001 | T12: 66.220001 | U12: 66.220001 | V12: 66.220001 | W12: 66.220001 | X12: 66.220001 | Y12: 66.220001 | Z12: 66.220001 | AA12: 66.220001 | AB12: 66.220001 | AC12: 66.220001 | AD12: 66.220001 | AE12: 66.220001 | AF12: 66.220001 | AG12: 66.220001 | AH12: 66.220001 | AI12: 66.220001 | AJ12: 66.220001 | AK12: 66.220001 | AL12: 66.220001
A13: Wind | B13: GWh | C13: 5258.4647 | D13: 5209.1739 | E13: 5043.8157 | F13: 4977.7798 | G13: 4885.761 | H13: 4956.6368 | I13: 5146.4005 | J13: 5268.1931 | K13: 5283.3571 | L13: 5276.4692 | M13: 5277.6423 | N13: 5280.3038 | O13: 5284.8539 | P13: 5283.3657 | Q13: 5289.0637 | R13: 5276.7932 | S13: 5241.2787 | T13: 5250.5159 | U13: 5737.7319 | V13: 6342.119 | W13: 6851.6246 | X13: 6811.521 | Y13: 6774.8825 | Z13: 6742.3778 | AA13: 6749.5328 | AB13: 7257.2699 | AC13: 7767.0108 | AD13: 7778.0817 | AE13: 7783.8814 | AF13: 7799.6389 | AG13: 7806.9618 | AH13: 7815.9452 | AI13: 7822.2955 | AJ13: 7792.0069 | AK13: 8885.4613 | AL13: 8877.426
A14: Biomass | B14: GWh | C14: 2118.5134 | D14: 2018.1733 | E14: 1923.8834 | F14: 1862.7833 | G14: 1779.3433 | H14: 1788.0233 | I14: 1882.7033 | J14: 2044.5933 | K14: 2109.6633 | L14: 2087.6833 | M14: 2078.7434 | N14: 2076.0633 | O14: 2052.9733 | P14: 2022.7233 | Q14: 2064.4733 | R14: 2015.9834 | S14: 1909.5034 | T14: 1899.3734 | U14: 1809.8233 | V14: 1804.8734 | W14: 1802.6234 | X14: 1752.8834 | Y14: 1727.5633 | Z14: 1750.9633 | AA14: 1745.0833 | AB14: 1721.7634 | AC14: 1631.8634 | AD14: 1709.2033 | AE14: 1697.5633 | AF14: 1671.0633 | AG14: 1632.3033 | AH14: 1655.4333 | AI14: 1652.9633 | AJ14: 1630.7833 | AK14: 1622.5633 | AL14: 1646.7833
A15: Solar | B15: GWh | C15: 4962.921 | D15: 7099.76 | E15: 9110.3382 | F15: 8991.0616 | G15: 9411.6213 | H15: 9548.1518 | I15: 9913.7006 | J15: 10148.314 | K15: 10177.525 | L15: 10164.257 | M15: 10524.439 | N15: 10529.746 | O15: 13494.327 | P15: 15173.611 | Q15: 15189.976 | R15: 17658.662 | S15: 17951.704 | T15: 17983.342 | U15: 17730.123 | V15: 17794.148 | W15: 18346.371 | X15: 19911.954 | Y15: 21838.401 | Z15: 21733.625 | AA15: 21756.688 | AB15: 22984.674 | AC15: 25258.194 | AD15: 26801.951 | AE15: 27226.898 | AF15: 27282.015 | AG15: 27307.63 | AH15: 27339.052 | AI15: 27361.265 | AJ15: 28091.013 | AK15: 28416.705 | AL15: 28794.893
... A22: Total | B22: GWh | C22: 38805.013 | D22: 42389.627 | E22: 44123.074 | F22: 43156.192 | G22: 43348.232 | H22: 44612.619 | I22: 49304.785 | J22: 52944.171 | K22: 55364.208 | L22: 57238.771 | M22: 59983.383 | N22: 59111.927 | O22: 58222.319 | P22: 57581.092 | Q22: 58229.119 | R22: 61437.907 | S22: 61222.931 | T22: 60436.551 | U22: 59168.468 | V22: 61228.772 | W22: 63333.34 | X22: 62739.445 | Y22: 65186.7 | Z22: 66341.908 | AA22: 67362.158 | AB22: 69407.221 | AC22: 70243.088 | AD22: 72281.02 | AE22: 74114.143 | AF22: 74850.119 | AG22: 75553.582 | AH22: 76465.839 | AI22: 76657.487 | AJ22: 78125.284 | AK22: 80117.109 | AL22: 80960.152
A23: Queensland North
A24: Black Coal | B24: GWh | C24: 0 | D24: 0 | E24: 0 | F24: 0 | G24: 0 | H24: 0 | I24: 0 | J24: 0 | K24: 0 | L24: 0 | M24: 0 | N24: 0 | O24: 0 | P24: 0 | Q24: 0 | R24: 0 | S24: 0 | T24: 0 | U24: 0 | V24: 0 | W24: 0 | X24: 0 | Y24: 0 | Z24: 0 | AA24: 0 | AB24: 0 | AC24: 0 | AD24: 0 | AE24: 0 | AF24: 0 | AG24: 0 | AH24: 0 | AI24: 0 | AJ24: 0 | AK24: 0 | AL24: 0
A25: Brown Coal | B25: GWh | C25: 0 | D25: 0 | E25: 0 | F25: 0 | G25: 0 | H25: 0 | I25: 0 | J25: 0 | K25: 0 | L25: 0 | M25: 0 | N25: 0 | O25: 0 | P25: 0 | Q25: 0 | R25: 0 | S25: 0 | T25: 0 | U25: 0 | V25: 0 | W25: 0 | X25: 0 | Y25: 0 | Z25: 0 | AA25: 0 | AB25: 0 | AC25: 0 | AD25: 0 | AE25: 0 | AF25: 0 | AG25: 0 | AH25: 0 | AI25: 0 | AJ25: 0 | AK25: 0 | AL25: 0
A26: Hydrogen ready | B26: GWh | C26: 0 | D26: 0 | E26: 0 | F26: 0 | G26: 0 | H26: 0 | I26: 0 | J26: 0 | K26: 0 | L26: 0 | M26: 0 | N26: 0 | O26: 0 | P26: 0 | Q26: 0 | R26: 120.15 | S26: 167.31 | T26: 176.45 | U26: 344.73 | V26: 231.69999 | W26: 245.69 | X26: 451.56999 | Y26: 396.41002 | Z26: 258.26 | AA26: 267.95 | AB26: 187.78 | AC26: 268.85 | AD26: 357.24 | AE26: 408.50999 | AF26: 437.13999 | AG26: 428.84999 | AH26: 344.50999 | AI26: 493.56001 | AJ26: 499.38 | AK26: 481.85001 | AL26: 391.29999
A27: Gas GT | B27: GWh | C27: 1.56 | D27: 1.44 | E27: 1.5399999 | F27: 1.43 | G27: 1.25 | H27: 1.05 | I27: 2.58 | J27: 6.7700001 | K27: 5.9400001 | L27: 5.4699998 | M27: 5.8299999 | N27: 6.1399999 | O27: 6.4299998 | P27: 6.2800002 | Q27: 6.21 | R27: 5.6300001 | S27: 6.3800001 | T27: 6.4200001 | U27: 5.75 | V27: 4.1900001 | W27: 0 | X27: 0 | Y27: 0 | Z27: 0 | AA27: 0 | AB27: 0 | AC27: 0 | AD27: 0 | AE27: 0 | AF27: 0 | AG27: 0 | AH27: 0 | AI27: 0 | AJ27: 0 | AK27: 0 | AL27: 0
A28: Gas CCGT & Cogen | B28: GWh | C28: 103.64 | D28: 96.269997 | E28: 105.01 | F28: 91.169998 | G28: 73.220001 | H28: 56.860001 | I28: 196.83 | J28: 414.35999 | K28: 431.94 | L28: 419.67999 | M28: 505.67999 | N28: 533.65997 | O28: 529.54999 | P28: 523.69 | Q28: 515.97998 | R28: 469.60001 | S28: 393.42999 | T28: 384.22 | U28: 393.28 | V28: 191.84 | W28: 128.94 | X28: 143.41 | Y28: 0 | Z28: 0 | AA28: 0 | AB28: 0 | AC28: 0 | AD28: 0 | AE28: 0 | AF28: 0 | AG28: 0 | AH28: 0 | AI28: 0 | AJ28: 0 | AK28: 0 | AL28: 0
A29: Gas CC CCS | B29: GWh | C29: 0 | D29: 0 | E29: 0 | F29: 0 | G29: 0 | H29: 0 | I29: 0 | J29: 0 | K29: 0 | L29: 0 | M29: 0 | N29: 0 | O29: 0 | P29: 0 | Q29: 0 | R29: 0 | S29: 0 | T29: 0 | U29: 0 | V29: 0 | W29: 0 | X29: 0 | Y29: 0 | Z29: 0 | AA29: 0 | AB29: 0 | AC29: 0 | AD29: 0 | AE29: 0 | AF29: 0 | AG29: 0 | AH29: 0 | AI29: 0 | AJ29: 0 | AK29: 0 | AL29: 0
A30: Gas Steam | B30: GWh | C30: 0 | D30: 0 | E30: 0 | F30: 0 | G30: 0 | H30: 0 | I30: 0 | J30: 0 | K30: 0 | L30: 0 | M30: 0 | N30: 0 | O30: 0 | P30: 0 | Q30: 0 | R30: 0 | S30: 0 | T30: 0 | U30: 0 | V30: 0 | W30: 0 | X30: 0 | Y30: 0 | Z30: 0 | AA30: 0 | AB30: 0 | AC30: 0 | AD30: 0 | AE30: 0 | AF30: 0 | AG30: 0 | AH30: 0 | AI30: 0 | AJ30: 0 | AK30: 0 | AL30: 0
A31: Distillate | B31: GWh | C31: 0 | D31: 0 | E31: 0 | F31: 0 | G31: 0 | H31: 0 | I31: 0 | J31: 0 | K31: 0 | L31: 0 | M31: 0 | N31: 0 | O31: 0 | P31: 0 | Q31: 0 | R31: 0 | S31: 0 | T31: 0 | U31: 0 | V31: 0 | W31: 0 | X31: 0 | Y31: 0 | Z31: 0 | AA31: 0 | AB31: 0 | AC31: 0 | AD31: 0 | AE31: 0 | AF31: 0 | AG31: 0 | AH31: 0 | AI31: 0 | AJ31: 0 | AK31: 0 | AL31: 0
A32: Hydro | B32: GWh | C32: 591.08002 | D32: 591.08002 | E32: 591.07001 | F32: 591.08002 | G32: 591.08002 | H32: 591.08002 | I32: 591.08002 | J32: 591.08002 | K32: 591.08002 | L32: 591.08002 | M32: 591.08002 | N32: 591.07001 | O32: 591.08002 | P32: 591.08002 | Q32: 591.08002 | R32: 591.08002 | S32: 591.08002 | T32: 591.07001 | U32: 591.08002 | V32: 591.08002 | W32: 591.08002 | X32: 591.08002 | Y32: 591.08002 | Z32: 591.08002 | AA32: 591.08002 | AB32: 591.08002 | AC32: 591.08002 | AD32: 591.08002 | AE32: 591.07001 | AF32: 591.08002 | AG32: 591.08002 | AH32: 591.08002 | AI32: 591.08002 | AJ32: 591.08002 | AK32: 591.08002 | AL32: 591.08002
A33: Wind | B33: GWh | C33: 1151.9252 | D33: 1151.9252 | E33: 1151.9252 | F33: 1366.3589 | G33: 2589.5865 | H33: 2603.5726 | I33: 2605.5411 | J33: 2606.0286 | K33: 2606.0286 | L33: 3952.9278 | M33: 5844.7763 | N33: 6514.1209 | O33: 6526.4604 | P33: 7586.0807 | Q33: 7586.0807 | R33: 8973.8892 | S33: 11281.751 | T33: 11291.037 | U33: 12763.82 | V33: 12754.216 | W33: 13508.766 | X33: 13352.696 | Y33: 14102.462 | Z33: 14053.171 | AA33: 14082.771 | AB33: 14035.192 | AC33: 14462.973 | AD33: 14566.779 | AE33: 14433.792 | AF33: 15650.503 | AG33: 15193.445 | AH33: 15280.042 | AI33: 15400.923 | AJ33: 18065.76 | AK33: 18933.536 | AL33: 19031.443
A34: Biomass | B34: GWh | C34: 280.27999 | D34: 267.2 | E34: 254.12 | F34: 240.65001 | G34: 201.52 | H34: 206.06001 | I34: 245.45 | J34: 272.18001 | K34: 287.32999 | L34: 284.31 | M34: 283.46001 | N34: 284.69 | O34: 281.77 | P34: 281.65001 | Q34: 283.63 | R34: 278.38999 | S34: 253.02 | T34: 254.38 | U34: 246.37999 | V34: 216.75 | W34: 211.56001 | X34: 210.37 | Y34: 10.54 | Z34: 11.05 | AA34: 12.41 | AB34: 11.49 | AC34: 11.87 | AD34: 14.06 | AE34: 11.51 | AF34: 12.04 | AG34: 13.58 | AH34: 12.7 | AI34: 13.75 | AJ34: 14.82 | AK34: 14.45 | AL34: 15.54
A35: Solar | B35: GWh | C35: 843.3596 | D35: 843.3596 | E35: 843.3596 | F35: 1363.0398 | G35: 1726.8437 | H35: 1736.1702 | I35: 1737.4829 | J35: 1737.8079 | K35: 1737.8079 | L35: 1737.8079 | M35: 1735.2826 | N35: 1734.4501 | O35: 1737.7356 | P35: 2021.1063 | Q35: 2021.1063 | R35: 2020.6181 | S35: 2006.4691 | T35: 2008.1207 | U35: 1980.7793 | V35: 1979.289 | W35: 1983.3318 | X35: 2831.1007 | Y35: 2840.4459 | Z35: 2830.5179 | AA35: 2836.4799 | AB35: 3285.5049 | AC35: 3671.191 | AD35: 3697.5406 | AE35: 4394.6297 | AF35: 4364.9889 | AG35: 5690.6381 | AH35: 5723.0725 | AI35: 5768.3479 | AJ35: 5650.087 | AK35: 5614.0112 | AL35: 5643.0417
... A42: Total | B42: GWh | C42: 4224.4493 | D42: 4693.0595 | E42: 4845.6415 | F42: 5867.4535 | G42: 7548.8454 | H42: 7706.6139 | I42: 8065.1011 | J42: 8960.7757 | K42: 9027.1347 | L42: 10690.052 | M42: 14428.668 | N42: 15752.947 | O42: 16912.33 | P42: 18582.594 | Q42: 18855.499 | R42: 20732.021 | S42: 22994.481 | T42: 23532.991 | U42: 24988.584 | V42: 25037.049 | W42: 25910.874 | X42: 26713.025 | Y42: 27653.773 | Z42: 27744.252 | AA42: 28198.184 | AB42: 28353.694 | AC42: 29282.464 | AD42: 29902.529 | AE42: 30274.542 | AF42: 31681.971 | AG42: 32080.293 | AH42: 32354.292 | AI42: 32741.06 | AJ42: 35321.767 | AK42: 36239.251 | AL42: 36552.473
A43: Queensland Central
A44: Black Coal | B44: GWh | C44: 18797.34 | D44: 17182.58 | E44: 16145.64 | F44: 15021.04 | G44: 17954.57 | H44: 17868.07 | I44: 17219.27 | J44: 14783.7 | K44: 15674.57 | L44: 16144.11 | M44: 11691.99 | N44: 11006.96 | O44: 11232.04 | P44: 11193.03 | Q44: 10242.49 | R44: 10493.66 | S44: 9042.3299 | T44: 10353.9 | U44: 8928.2899 | V44: 8081.54 | W44: 6291.5499 | X44: 5125.9298 | Y44: 4697.3699 | Z44: 4758.4199 | AA44: 4725.5999 | AB44: 4697.9001 | AC44: 2453.2899 | AD44: 0 | AE44: 0 | AF44: 0 | AG44: 0 | AH44: 0 | AI44: 0 | AJ44: 0 | AK44: 0 | AL44: 0
A45: Brown Coal | B45: GWh | C45: 0 | D45: 0 | E45: 0 | F45: 0 | G45: 0 | H45: 0 | I45: 0 | J45: 0 | K45: 0 | L45: 0 | M45: 0 | N45: 0 | O45: 0 | P45: 0 | Q45: 0 | R45: 0 | S45: 0 | T45: 0 | U45: 0 | V45: 0 | W45: 0 | X45: 0 | Y45: 0 | Z45: 0 | AA45: 0 | AB45: 0 | AC45: 0 | AD45: 0 | AE45: 0 | AF45: 0 | AG45: 0 | AH45: 0 | AI45: 0 | AJ45: 0 | AK45: 0 | AL45: 0
A46: Hydrogen ready | B46: GWh | C46: 0 | D46: 0 | E46: 0 | F46: 0 | G46: 207.64 | H46: 183.27 | I46: 304.95001 | J46: 546.65002 | K46: 648.06 | L46: 737.82001 | M46: 112.21 | N46: 432.51001 | O46: 677.05999 | P46: 713.28001 | Q46: 692.11002 | R46: 852.30002 | S46: 790.45999 | T46: 800.63998 | U46: 844.86998 | V46: 1110.47 | W46: 1284.65 | X46: 1683.66 | Y46: 2405.35 | Z46: 2272.12 | AA46: 2544.4301 | AB46: 2183.6199 | AC46: 3317.97 | AD46: 4475.74 | AE46: 4834.76 | AF46: 4581.2101 | AG46: 4272.45 | AH46: 4332.45 | AI46: 4737.7801 | AJ46: 4235.04 | AK46: 4080.18 | AL46: 4318.5001
A47: Gas GT | B47: GWh | C47: 10.91 | D47: 7.7900002 | E47: 8.3700001 | F47: 5.6299998 | G47: 7.5899998 | H47: 6.4499998 | I47: 19.01 | J47: 40.820001 | K47: 52.149999 | L47: 63.579998 | M47: 88.93 | N47: 136.05 | O47: 166.99001 | P47: 176.55 | Q47: 183.46001 | R47: 176.99001 | S47: 169.23 | T47: 135.33 | U47: 138.38 | V47: 150.31 | W47: 169.89999 | X47: 183.53999 | Y47: 181.42 | Z47: 187.07001 | AA47: 193.84 | AB47: 172.53 | AC47: 188.21001 | AD47: 215 | AE47: 221.61 | AF47: 214.59 | AG47: 203.14999 | AH47: 205.12 | AI47: 204.92 | AJ47: 196.48 | AK47: 192.53 | AL47: 201.37
A48: Gas CCGT & Cogen | B48: GWh | C48: 257.07001 | D48: 233.09 | E48: 232.00999 | F48: 214.32001 | G48: 217.84 | H48: 213.72 | I48: 239.33 | J48: 284.67999 | K48: 312.79001 | L48: 325.95999 | M48: 430.07001 | N48: 528.37 | O48: 805.71997 | P48: 826.38 | Q48: 842.71002 | R48: 836.20001 | S48: 791.45001 | T48: 691.40997 | U48: 696.38 | V48: 742.91998 | W48: 801.54999 | X48: 864.60999 | Y48: 864.40002 | Z48: 865.40002 | AA48: 889.58002 | AB48: 810.42999 | AC48: 345.64999 | AD48: 373.07999 | AE48: 383.34 | AF48: 368.09 | AG48: 355.73999 | AH48: 363.89999 | AI48: 402.51999 | AJ48: 380.51001 | AK48: 369.14001 | AL48: 369.29999
A49: Gas CC CCS | B49: GWh | C49: 0 | D49: 0 | E49: 0 | F49: 0 | G49: 0 | H49: 0 | I49: 0 | J49: 0 | K49: 0 | L49: 0 | M49: 0 | N49: 0 | O49: 0 | P49: 0 | Q49: 0 | R49: 0 | S49: 0 | T49: 0 | U49: 0 | V49: 0 | W49: 0 | X49: 0 | Y49: 0 | Z49: 0 | AA49: 0 | AB49: 0 | AC49: 0 | AD49: 0 | AE49: 0 | AF49: 0 | AG49: 0 | AH49: 0 | AI49: 0 | AJ49: 0 | AK49: 0 | AL49: 0
A50: Gas Steam | B50: GWh | C50: 0 | D50: 0 | E50: 0 | F50: 0 | G50: 0 | H50: 0 | I50: 0 | J50: 0 | K50: 0 | L50: 0 | M50: 0 | N50: 0 | O50: 0 | P50: 0 | Q50: 0 | R50: 0 | S50: 0 | T50: 0 | U50: 0 | V50: 0 | W50: 0 | X50: 0 | Y50: 0 | Z50: 0 | AA50: 0 | AB50: 0 | AC50: 0 | AD50: 0 | AE50: 0 | AF50: 0 | AG50: 0 | AH50: 0 | AI50: 0 | AJ50: 0 | AK50: 0 | AL50: 0
A51: Distillate | B51: GWh | C51: 0 | D51: 0 | E51: 0 | F51: 0 | G51: 0 | H51: 0 | I51: 0 | J51: 0 | K51: 0 | L51: 0 | M51: 0 | N51: 0 | O51: 0 | P51: 0 | Q51: 0 | R51: 0 | S51: 0 | T51: 0 | U51: 0 | V51: 0 | W51: 0 | X51: 0 | Y51: 0 | Z51: 0 | AA51: 0 | AB51: 0 | AC51: 0 | AD51: 0 | AE51: 0 | AF51: 0 | AG51: 0 | AH51: 0 | AI51: 0 | AJ51: 0 | AK51: 0 | AL51: 0
A52: Hydro | B52: GWh | C52: 0 | D52: 0 | E52: 0 | F52: 0 | G52: 0 | H52: 0 | I52: 0 | J52: 0 | K52: 0 | L52: 0 | M52: 0 | N52: 0 | O52: 0 | P52: 0 | Q52: 0 | R52: 0 | S52: 0 | T52: 0 | U52: 0 | V52: 0 | W52: 0 | X52: 0 | Y52: 0 | Z52: 0 | AA52: 0 | AB52: 0 | AC52: 0 | AD52: 0 | AE52: 0 | AF52: 0 | AG52: 0 | AH52: 0 | AI52: 0 | AJ52: 0 | AK52: 0 | AL52: 0
A53: Wind | B53: GWh | C53: 1075.0396 | D53: 1016.6082 | E53: 924.92303 | F53: 1590.9797 | G53: 1374.9527 | H53: 1533.476 | I53: 1712.4772 | J53: 1893.7666 | K53: 1926.1642 | L53: 2281.118 | M53: 3181.2598 | N53: 3738.6885 | O53: 5303.223 | P53: 5292.9929 | Q53: 5316.5746 | R53: 6357.0921 | S53: 7899.9212 | T53: 9283.468 | U53: 12442.376 | V53: 13447.168 | W53: 14118.475 | X53: 14081.583 | Y53: 14035.665 | Z53: 14445.645 | AA53: 14270.954 | AB53: 15218.509 | AC53: 15779.68 | AD53: 16381.87 | AE53: 16849.369 | AF53: 16762.691 | AG53: 17421.967 | AH53: 17540.53 | AI53: 18652.228 | AJ53: 19542.267 | AK53: 20050.743 | AL53: 20064.195
A54: Biomass | B54: GWh | C54: 630.49667 | D54: 605.89666 | E54: 578.09667 | F54: 562.34666 | G54: 547.80667 | H54: 546.37666 | I54: 572.91667 | J54: 601.33666 | K54: 625.15667 | L54: 615.00668 | M54: 613.44667 | N54: 614.50666 | O54: 608.82667 | P54: 604.57666 | Q54: 612.87667 | R54: 601.08666 | S54: 572.05667 | T54: 571.75666 | U54: 555.42666 | V54: 561.85667 | W54: 561.38667 | X54: 557.19667 | Y54: 549.80667 | Z54: 548.78666 | AA54: 546.52667 | AB54: 540.93667 | AC54: 535.88667 | AD54: 545.06666 | AE54: 537.45668 | AF54: 532.69667 | AG54: 516.86666 | AH54: 527.41667 | AI54: 528.26666 | AJ54: 513.67668 | AK54: 508.49665 | AL54: 511.45666
A55: Solar | B55: GWh | C55: 1474.2804 | D55: 1394.1492 | E55: 1944.142 | F55: 2254.7876 | G55: 1948.6271 | H55: 2173.2914 | I55: 2426.9777 | J55: 2683.9069 | K55: 2729.8219 | L55: 2719.404 | M55: 2968.0546 | N55: 2979.8521 | O55: 3863.1186 | P55: 4253.2883 | Q55: 4272.2378 | R55: 5670.3354 | S55: 10000.911 | T55: 10694.026 | U55: 10603.177 | V55: 10943.855 | W55: 11533.988 | X55: 11503.849 | Y55: 11877.69 | Z55: 11805.009 | AA55: 13580.223 | AB55: 13520.199 | AC55: 15466.37 | AD55: 16871.607 | AE55: 17601.625 | AF55: 18608.469 | AG55: 19492.892 | AH55: 19625.548 | AI55: 19694.754 | AJ55: 20941.939 | AK55: 20928.078 | AL55: 21314.128
... A62: Total | B62: GWh | C62: 24484.711 | D62: 22822.269 | E62: 22298.331 | F62: 22276.744 | G62: 24607.232 | H62: 25297.198 | I62: 25800.811 | J62: 24930.792 | K62: 26562.477 | L62: 27714.832 | M62: 24761.566 | N62: 25568.654 | O62: 29860.205 | P62: 30269.094 | Q62: 29614.452 | R62: 32953.74 | S62: 37870.654 | T62: 40687.804 | U62: 42944.512 | V62: 43920.948 | W62: 44386.018 | X62: 44506.37 | Y62: 45295.902 | Z62: 45878.298 | AA62: 47963.091 | AB62: 48099.95 | AC62: 49708.986 | AD62: 52244.958 | AE62: 54566.914 | AF62: 55212.303 | AG62: 56524.983 | AH62: 57212.342 | AI62: 59089.154 | AJ62: 60856.978 | AK62: 61723.273 | AL62: 63023.495
A63: Queensland
A64: Black Coal | B64: GWh | C64: 37266.59 | D64: 35867.19 | E64: 34003.33 | F64: 31667.12 | G64: 33610.43 | H64: 33454.17 | I64: 34071.32 | J64: 32775.05 | K64: 34792.01 | L64: 35427.67 | M64: 31142.319 | N64: 28705.53 | O64: 24080.68 | P64: 20557.08 | Q64: 19681.83 | R64: 19825.23 | S64: 17987.37 | T64: 17414.53 | U64: 13991.8 | V64: 13157.37 | W64: 11360.61 | X64: 10046.36 | Y64: 9521.0898 | Z64: 9680.1599 | AA64: 9669.5898 | AB64: 9587.5002 | AC64: 4118.8 | AD64: 0 | AE64: 0 | AF64: 0 | AG64: 0 | AH64: 0 | AI64: 0 | AJ64: 0 | AK64: 0 | AL64: 0
A65: Brown Coal | B65: GWh | C65: 0 | D65: 0 | E65: 0 | F65: 0 | G65: 0 | H65: 0 | I65: 0 | J65: 0 | K65: 0 | L65: 0 | M65: 0 | N65: 0 | O65: 0 | P65: 0 | Q65: 0 | R65: 0 | S65: 0 | T65: 0 | U65: 0 | V65: 0 | W65: 0 | X65: 0 | Y65: 0 | Z65: 0 | AA65: 0 | AB65: 0 | AC65: 0 | AD65: 0 | AE65: 0 | AF65: 0 | AG65: 0 | AH65: 0 | AI65: 0 | AJ65: 0 | AK65: 0 | AL65: 0
A66: Hydrogen ready | B66: GWh | C66: 0 | D66: 0 | E66: 0 | F66: 0 | G66: 842.43999 | H66: 768.17003 | I66: 1198.23 | J66: 1834.01 | K66: 2236.06 | L66: 2543.41 | M66: 369.25 | N66: 715.21 | O66: 978.75999 | P66: 1058.91 | Q66: 1019.94 | R66: 1301.05 | S66: 1278.19 | T66: 1311.61 | U66: 1450.12 | V66: 1765.48 | W66: 2044.98 | X66: 2721.06 | Y66: 3743.61 | Z66: 4132.46 | AA66: 4777.4601 | AB66: 4271.27 | AC66: 5817.2299 | AD66: 7687.32 | AE66: 8355.1299 | AF66: 7979.85 | AG66: 7622.7001 | AH66: 7728.8701 | AI66: 8642.29 | AJ66: 8114.72 | AK66: 7862.4601 | AL66: 8109.4499
A67: Gas GT | B67: GWh | C67: 15.96 | D67: 16.96 | E67: 27.7 | F67: 33.91 | G67: 22.56 | H67: 14.38 | I67: 34.58 | J67: 85.17 | K67: 119.85 | L67: 166.39 | M67: 578.91001 | N67: 677.49 | O67: 773.60002 | P67: 891.91002 | Q67: 862.71002 | R67: 932.24002 | S67: 949.75001 | T67: 985.73002 | U67: 1038.38 | V67: 1134.93 | W67: 1204.63 | X67: 1534.7 | Y67: 869.01997 | Z67: 917.25998 | AA67: 972.44998 | AB67: 910.65998 | AC67: 943.16003 | AD67: 1054.97 | AE67: 1055.8 | AF67: 1033 | AG67: 1008.04 | AH67: 1014.59 | AI67: 204.92 | AJ67: 196.48 | AK67: 192.53 | AL67: 201.37
A68: Gas CCGT & Cogen | B68: GWh | C68: 1023.51 | D68: 1373.46 | E68: 1606.19 | F68: 970.78001 | G68: 550.88 | H68: 488.17001 | I68: 807.07001 | J68: 1348.12 | K68: 1575.85 | L68: 1761.37 | M68: 3818.95 | N68: 4206.1299 | O68: 4787.4699 | P68: 5056.7901 | Q68: 5024.36 | R68: 4887.06 | S68: 3961.1901 | T68: 3964.5999 | U68: 4105.2801 | V68: 4008.3999 | W68: 4114.99 | X68: 1248.92 | Y68: 864.40002 | Z68: 865.40002 | AA68: 889.58002 | AB68: 810.42999 | AC68: 345.64999 | AD68: 373.07999 | AE68: 383.34 | AF68: 368.09 | AG68: 355.73999 | AH68: 363.89999 | AI68: 402.51999 | AJ68: 380.51001 | AK68: 369.14001 | AL68: 369.29999
A69: Gas CC CCS | B69: GWh | C69: 0 | D69: 0 | E69: 0 | F69: 0 | G69: 0 | H69: 0 | I69: 0 | J69: 0 | K69: 0 | L69: 0 | M69: 0 | N69: 0 | O69: 0 | P69: 0 | Q69: 0 | R69: 0 | S69: 0 | T69: 0 | U69: 0 | V69: 0 | W69: 0 | X69: 0 | Y69: 0 | Z69: 0 | AA69: 0 | AB69: 0 | AC69: 0 | AD69: 0 | AE69: 0 | AF69: 0 | AG69: 0 | AH69: 0 | AI69: 0 | AJ69: 0 | AK69: 0 | AL69: 0
A70: Gas Steam | B70: GWh | C70: 0 | D70: 0 | E70: 0 | F70: 0 | G70: 0 | H70: 0 | I70: 0 | J70: 0 | K70: 0 | L70: 0 | M70: 0 | N70: 0 | O70: 0 | P70: 0 | Q70: 0 | R70: 0 | S70: 0 | T70: 0 | U70: 0 | V70: 0 | W70: 0 | X70: 0 | Y70: 0 | Z70: 0 | AA70: 0 | AB70: 0 | AC70: 0 | AD70: 0 | AE70: 0 | AF70: 0 | AG70: 0 | AH70: 0 | AI70: 0 | AJ70: 0 | AK70: 0 | AL70: 0
A71: Distillate | B71: GWh | C71: 0 | D71: 0 | E71: 0 | F71: 0 | G71: 0 | H71: 0 | I71: 0 | J71: 0 | K71: 0 | L71: 0 | M71: 0 | N71: 0 | O71: 0 | P71: 0 | Q71: 0 | R71: 0 | S71: 0 | T71: 0 | U71: 0 | V71: 0 | W71: 0 | X71: 0 | Y71: 0 | Z71: 0 | AA71: 0 | AB71: 0 | AC71: 0 | AD71: 0 | AE71: 0 | AF71: 0 | AG71: 0 | AH71: 0 | AI71: 0 | AJ71: 0 | AK71: 0 | AL71: 0
A72: Hydro | B72: GWh | C72: 657.30002 | D72: 657.30002 | E72: 657.29002 | F72: 657.30002 | G72: 657.30002 | H72: 657.30002 | I72: 657.30002 | J72: 657.30002 | K72: 657.30002 | L72: 657.30002 | M72: 657.30002 | N72: 657.29002 | O72: 657.30002 | P72: 657.30002 | Q72: 657.30002 | R72: 657.30002 | S72: 657.30002 | T72: 657.29002 | U72: 657.30002 | V72: 657.30002 | W72: 657.30002 | X72: 657.30002 | Y72: 657.30002 | Z72: 657.30002 | AA72: 657.30002 | AB72: 657.30002 | AC72: 657.30002 | AD72: 657.30002 | AE72: 657.29002 | AF72: 657.30002 | AG72: 657.30002 | AH72: 657.30002 | AI72: 657.30002 | AJ72: 657.30002 | AK72: 657.30002 | AL72: 657.30002
A73: Wind | B73: GWh | C73: 7485.4294 | D73: 7377.7073 | E73: 7120.6639 | F73: 7935.1184 | G73: 8850.3003 | H73: 9093.6853 | I73: 9464.4188 | J73: 9767.9883 | K73: 9815.5499 | L73: 11510.515 | M73: 14303.678 | N73: 15533.113 | O73: 17114.537 | P73: 18162.439 | Q73: 18191.719 | R73: 20607.775 | S73: 24422.951 | T73: 25825.021 | U73: 30943.927 | V73: 32543.504 | W73: 34478.865 | X73: 34245.799 | Y73: 34913.009 | Z73: 35241.194 | AA73: 35103.258 | AB73: 36510.971 | AC73: 38009.663 | AD73: 38726.731 | AE73: 39067.042 | AF73: 40212.833 | AG73: 40422.374 | AH73: 40636.517 | AI73: 41875.446 | AJ73: 45400.033 | AK73: 47869.741 | AL73: 47973.064
A74: Biomass | B74: GWh | C74: 3029.29 | D74: 2891.27 | E74: 2756.1001 | F74: 2665.78 | G74: 2528.67 | H74: 2540.4599 | I74: 2701.07 | J74: 2918.11 | K74: 3022.15 | L74: 2987 | M74: 2975.65 | N74: 2975.26 | O74: 2943.57 | P74: 2908.95 | Q74: 2960.98 | R74: 2895.46 | S74: 2734.58 | T74: 2725.51 | U74: 2611.63 | V74: 2583.48 | W74: 2575.57 | X74: 2520.4501 | Y74: 2287.91 | Z74: 2310.8 | AA74: 2304.02 | AB74: 2274.1901 | AC74: 2179.62 | AD74: 2268.33 | AE74: 2246.53 | AF74: 2215.8 | AG74: 2162.75 | AH74: 2195.55 | AI74: 2194.98 | AJ74: 2159.28 | AK74: 2145.51 | AL74: 2173.7799
A75: Solar | B75: GWh | C75: 7280.561 | D75: 9337.2688 | E75: 11897.84 | F75: 12608.889 | G75: 13087.092 | H75: 13457.613 | I75: 14078.161 | J75: 14570.029 | K75: 14645.155 | L75: 14621.469 | M75: 15227.776 | N75: 15244.048 | O75: 19095.182 | P75: 21448.006 | Q75: 21483.32 | R75: 25349.615 | S75: 29959.084 | T75: 30685.488 | U75: 30314.079 | V75: 30717.292 | W75: 31863.691 | X75: 34246.904 | Y75: 36556.537 | Z75: 36369.152 | AA75: 38173.391 | AB75: 39790.378 | AC75: 44395.755 | AD75: 47371.099 | AE75: 49223.152 | AF75: 50255.473 | AG75: 52491.16 | AH75: 52687.673 | AI75: 52824.367 | AJ75: 54683.038 | AK75: 54958.794 | AL75: 55752.062
... A82: Total | B82: GWh | C82: 67514.174 | D82: 69904.955 | E82: 71267.046 | F82: 71300.389 | G82: 75504.309 | H82: 77616.431 | I82: 83170.697 | J82: 86835.738 | K82: 90953.82 | L82: 95643.655 | M82: 99173.617 | N82: 100433.53 | O82: 104994.85 | P82: 106432.78 | Q82: 106699.07 | R82: 115123.67 | S82: 122088.07 | T82: 124657.35 | U82: 127101.56 | V82: 130186.77 | W82: 133630.23 | X82: 133958.84 | Y82: 138136.37 | Z82: 139964.46 | AA82: 143523.43 | AB82: 145860.86 | AC82: 149234.54 | AD82: 154428.51 | AE82: 158955.6 | AF82: 161744.39 | AG82: 164158.86 | AH82: 166032.47 | AI82: 168487.7 | AJ82: 174304.03 | AK82: 178079.63 | AL82: 180536.12
A83: New South Wales
A84: Black Coal | B84: GWh | C84: 35134.451 | D84: 32007.12 | E84: 30841.87 | F84: 29225.6 | G84: 24637.44 | H84: 23828.66 | I84: 18272.05 | J84: 16422.3 | K84: 10436.48 | L84: 7619.7102 | M84: 7698.3501 | N84: 7770.1602 | O84: 7740.51 | P84: 7722.27 | Q84: 7844.8799 | R84: 4301.78 | S84: 0 | T84: 0 | U84: 0 | V84: 0 | W84: 0 | X84: 0 | Y84: 0 | Z84: 0 | AA84: 0 | AB84: 0 | AC84: 0 | AD84: 0 | AE84: 0 | AF84: 0 | AG84: 0 | AH84: 0 | AI84: 0 | AJ84: 0 | AK84: 0 | AL84: 0
A85: Brown Coal | B85: GWh | C85: 0 | D85: 0 | E85: 0 | F85: 0 | G85: 0 | H85: 0 | I85: 0 | J85: 0 | K85: 0 | L85: 0 | M85: 0 | N85: 0 | O85: 0 | P85: 0 | Q85: 0 | R85: 0 | S85: 0 | T85: 0 | U85: 0 | V85: 0 | W85: 0 | X85: 0 | Y85: 0 | Z85: 0 | AA85: 0 | AB85: 0 | AC85: 0 | AD85: 0 | AE85: 0 | AF85: 0 | AG85: 0 | AH85: 0 | AI85: 0 | AJ85: 0 | AK85: 0 | AL85: 0
A86: Hydrogen ready | B86: GWh | C86: 0 | D86: 0 | E86: 0 | F86: 0 | G86: 0 | H86: 0 | I86: 0 | J86: 0 | K86: 0 | L86: 0 | M86: 619.11 | N86: 692.13 | O86: 884.51 | P86: 822.09 | Q86: 772.24001 | R86: 1142.19 | S86: 1219.61 | T86: 1436.97 | U86: 1361.62 | V86: 1555.34 | W86: 1825.1399 | X86: 2064.8201 | Y86: 2820.81 | Z86: 2236.5001 | AA86: 2331.8399 | AB86: 2428.86 | AC86: 2632.24 | AD86: 3099.7599 | AE86: 3229.24 | AF86: 3456.27 | AG86: 3507.28 | AH86: 3445.42 | AI86: 3690.4899 | AJ86: 3846.56 | AK86: 3734.21 | AL86: 3528.7101
A87: Gas GT | B87: GWh | C87: 205.64 | D87: 342.02 | E87: 192.6 | F87: 141.91 | G87: 213.13 | H87: 146.67 | I87: 191.99 | J87: 218.99 | K87: 331.67 | L87: 305.55001 | M87: 47.19 | N87: 31.79 | O87: 43.81 | P87: 18.879999 | Q87: 21.21 | R87: 57.090001 | S87: 52.459999 | T87: 105.87 | U87: 112.63 | V87: 156.29 | W87: 63.11 | X87: 2.94 | Y87: 31 | Z87: 1780.77 | AA87: 1794.25 | AB87: 1671.15 | AC87: 1752.75 | AD87: 1869.8 | AE87: 1859.44 | AF87: 1482.26 | AG87: 1499.32 | AH87: 1487.1 | AI87: 1526.45 | AJ87: 1551.37 | AK87: 1523.86 | AL87: 2674.44
A88: Gas CCGT & Cogen | B88: GWh | C88: 699.41998 | D88: 707.71997 | E88: 556.97998 | F88: 281.35999 | G88: 439.75 | H88: 368 | I88: 480.31 | J88: 1789.74 | K88: 2457.1799 | L88: 2864.78 | M88: 3525.5699 | N88: 3677.65 | O88: 3816.5599 | P88: 3432.4801 | Q88: 6074.1702 | R88: 6484.5901 | S88: 6778.67 | T88: 6941.1901 | U88: 5694.9401 | V88: 5490.0999 | W88: 5644.8999 | X88: 5531.9399 | Y88: 5406.47 | Z88: 5816.9402 | AA88: 5831.6201 | AB88: 5593.8799 | AC88: 5590.96 | AD88: 6096.3901 | AE88: 6058.5798 | AF88: 5938.3301 | AG88: 5745.79 | AH88: 5833.8999 | AI88: 5855.1802 | AJ88: 5764.3699 | AK88: 5665.8999 | AL88: 5791.1299
A89: Gas CC CCS | B89: GWh | C89: 0 | D89: 0 | E89: 0 | F89: 0 | G89: 0 | H89: 0 | I89: 0 | J89: 0 | K89: 0 | L89: 0 | M89: 0 | N89: 0 | O89: 0 | P89: 0 | Q89: 0 | R89: 0 | S89: 0 | T89: 0 | U89: 0 | V89: 0 | W89: 0 | X89: 0 | Y89: 0 | Z89: 0 | AA89: 0 | AB89: 0 | AC89: 0 | AD89: 0 | AE89: 0 | AF89: 0 | AG89: 0 | AH89: 0 | AI89: 0 | AJ89: 0 | AK89: 0 | AL89: 0
A90: Gas Steam | B90: GWh | C90: 0 | D90: 0 | E90: 0 | F90: 0 | G90: 0 | H90: 0 | I90: 0 | J90: 0 | K90: 0 | L90: 0 | M90: 0 | N90: 0 | O90: 0 | P90: 0 | Q90: 0 | R90: 0 | S90: 0 | T90: 0 | U90: 0 | V90: 0 | W90: 0 | X90: 0 | Y90: 0 | Z90: 0 | AA90: 0 | AB90: 0 | AC90: 0 | AD90: 0 | AE90: 0 | AF90: 0 | AG90: 0 | AH90: 0 | AI90: 0 | AJ90: 0 | AK90: 0 | AL90: 0
A91: Distillate | B91: GWh | C91: 0 | D91: 0 | E91: 0 | F91: 0 | G91: 0 | H91: 0 | I91: 0 | J91: 0 | K91: 0 | L91: 0 | M91: 0 | N91: 0 | O91: 0 | P91: 0 | Q91: 0 | R91: 0 | S91: 0 | T91: 0 | U91: 0 | V91: 0 | W91: 0 | X91: 0 | Y91: 0 | Z91: 0 | AA91: 0 | AB91: 0 | AC91: 0 | AD91: 0 | AE91: 0 | AF91: 0 | AG91: 0 | AH91: 0 | AI91: 0 | AJ91: 0 | AK91: 0 | AL91: 0
A92: Hydro | B92: GWh | C92: 2490.82 | D92: 2490.82 | E92: 2490.82 | F92: 2490.82 | G92: 2490.82 | H92: 2490.53 | I92: 2490.82 | J92: 2490.82 | K92: 2490.82 | L92: 2490.82 | M92: 2490.82 | N92: 2490.82 | O92: 2490.82 | P92: 2490.82 | Q92: 2490.82 | R92: 2490.82 | S92: 2490.82 | T92: 2490.82 | U92: 2490.82 | V92: 2490.82 | W92: 2490.82 | X92: 2490.43 | Y92: 2490.02 | Z92: 2490.19 | AA92: 2490.05 | AB92: 2490.29 | AC92: 2489.82 | AD92: 2489.92 | AE92: 2489.72 | AF92: 2490.05 | AG92: 2489.09 | AH92: 2489.02 | AI92: 2487.7099 | AJ92: 2489.16 | AK92: 2486.48 | AL92: 2484.5
A93: Wind | B93: GWh | C93: 7826.0003 | D93: 7680.8121 | E93: 10179.02 | F93: 13635.106 | G93: 17193.992 | H93: 20827.771 | I93: 25180.713 | J93: 26055.856 | K93: 26531.864 | L93: 27144.423 | M93: 29738.37 | N93: 31594.9 | O93: 33938.287 | P93: 35815.926 | Q93: 35916.555 | R93: 35837.522 | S93: 37713.308 | T93: 37716.777 | U93: 40301.545 | V93: 41950.179 | W93: 41934.638 | X93: 41932.445 | Y93: 41913.03 | Z93: 41974.082 | AA93: 41896.911 | AB93: 41731.103 | AC93: 42728.43 | AD93: 42730.017 | AE93: 45267.593 | AF93: 45466.835 | AG93: 46513.298 | AH93: 46598.259 | AI93: 47167.07 | AJ93: 47152.795 | AK93: 48458.246 | AL93: 48529.459
A94: Biomass | B94: GWh | C94: 1294.48 | D94: 1222.78 | E94: 1159.73 | F94: 1105.41 | G94: 1047.14 | H94: 1056.37 | I94: 1118.09 | J94: 1172.53 | K94: 1205.4301 | L94: 1226.62 | M94: 1220.27 | N94: 1208.77 | O94: 1178.36 | P94: 1192.28 | Q94: 1195.67 | R94: 1197.9399 | S94: 1150.3 | T94: 1149.64 | U94: 1109.41 | V94: 1113.36 | W94: 1116.5 | X94: 1096.92 | Y94: 1097.35 | Z94: 1109.55 | AA94: 1104.25 | AB94: 1107.63 | AC94: 1060.92 | AD94: 1099.2 | AE94: 1086.58 | AF94: 1084.4399 | AG94: 1053.76 | AH94: 1069.7 | AI94: 1077.89 | AJ94: 1065.1 | AK94: 1071.64 | AL94: 1076.79
A95: Solar | B95: GWh | C95: 8953.9669 | D95: 11905.688 | E95: 12117.682 | F95: 13348.45 | G95: 14980.481 | H95: 15272.849 | I95: 15599.889 | J95: 15690.685 | K95: 15977.334 | L95: 16012.818 | M95: 16019.858 | N95: 16037.171 | O95: 15968.842 | P95: 15937.175 | Q95: 15981.952 | R95: 16389.152 | S95: 17421.696 | T95: 18645.69 | U95: 19529.124 | V95: 19903.943 | W95: 20314.375 | X95: 22049.961 | Y95: 22039.752 | Z95: 22071.856 | AA95: 22422.741 | AB95: 23182.374 | AC95: 23123.473 | AD95: 24318.422 | AE95: 26435.16 | AF95: 26551.512 | AG95: 26936.653 | AH95: 27400.771 | AI95: 28518.019 | AJ95: 28509.388 | AK95: 29444.616 | AL95: 30156.161
... A102: Total | B102: GWh | C102: 69242.579 | D102: 71222.037 | E102: 74315.258 | F102: 80123.857 | G102: 83362.368 | H102: 89892.681 | I102: 91747.12 | J102: 94001.369 | K102: 91420.234 | L102: 91707.766 | M102: 94562.167 | N102: 97189.753 | O102: 101618.55 | P102: 105658.31 | Q102: 109874.63 | R102: 109807.67 | S102: 110727.83 | T102: 114324.24 | U102: 117989.28 | V102: 121818.94 | W102: 124481.18 | X102: 127286.35 | Y102: 129261.65 | Z102: 132235.6 | AA102: 134502.5 | AB102: 136897.87 | AC102: 139306.58 | AD102: 143078.85 | AE102: 149494.67 | AF102: 151427.92 | AG102: 153953.6 | AH102: 156342.88 | AI102: 159893.79 | AJ102: 161378.86 | AK102: 165217.05 | AL102: 168563.22
A103: Victoria
A104: Black Coal | B104: GWh | C104: 0 | D104: 0 | E104: 0 | F104: 0 | G104: 0 | H104: 0 | I104: 0 | J104: 0 | K104: 0 | L104: 0 | M104: 0 | N104: 0 | O104: 0 | P104: 0 | Q104: 0 | R104: 0 | S104: 0 | T104: 0 | U104: 0 | V104: 0 | W104: 0 | X104: 0 | Y104: 0 | Z104: 0 | AA104: 0 | AB104: 0 | AC104: 0 | AD104: 0 | AE104: 0 | AF104: 0 | AG104: 0 | AH104: 0 | AI104: 0 | AJ104: 0 | AK104: 0 | AL104: 0
A105: Brown Coal | B105: GWh | C105: 26607.25 | D105: 26126.02 | E105: 25801.17 | F105: 25786.13 | G105: 17737.92 | H105: 17939.13 | I105: 18332.89 | J105: 19037.64 | K105: 19075.86 | L105: 16760.18 | M105: 8150.91 | N105: 6321.8201 | O105: 6022.9402 | P105: 6064.5 | Q105: 5994.4202 | R105: 5059.1799 | S105: 5320.6101 | T105: 5458.55 | U105: 5099.79 | V105: 5228.4299 | W105: 5306.0601 | X105: 4940.9299 | Y105: 2793.7599 | Z105: 0 | AA105: 0 | AB105: 0 | AC105: 0 | AD105: 0 | AE105: 0 | AF105: 0 | AG105: 0 | AH105: 0 | AI105: 0 | AJ105: 0 | AK105: 0 | AL105: 0
A106: Hydrogen ready | B106: GWh | C106: 0 | D106: 0 | E106: 0 | F106: 0 | G106: 0 | H106: 0 | I106: 0 | J106: 0 | K106: 0 | L106: 0 | M106: 0 | N106: 0 | O106: 0 | P106: 0 | Q106: 0 | R106: 0 | S106: 0 | T106: 0 | U106: 0 | V106: 0 | W106: 0 | X106: 0 | Y106: 65.019997 | Z106: 42.619999 | AA106: 44 | AB106: 45.599998 | AC106: 57.919998 | AD106: 56.59 | AE106: 61.68 | AF106: 59.43 | AG106: 56.959999 | AH106: 535.35001 | AI106: 749.93 | AJ106: 779.08002 | AK106: 771.37001 | AL106: 1190.96
A107: Gas GT | B107: GWh | C107: 1925.29 | D107: 1665.51 | E107: 1707.25 | F107: 1588.91 | G107: 1750.45 | H107: 1545.77 | I107: 1713.02 | J107: 2061.87 | K107: 2352.93 | L107: 2139.66 | M107: 1993.6 | N107: 2164.41 | O107: 2200.13 | P107: 2131.67 | Q107: 1507.18 | R107: 925.42999 | S107: 787.48 | T107: 819.38001 | U107: 689.18 | V107: 656.84999 | W107: 658.20001 | X107: 683.04002 | Y107: 153.81 | Z107: 99.920001 | AA107: 99.529999 | AB107: 99.090001 | AC107: 109.79 | AD107: 117.03 | AE107: 121.89 | AF107: 115.63 | AG107: 114.6 | AH107: 70.569999 | AI107: 64.81 | AJ107: 68.799999 | AK107: 69.850001 | AL107: 358.36999
A108: Gas CCGT & Cogen | B108: GWh | C108: 139.47 | D108: 132.10001 | E108: 126.85 | F108: 127.49 | G108: 128.92999 | H108: 130.14999 | I108: 136.75999 | J108: 141.67 | K108: 141.96001 | L108: 140.22 | M108: 137.84 | N108: 147.03 | O108: 142.74001 | P108: 138.8 | Q108: 134.92 | R108: 125.11 | S108: 118.79 | T108: 121.45 | U108: 113.54 | V108: 118.4 | W108: 117.96 | X108: 547.00999 | Y108: 1874.96 | Z108: 2250.5301 | AA108: 2235 | AB108: 2146.68 | AC108: 2126.5 | AD108: 2313.6 | AE108: 2308.87 | AF108: 2226.12 | AG108: 2176.04 | AH108: 2558.01 | AI108: 2686.8401 | AJ108: 2668.69 | AK108: 2637.9599 | AL108: 2715.5801
A109: Gas CC CCS | B109: GWh | C109: 0 | D109: 0 | E109: 0 | F109: 0 | G109: 0 | H109: 0 | I109: 0 | J109: 0 | K109: 0 | L109: 0 | M109: 0 | N109: 0 | O109: 0 | P109: 0 | Q109: 0 | R109: 0 | S109: 0 | T109: 0 | U109: 0 | V109: 0 | W109: 0 | X109: 0 | Y109: 0 | Z109: 0 | AA109: 0 | AB109: 0 | AC109: 0 | AD109: 0 | AE109: 0 | AF109: 0 | AG109: 0 | AH109: 0 | AI109: 0 | AJ109: 0 | AK109: 0 | AL109: 0
A110: Gas Steam | B110: GWh | C110: 485.31 | D110: 530.09003 | E110: 563.76001 | F110: 480.70001 | G110: 518.34998 | H110: 456.64999 | I110: 493.32999 | J110: 649.96997 | K110: 811.89001 | L110: 705.41998 | M110: 535.97998 | N110: 603.65997 | O110: 671.65002 | P110: 600.77002 | Q110: 68.300003 | R110: 0 | S110: 0 | T110: 0 | U110: 0 | V110: 0 | W110: 0 | X110: 0 | Y110: 0 | Z110: 0 | AA110: 0 | AB110: 0 | AC110: 0 | AD110: 0 | AE110: 0 | AF110: 0 | AG110: 0 | AH110: 0 | AI110: 0 | AJ110: 0 | AK110: 0 | AL110: 0
A111: Distillate | B111: GWh | C111: 0 | D111: 0 | E111: 0 | F111: 0 | G111: 0 | H111: 0 | I111: 0 | J111: 0 | K111: 0 | L111: 0 | M111: 0 | N111: 0 | O111: 0 | P111: 0 | Q111: 0 | R111: 0 | S111: 0 | T111: 0 | U111: 0 | V111: 0 | W111: 0 | X111: 0 | Y111: 0 | Z111: 0 | AA111: 0 | AB111: 0 | AC111: 0 | AD111: 0 | AE111: 0 | AF111: 0 | AG111: 0 | AH111: 0 | AI111: 0 | AJ111: 0 | AK111: 0 | AL111: 0
A112: Hydro | B112: GWh | C112: 2925.7401 | D112: 2925.7401 | E112: 2925.7401 | F112: 2925.7401 | G112: 2925.7401 | H112: 2925.7401 | I112: 2925.7401 | J112: 2925.7401 | K112: 2925.7401 | L112: 2925.7401 | M112: 2925.7401 | N112: 2925.7401 | O112: 2925.7401 | P112: 2925.7401 | Q112: 2925.7401 | R112: 2925.7401 | S112: 2925.7401 | T112: 2925.7401 | U112: 2925.7401 | V112: 2925.7401 | W112: 2925.7401 | X112: 2925.7401 | Y112: 2925.7401 | Z112: 2925.7401 | AA112: 2925.7401 | AB112: 2925.7401 | AC112: 2925.7401 | AD112: 2925.7401 | AE112: 2925.7401 | AF112: 2925.7401 | AG112: 2925.7401 | AH112: 2925.7401 | AI112: 2925.7401 | AJ112: 2925.7401 | AK112: 2925.7401 | AL112: 2925.7401
A113: Wind | B113: GWh | C113: 11632.636 | D113: 13341.735 | E113: 14527.878 | F113: 15728.478 | G113: 18583.756 | H113: 20304.326 | I113: 23058.359 | J113: 25950.249 | K113: 32744.482 | L113: 41451.056 | M113: 48066.755 | N113: 50145.545 | O113: 54570.01 | P113: 58886.378 | Q113: 60731.85 | R113: 63197.856 | S113: 62767.441 | T113: 62625.578 | U113: 61961.173 | V113: 61947.492 | W113: 62046.402 | X113: 61613.483 | Y113: 61341.731 | Z113: 62293.132 | AA113: 62270.399 | AB113: 62107.797 | AC113: 62740.661 | AD113: 62774.474 | AE113: 62622.258 | AF113: 62411.053 | AG113: 62110.314 | AH113: 62096.192 | AI113: 61837.392 | AJ113: 61856.544 | AK113: 61529.294 | AL113: 61264.84
A114: Biomass | B114: GWh | C114: 783.12 | D114: 744.51001 | E114: 712 | F114: 720.02002 | G114: 725.07001 | H114: 737.95001 | I114: 766.82001 | J114: 786.97998 | K114: 783.60999 | L114: 777.97998 | M114: 753.70001 | N114: 805.27002 | O114: 789.71997 | P114: 769.57001 | Q114: 740.38 | R114: 716.14001 | S114: 696.87 | T114: 706.21002 | U114: 680.73999 | V114: 698.03003 | W114: 695.21002 | X114: 670.39001 | Y114: 671.04999 | Z114: 665.39001 | AA114: 665.73999 | AB114: 649.40002 | AC114: 623.12 | AD114: 659.21002 | AE114: 650.95001 | AF114: 634.48999 | AG114: 618.37 | AH114: 633.90002 | AI114: 633.95001 | AJ114: 621.27002 | AK114: 617.69 | AL114: 628.81
A115: Solar | B115: GWh | C115: 2608.845 | D115: 2951.9328 | E115: 3921.0602 | F115: 3945.8643 | G115: 4471.7802 | H115: 5077.0443 | I115: 5698.6964 | J115: 5750.0128 | K115: 5713.0158 | L115: 5646.9778 | M115: 5967.6768 | N115: 6103.027 | O115: 6045.5757 | P115: 5986.5961 | Q115: 5977.3419 | R115: 5936.1311 | S115: 5895.7025 | T115: 5882.3775 | U115: 5819.9703 | V115: 5810.4959 | W115: 5819.7734 | X115: 6156.629 | Y115: 6129.4747 | Z115: 6224.5419 | AA115: 6181.7105 | AB115: 6311.7269 | AC115: 6260.9248 | AD115: 6264.2991 | AE115: 6249.1093 | AF115: 6228.033 | AG115: 6198.0221 | AH115: 6196.6129 | AI115: 6170.7871 | AJ115: 6172.6983 | AK115: 6140.0418 | AL115: 6113.6518
... A122: Total | B122: GWh | C122: 53824.244 | D122: 55924.105 | E122: 58724.415 | F122: 61179.293 | G122: 59006.34 | H122: 61835.187 | I122: 67700.462 | J122: 73738.932 | K122: 81514.662 | L122: 87981.357 | M122: 88803.477 | N122: 91773.622 | O122: 96873.412 | P122: 101719.88 | Q122: 103663.7 | R122: 106069.34 | S122: 106931 | T122: 108519.35 | U122: 108887.02 | V122: 110682.04 | W122: 112597.91 | X122: 113814.38 | Y122: 113818.7 | Z122: 115337.88 | AA122: 116597.78 | AB122: 118345.75 | AC122: 119916.58 | AD122: 121262.89 | AE122: 122656.12 | AF122: 123567.1 | AG122: 124495.34 | AH122: 126868.02 | AI122: 128193.38 | AJ122: 129680.18 | AK122: 130472.73 | AL122: 132466.68
A123: Tasmania
A124: Black Coal | B124: GWh | C124: 0 | D124: 0 | E124: 0 | F124: 0 | G124: 0 | H124: 0 | I124: 0 | J124: 0 | K124: 0 | L124: 0 | M124: 0 | N124: 0 | O124: 0 | P124: 0 | Q124: 0 | R124: 0 | S124: 0 | T124: 0 | U124: 0 | V124: 0 | W124: 0 | X124: 0 | Y124: 0 | Z124: 0 | AA124: 0 | AB124: 0 | AC124: 0 | AD124: 0 | AE124: 0 | AF124: 0 | AG124: 0 | AH124: 0 | AI124: 0 | AJ124: 0 | AK124: 0 | AL124: 0
A125: Brown Coal | B125: GWh | C125: 0 | D125: 0 | E125: 0 | F125: 0 | G125: 0 | H125: 0 | I125: 0 | J125: 0 | K125: 0 | L125: 0 | M125: 0 | N125: 0 | O125: 0 | P125: 0 | Q125: 0 | R125: 0 | S125: 0 | T125: 0 | U125: 0 | V125: 0 | W125: 0 | X125: 0 | Y125: 0 | Z125: 0 | AA125: 0 | AB125: 0 | AC125: 0 | AD125: 0 | AE125: 0 | AF125: 0 | AG125: 0 | AH125: 0 | AI125: 0 | AJ125: 0 | AK125: 0 | AL125: 0
A126: Hydrogen ready | B126: GWh | C126: 0 | D126: 0 | E126: 0 | F126: 0 | G126: 0 | H126: 0 | I126: 0 | J126: 0 | K126: 0 | L126: 0 | M126: 0 | N126: 0 | O126: 0 | P126: 0 | Q126: 0 | R126: 0 | S126: 0 | T126: 0 | U126: 0 | V126: 0 | W126: 0 | X126: 0 | Y126: 0 | Z126: 0 | AA126: 0 | AB126: 0 | AC126: 0 | AD126: 0 | AE126: 0 | AF126: 0 | AG126: 0 | AH126: 0 | AI126: 0 | AJ126: 0 | AK126: 0 | AL126: 0
A127: Gas GT | B127: GWh | C127: 4.7799999 | D127: 6.58 | E127: 7.9400002 | F127: 4.2099999 | G127: 6.33 | H127: 6.05 | I127: 5.3499999 | J127: 7.1600003 | K127: 8.7399998 | L127: 9.1899999 | M127: 9.0999999 | N127: 11.1 | O127: 46.31 | P127: 6.8299999 | Q127: 1.19 | R127: 49.630001 | S127: 28.71 | T127: 43.219999 | U127: 42.28 | V127: 45.28 | W127: 53.7 | X127: 44.66 | Y127: 84.769999 | Z127: 62.320001 | AA127: 52.769999 | AB127: 53.309999 | AC127: 56.8 | AD127: 57.359999 | AE127: 70.799999 | AF127: 49.309999 | AG127: 59.170001 | AH127: 47.069999 | AI127: 60.87 | AJ127: 70.56 | AK127: 71.050002 | AL127: 52.970001
A128: Gas CCGT & Cogen | B128: GWh | C128: 110.85 | D128: 110.88 | E128: 151.52 | F128: 103.39 | G128: 178.63 | H128: 142.38 | I128: 152.75 | J128: 205.82001 | K128: 283.57001 | L128: 286.09 | M128: 270.98999 | N128: 330.51001 | O128: 53.27 | P128: 0 | Q128: 0 | R128: 0 | S128: 0 | T128: 0 | U128: 0 | V128: 0 | W128: 0 | X128: 0 | Y128: 0 | Z128: 0 | AA128: 0 | AB128: 0 | AC128: 0 | AD128: 0 | AE128: 0 | AF128: 0 | AG128: 0 | AH128: 0 | AI128: 0 | AJ128: 0 | AK128: 0 | AL128: 0
A129: Gas CC CCS | B129: GWh | C129: 0 | D129: 0 | E129: 0 | F129: 0 | G129: 0 | H129: 0 | I129: 0 | J129: 0 | K129: 0 | L129: 0 | M129: 0 | N129: 0 | O129: 0 | P129: 0 | Q129: 0 | R129: 0 | S129: 0 | T129: 0 | U129: 0 | V129: 0 | W129: 0 | X129: 0 | Y129: 0 | Z129: 0 | AA129: 0 | AB129: 0 | AC129: 0 | AD129: 0 | AE129: 0 | AF129: 0 | AG129: 0 | AH129: 0 | AI129: 0 | AJ129: 0 | AK129: 0 | AL129: 0
A130: Gas Steam | B130: GWh | C130: 0 | D130: 0 | E130: 0 | F130: 0 | G130: 0 | H130: 0 | I130: 0 | J130: 0 | K130: 0 | L130: 0 | M130: 0 | N130: 0 | O130: 0 | P130: 0 | Q130: 0 | R130: 0 | S130: 0 | T130: 0 | U130: 0 | V130: 0 | W130: 0 | X130: 0 | Y130: 0 | Z130: 0 | AA130: 0 | AB130: 0 | AC130: 0 | AD130: 0 | AE130: 0 | AF130: 0 | AG130: 0 | AH130: 0 | AI130: 0 | AJ130: 0 | AK130: 0 | AL130: 0
A131: Distillate | B131: GWh | C131: 0 | D131: 0 | E131: 0 | F131: 0 | G131: 0 | H131: 0 | I131: 0 | J131: 0 | K131: 0 | L131: 0 | M131: 0 | N131: 0 | O131: 0 | P131: 0 | Q131: 0 | R131: 0 | S131: 0 | T131: 0 | U131: 0 | V131: 0 | W131: 0 | X131: 0 | Y131: 0 | Z131: 0 | AA131: 0 | AB131: 0 | AC131: 0 | AD131: 0 | AE131: 0 | AF131: 0 | AG131: 0 | AH131: 0 | AI131: 0 | AJ131: 0 | AK131: 0 | AL131: 0
A132: Hydro | B132: GWh | C132: 10067.56 | D132: 10514.36 | E132: 9620.56 | F132: 9620.56 | G132: 9620.56 | H132: 9620.56 | I132: 9367.56 | J132: 9367.56 | K132: 9367.56 | L132: 9367.56 | M132: 9367.56 | N132: 9367.56 | O132: 9367.56 | P132: 9367.56 | Q132: 9375.56 | R132: 9375.56 | S132: 9375.56 | T132: 9375.56 | U132: 9375.56 | V132: 9375.56 | W132: 9375.56 | X132: 9375.56 | Y132: 9375.56 | Z132: 9375.56 | AA132: 9375.56 | AB132: 9375.56 | AC132: 9375.56 | AD132: 9375.56 | AE132: 9375.56 | AF132: 9375.56 | AG132: 9375.56 | AH132: 9375.56 | AI132: 9375.56 | AJ132: 9375.56 | AK132: 9375.56 | AL132: 9375.56
A133: Wind | B133: GWh | C133: 1666.2828 | D133: 1604.6627 | E133: 1646.0657 | F133: 1662.4081 | G133: 2503.0912 | H133: 2501.7787 | I133: 2550.245 | J133: 2554.151 | K133: 2557.3071 | L133: 2557.3383 | M133: 3408.9598 | N133: 3408.9598 | O133: 3408.9911 | P133: 3408.9911 | Q133: 3408.9911 | R133: 3408.9911 | S133: 3408.9911 | T133: 3408.9911 | U133: 3408.9911 | V133: 3408.9911 | W133: 3408.9911 | X133: 3408.9911 | Y133: 3408.9911 | Z133: 3408.9911 | AA133: 3408.9911 | AB133: 3408.9911 | AC133: 4277.8292 | AD133: 4277.8292 | AE133: 4277.8292 | AF133: 4277.7979 | AG133: 4929.2912 | AH133: 5902.5115 | AI133: 5902.5427 | AJ133: 5902.5427 | AK133: 5902.5427 | AL133: 5902.5427
A134: Biomass | B134: GWh | C134: 19.74 | D134: 19.74 | E134: 19.74 | F134: 19.74 | G134: 19.74 | H134: 19.74 | I134: 19.74 | J134: 19.74 | K134: 19.74 | L134: 19.74 | M134: 19.74 | N134: 19.74 | O134: 19.74 | P134: 19.74 | Q134: 44.700001 | R134: 44.700001 | S134: 44.700001 | T134: 44.700001 | U134: 44.700001 | V134: 44.700001 | W134: 44.700001 | X134: 44.700001 | Y134: 44.700001 | Z134: 44.700001 | AA134: 44.700001 | AB134: 44.700001 | AC134: 44.700001 | AD134: 44.700001 | AE134: 44.700001 | AF134: 44.700001 | AG134: 44.700001 | AH134: 44.700001 | AI134: 44.700001 | AJ134: 44.700001 | AK134: 44.700001 | AL134: 44.700001
A135: Solar | B135: GWh | C135: 0.13075009 | D135: 0.12591487 | E135: 0.12916369 | F135: 0.13044605 | G135: 0.1303429 | H135: 0.13027456 | I135: 0.13279833 | J135: 0.13300172 | K135: 0.13316607 | L135: 0.1331677 | M135: 0.13316648 | N135: 0.13316648 | O135: 0.1331677 | P135: 0.1331677 | Q135: 0.1331677 | R135: 0.1331677 | S135: 0.1331677 | T135: 0.1331677 | U135: 0.1331677 | V135: 0.1331677 | W135: 0.1331677 | X135: 0.1331677 | Y135: 0.1331677 | Z135: 0.1331677 | AA135: 0.1331677 | AB135: 0.1331677 | AC135: 0.1331677 | AD135: 0.1331677 | AE135: 0.1331677 | AF135: 0.13316673 | AG135: 0.1331677 | AH135: 0.13316699 | AI135: 0.1331677 | AJ135: 0.1331677 | AK135: 0.1331677 | AL135: 0.1331677
... A142: Total | B142: GWh | C142: 12258.154 | D142: 12679.949 | E142: 11931.891 | F142: 11955.075 | G142: 12924.563 | H142: 12939.235 | I142: 12815.775 | J142: 12939.584 | K142: 13093.04 | L142: 13164.051 | M142: 14065.474 | N142: 14193.993 | O142: 14030.004 | P142: 14023.254 | Q142: 14145.574 | R142: 14300.014 | S142: 14376.094 | T142: 14485.604 | U142: 14593.664 | V142: 14705.664 | W142: 14807.084 | X142: 14889.044 | Y142: 15032.154 | Z142: 15117.704 | AA142: 15225.154 | AB142: 15350.694 | AC142: 16303.889 | AD142: 16410.262 | AE142: 16528.45 | AF142: 16613.176 | AG142: 17383.23 | AH142: 18452.306 | AI142: 18571.556 | AJ142: 18685.12 | AK142: 18788.517 | AL142: 18874.665
...

Sheet CoalRetirements
A1: Coal Plant Installed Capacity (MW)
A2: Plant | B2: Type | C2: State | D2: 2025 | E2: 2026 | F2: 2027 | G2: 2028 | H2: 2029 | I2: 2030 | J2: 2031 | K2: 2032 | L2: 2033 | M2: 2034 | N2: 2035 | O2: 2036 | P2: 2037 | Q2: 2038 | R2: 2039 | S2: 2040 | T2: 2041 | U2: 2042 | V2: 2043 | W2: 2044 | X2: 2045 | Y2: 2046 | Z2: 2047 | AA2: 2048 | AB2: 2049 | AC2: 2050 | AD2: 2051 | AE2: 2052 | AF2: 2053 | AG2: 2054 | AH2: 2055 | AI2: 2056 | AJ2: 2057 | AK2: 2058 | AL2: 2059 | AM2: 2060
A3: LYA | B3: Brown Coal | C3: Victoria | D3: 2031.12 | E3: 2031.12 | F3: 2031.12 | G3: 2031.12 | H3: 2031.12 | I3: 2031.12 | J3: 2031.12 | K3: 2031.12 | L3: 2031.12 | M3: 2031.12 | N3: 1523.34
A4: LYB | B4: Brown Coal | C4: Victoria | D4: 984.4 | E4: 984.4 | F4: 984.4 | G4: 984.4 | H4: 984.4 | I4: 984.4 | J4: 984.4 | K4: 984.4 | L4: 984.4 | M4: 984.4 | N4: 984.4 | O4: 984.4 | P4: 984.4 | Q4: 984.4 | R4: 984.4 | S4: 984.4 | T4: 984.4 | U4: 984.4 | V4: 984.4 | W4: 984.4 | X4: 984.4 | Y4: 984.4 | Z4: 984.4
A5: YALL | B5: Brown Coal | C5: Victoria | D5: 1375.2 | E5: 1375.2 | F5: 1375.2 | G5: 1375.2 | H5: 1375.2
A6: BAYSWATR | B6: Black Coal | C6: New South Wales | D6: 2481.6 | E6: 2481.6 | F6: 2481.6 | G6: 2481.6 | H6: 2481.6 | I6: 2481.6 | J6: 2481.6 | K6: 1240.8
A7: ERARING | B7: Black Coal | C7: New South Wales | D7: 2707.2 | E7: 1353.6 | F7: 1353.6 | G7: 1353.6
A8: MTPIPER | B8: Black Coal | C8: New South Wales | D8: 1330 | E8: 1330 | F8: 1330 | G8: 1330 | H8: 1330 | I8: 1330 | J8: 1330 | K8: 1330 | L8: 1330 | M8: 1330 | N8: 1330 | O8: 1330 | P8: 1330 | Q8: 1330 | R8: 1330 | S8: 1330
A9: LIDDELL | B9: Black Coal | C9: New South Wales
A10: VALESPNT | B10: Black Coal | C10: New South Wales | D10: 1254 | E10: 1254 | F10: 1254 | G10: 1254 | H10: 1254 | I10: 1254 | J10: 1254 | K10: 1254 | L10: 1254
A11: MILLMERN | B11: Black Coal | C11: Queensland South | D11: 800.88 | E11: 800.88 | F11: 800.88 | G11: 800.88 | H11: 800.88 | I11: 800.88 | J11: 800.88 | K11: 800.88 | L11: 800.88 | M11: 800.88 | N11: 800.88 | O11: 800.88 | P11: 800.88 | Q11: 800.88 | R11: 800.88 | S11: 800.88 | T11: 800.88 | U11: 800.88 | V11: 800.88 | W11: 800.88 | X11: 800.88 | Y11: 800.88 | Z11: 800.88 | AA11: 800.88 | AB11: 800.88 | AC11: 800.88
A12: TARONG | B12: Black Coal | C12: Queensland South | D12: 1288 | E12: 1288 | F12: 1288 | G12: 1288 | H12: 1288 | I12: 1288 | J12: 1288 | K12: 1288 | L12: 1288 | M12: 1288 | N12: 1288 | O12: 644
A13: TARONGN | B13: Black Coal | C13: Queensland South | D13: 416.42 | E13: 416.42 | F13: 416.42 | G13: 416.42 | H13: 416.42 | I13: 416.42 | J13: 416.42 | K13: 416.42 | L13: 416.42 | M13: 416.42 | N13: 416.42 | O13: 416.42
A14: KoganCrk | B14: Black Coal | C14: Queensland South | D14: 677.04 | E14: 677.04 | F14: 677.04 | G14: 677.04 | H14: 677.04 | I14: 677.04 | J14: 677.04 | K14: 677.04 | L14: 677.04 | M14: 677.04 | N14: 677.04 | O14: 677.04 | P14: 677.04 | Q14: 677.04 | R14: 677.04 | S14: 677.04 | T14: 677.04
A15: CALLIDEC | B15: Black Coal | C15: Queensland Central | D15: 789.6 | E15: 789.6 | F15: 789.6 | G15: 789.6 | H15: 789.6 | I15: 789.6 | J15: 789.6 | K15: 789.6 | L15: 789.6 | M15: 789.6 | N15: 789.6 | O15: 789.6 | P15: 789.6 | Q15: 789.6 | R15: 789.6 | S15: 789.6 | T15: 789.6 | U15: 789.6 | V15: 789.6 | W15: 789.6 | X15: 789.6 | Y15: 789.6 | Z15: 789.6 | AA15: 789.6 | AB15: 789.6 | AC15: 789.6
A16: CALLIDEB | B16: Black Coal | C16: Queensland Central | D16: 637 | E16: 637 | F16: 637 | G16: 637 | H16: 637 | I16: 637
A17: STANWELL | B17: Black Coal | C17: Queensland Central | D17: 1328.6 | E17: 1328.6 | F17: 1328.6 | G17: 1328.6 | H17: 1328.6 | I17: 1328.6 | J17: 1328.6 | K17: 1328.6 | L17: 1328.6 | M17: 1328.6 | N17: 1328.6 | O17: 1328.6 | P17: 1328.6 | Q17: 1328.6 | R17: 1328.6 | S17: 1328.6 | T17: 1328.6 | U17: 1328.6 | V17: 996.45 | W17: 664.3 | X17: 332.15
A18: GPS | B18: Black Coal | C18: Queensland Central | D18: 1545.6 | E18: 1545.6 | F18: 1545.6 | G18: 1545.6 | H18: 1545.6 | I18: 1545.6 | J18: 1545.6 | K18: 1545.6 | L18: 1545.6 | M18: 1545.6

Sheet NEM Emissions
A1: Emissions
A2: Financial Year | C2: 2025 | D2: 2026 | E2: 2027 | F2: 2028 | G2: 2029 | H2: 2030 | I2: 2031 | J2: 2032 | K2: 2033 | L2: 2034 | M2: 2035 | N2: 2036 | O2: 2037 | P2: 2038 | Q2: 2039 | R2: 2040 | S2: 2041 | T2: 2042 | U2: 2043 | V2: 2044 | W2: 2045 | X2: 2046 | Y2: 2047 | Z2: 2048 | AA2: 2049 | AB2: 2050 | AC2: 2051 | AD2: 2052 | AE2: 2053 | AF2: 2054 | AG2: 2055 | AH2: 2056 | AI2: 2057 | AJ2: 2058 | AK2: 2059 | AL2: 2060
A3: Queensland South
A4: Black Coal | B4: Mt CO2e | C4: 16.72849 | D4: 16.998495 | E4: 16.282403 | F4: 15.284321 | G4: 14.441741 | H4: 14.374529 | I4: 15.462668 | J4: 16.405623 | K4: 17.390672 | L4: 17.528387 | M4: 17.65988 | N4: 16.055474 | O4: 11.684445 | P4: 8.5751973 | Q4: 8.6385271 | R4: 8.5503541 | S4: 8.2220674 | T4: 6.5598017 | U4: 4.7991222 | V4: 4.8113199 | W4: 4.8037376 | X4: 4.6839811 | Y4: 4.6059623 | Z4: 4.6870748 | AA4: 4.7039644 | AB4: 4.6610461 | AC4: 1.602567 | AD4: 0 | AE4: 0 | AF4: 0 | AG4: 0 | AH4: 0 | AI4: 0 | AJ4: 0 | AK4: 0 | AL4: 0
A5: Brown Coal | B5: Mt CO2e | C5: 0 | D5: 0 | E5: 0 | F5: 0 | G5: 0 | H5: 0 | I5: 0 | J5: 0 | K5: 0 | L5: 0 | M5: 0 | N5: 0 | O5: 0 | P5: 0 | Q5: 0 | R5: 0 | S5: 0 | T5: 0 | U5: 0 | V5: 0 | W5: 0 | X5: 0 | Y5: 0 | Z5: 0 | AA5: 0 | AB5: 0 | AC5: 0 | AD5: 0 | AE5: 0 | AF5: 0 | AG5: 0 | AH5: 0 | AI5: 0 | AJ5: 0 | AK5: 0 | AL5: 0
A6: Hydrogen ready | B6: Mt CO2e | C6: 0 | D6: 0 | E6: 0 | F6: 0 | G6: 0.32325771 | H6: 0.29900237 | I6: 0.44941122 | J6: 0.63432289 | K6: 0.77503143 | L6: 0.87252998 | M6: 0 | N6: 0 | O6: 0 | P6: 0 | Q6: 0 | R6: 0 | S6: 0 | T6: 0 | U6: 0 | V6: 0 | W6: 0 | X6: 0 | Y6: 0 | Z6: 0 | AA6: 0 | AB6: 0 | AC6: 0 | AD6: 0 | AE6: 0 | AF6: 0 | AG6: 0 | AH6: 0 | AI6: 0 | AJ6: 0 | AK6: 0 | AL6: 0
A7: Gas GT | B7: Mt CO2e | C7: 0.0023706599 | D7: 0.00519045 | E7: 0.01173613 | F7: 0.01763729 | G7: 0.0088556399 | H7: 0.0045614401 | I7: 0.00852622 | J7: 0.02452796 | K7: 0.040076861 | L7: 0.06263465 | M7: 0.29954969 | N7: 0.33139067 | O7: 0.37097065 | P7: 0.43762439 | Q7: 0.41605856 | R7: 0.46050297 | S7: 0.47517195 | T7: 0.5165231 | U7: 0.54906574 | V7: 0.59850782 | W7: 0.63188918 | X7: 0.82586599 | Y7: 0.41676543 | Z7: 0.44218766 | AA7: 0.47007 | AB7: 0.44609217 | AC7: 0.45640358 | AD7: 0.50721008 | AE7: 0.50253715 | AF7: 0.4935591 | AG7: 0.48504318 | AH7: 0.48875396 | AI7: 0 | AJ7: 0 | AK7: 0 | AL7: 0
A8: Gas CCGT & Cogen | B8: Mt CO2e | C8: 0.30174676 | D8: 0.46514645 | E8: 0.56278613 | F8: 0.29435579 | G8: 0.11549342 | H8: 0.097690222 | I8: 0.16519084 | J8: 0.28527673 | K8: 0.36265635 | L8: 0.44060923 | M8: 1.2065022 | N8: 1.3128519 | O8: 1.432536 | P8: 1.5316256 | Q8: 1.5198262 | R8: 1.4801882 | S8: 1.1530242 | T8: 1.1948127 | U8: 1.2414747 | V8: 1.262701 | W8: 1.3039305 | X8: 0.096337934 | Y8: 0 | Z8: 0 | AA8: 0 | AB8: 0 | AC8: 0 | AD8: 0 | AE8: 0 | AF8: 0 | AG8: 0 | AH8: 0 | AI8: 0 | AJ8: 0 | AK8: 0 | AL8: 0
A9: Gas CC CCS | B9: Mt CO2e | C9: 0 | D9: 0 | E9: 0 | F9: 0 | G9: 0 | H9: 0 | I9: 0 | J9: 0 | K9: 0 | L9: 0 | M9: 0 | N9: 0 | O9: 0 | P9: 0 | Q9: 0 | R9: 0 | S9: 0 | T9: 0 | U9: 0 | V9: 0 | W9: 0 | X9: 0 | Y9: 0 | Z9: 0 | AA9: 0 | AB9: 0 | AC9: 0 | AD9: 0 | AE9: 0 | AF9: 0 | AG9: 0 | AH9: 0 | AI9: 0 | AJ9: 0 | AK9: 0 | AL9: 0
A10: Gas Steam | B10: Mt CO2e | C10: 0 | D10: 0 | E10: 0 | F10: 0 | G10: 0 | H10: 0 | I10: 0 | J10: 0 | K10: 0 | L10: 0 | M10: 0 | N10: 0 | O10: 0 | P10: 0 | Q10: 0 | R10: 0 | S10: 0 | T10: 0 | U10: 0 | V10: 0 | W10: 0 | X10: 0 | Y10: 0 | Z10: 0 | AA10: 0 | AB10: 0 | AC10: 0 | AD10: 0 | AE10: 0 | AF10: 0 | AG10: 0 | AH10: 0 | AI10: 0 | AJ10: 0 | AK10: 0 | AL10: 0
A11: Distillate | B11: Mt CO2e | C11: 0 | D11: 0 | E11: 0 | F11: 0 | G11: 0 | H11: 0 | I11: 0 | J11: 0 | K11: 0 | L11: 0 | M11: 0 | N11: 0 | O11: 0 | P11: 0 | Q11: 0 | R11: 0 | S11: 0 | T11: 0 | U11: 0 | V11: 0 | W11: 0 | X11: 0 | Y11: 0 | Z11: 0 | AA11: 0 | AB11: 0 | AC11: 0 | AD11: 0 | AE11: 0 | AF11: 0 | AG11: 0 | AH11: 0 | AI11: 0 | AJ11: 0 | AK11: 0 | AL11: 0
A12: Hydro | B12: Mt CO2e | C12: 0 | D12: 0 | E12: 0 | F12: 0 | G12: 0 | H12: 0 | I12: 0 | J12: 0 | K12: 0 | L12: 0 | M12: 0 | N12: 0 | O12: 0 | P12: 0 | Q12: 0 | R12: 0 | S12: 0 | T12: 0 | U12: 0 | V12: 0 | W12: 0 | X12: 0 | Y12: 0 | Z12: 0 | AA12: 0 | AB12: 0 | AC12: 0 | AD12: 0 | AE12: 0 | AF12: 0 | AG12: 0 | AH12: 0 | AI12: 0 | AJ12: 0 | AK12: 0 | AL12: 0
A13: Wind | B13: Mt CO2e | C13: 0 | D13: 0 | E13: 0 | F13: 0 | G13: 0 | H13: 0 | I13: 0 | J13: 0 | K13: 0 | L13: 0 | M13: 0 | N13: 0 | O13: 0 | P13: 0 | Q13: 0 | R13: 0 | S13: 0 | T13: 0 | U13: 0 | V13: 0 | W13: 0 | X13: 0 | Y13: 0 | Z13: 0 | AA13: 0 | AB13: 0 | AC13: 0 | AD13: 0 | AE13: 0 | AF13: 0 | AG13: 0 | AH13: 0 | AI13: 0 | AJ13: 0 | AK13: 0 | AL13: 0
A14: Biomass | B14: Mt CO2e | C14: 0 | D14: 0 | E14: 0 | F14: 0 | G14: 0 | H14: 0 | I14: 0 | J14: 0 | K14: 0 | L14: 0 | M14: 0 | N14: 0 | O14: 0 | P14: 0 | Q14: 0 | R14: 0 | S14: 0 | T14: 0 | U14: 0 | V14: 0 | W14: 0 | X14: 0 | Y14: 0 | Z14: 0 | AA14: 0 | AB14: 0 | AC14: 0 | AD14: 0 | AE14: 0 | AF14: 0 | AG14: 0 | AH14: 0 | AI14: 0 | AJ14: 0 | AK14: 0 | AL14: 0
A15: Solar | B15: Mt CO2e | C15: 0 | D15: 0 | E15: 0 | F15: 0 | G15: 0 | H15: 0 | I15: 0 | J15: 0 | K15: 0 | L15: 0 | M15: 0 | N15: 0 | O15: 0 | P15: 0 | Q15: 0 | R15: 0 | S15: 0 | T15: 0 | U15: 0 | V15: 0 | W15: 0 | X15: 0 | Y15: 0 | Z15: 0 | AA15: 0 | AB15: 0 | AC15: 0 | AD15: 0 | AE15: 0 | AF15: 0 | AG15: 0 | AH15: 0 | AI15: 0 | AJ15: 0 | AK15: 0 | AL15: 0
... A19: Total | B19: Mt CO2e | C19: 17.032607 | D19: 17.468831 | E19: 16.856925 | F19: 15.596314 | G19: 14.889348 | H19: 14.775783 | I19: 16.085796 | J19: 17.349751 | K19: 18.568436 | L19: 18.904161 | M19: 19.165931 | N19: 17.699717 | O19: 13.487952 | P19: 10.544447 | Q19: 10.574412 | R19: 10.491045 | S19: 9.8502636 | T19: 8.2711375 | U19: 6.5896626 | V19: 6.6725288 | W19: 6.7395573 | X19: 5.606185 | Y19: 5.0227277 | Z19: 5.1292625 | AA19: 5.1740344 | AB19: 5.1071383 | AC19: 2.0589705 | AD19: 0.50721008 | AE19: 0.50253715 | AF19: 0.4935591 | AG19: 0.48504318 | AH19: 0.48875396 | AI19: 0 | AJ19: 0 | AK19: 0 | AL19: 0
A20: Queensland North
A21: Black Coal | B21: Mt CO2e | C21: 0 | D21: 0 | E21: 0 | F21: 0 | G21: 0 | H21: 0 | I21: 0 | J21: 0 | K21: 0 | L21: 0 | M21: 0 | N21: 0 | O21: 0 | P21: 0 | Q21: 0 | R21: 0 | S21: 0 | T21: 0 | U21: 0 | V21: 0 | W21: 0 | X21: 0 | Y21: 0 | Z21: 0 | AA21: 0 | AB21: 0 | AC21: 0 | AD21: 0 | AE21: 0 | AF21: 0 | AG21: 0 | AH21: 0 | AI21: 0 | AJ21: 0 | AK21: 0 | AL21: 0
A22: Brown Coal | B22: Mt CO2e | C22: 0 | D22: 0 | E22: 0 | F22: 0 | G22: 0 | H22: 0 | I22: 0 | J22: 0 | K22: 0 | L22: 0 | M22: 0 | N22: 0 | O22: 0 | P22: 0 | Q22: 0 | R22: 0 | S22: 0 | T22: 0 | U22: 0 | V22: 0 | W22: 0 | X22: 0 | Y22: 0 | Z22: 0 | AA22: 0 | AB22: 0 | AC22: 0 | AD22: 0 | AE22: 0 | AF22: 0 | AG22: 0 | AH22: 0 | AI22: 0 | AJ22: 0 | AK22: 0 | AL22: 0
A23: Coal CCS | B23: Mt CO2e | C23: 0 | D23: 0 | E23: 0 | F23: 0 | G23: 0 | H23: 0 | I23: 0 | J23: 0 | K23: 0 | L23: 0 | M23: 0 | N23: 0 | O23: 0 | P23: 0 | Q23: 0 | R23: 0 | S23: 0 | T23: 0 | U23: 0 | V23: 0 | W23: 0 | X23: 0 | Y23: 0 | Z23: 0 | AA23: 0 | AB23: 0 | AC23: 0 | AD23: 0 | AE23: 0 | AF23: 0 | AG23: 0 | AH23: 0 | AI23: 0 | AJ23: 0 | AK23: 0 | AL23: 0
A24: Gas GT | B24: Mt CO2e | C24: 0.0017611 | D24: 0.00161904 | E24: 0.0017497399 | F24: 0.00159418 | G24: 0.00141837 | H24: 0.00119212 | I24: 0.00290885 | J24: 0.0078290902 | K24: 0.0069194902 | L24: 0.0065626201 | M24: 0.0064014899 | N24: 0.0066876202 | O24: 0.0067995798 | P24: 0.0066078498 | Q24: 0.0064827799 | R24: 0.0058887198 | S24: 0.0066833299 | T24: 0.0067700102 | U24: 0.0061250298 | V24: 0.0042187301 | W24: 0 | X24: 0 | Y24: 0 | Z24: 0 | AA24: 0 | AB24: 0 | AC24: 0 | AD24: 0 | AE24: 0 | AF24: 0 | AG24: 0 | AH24: 0 | AI24: 0 | AJ24: 0 | AK24: 0 | AL24: 0
A25: Gas CCGT & Cogen | B25: Mt CO2e | C25: 0.063686729 | D25: 0.059466659 | E25: 0.064298489 | F25: 0.056064169 | G25: 0.043102311 | H25: 0.03508563 | I25: 0.10517731 | J25: 0.2048503 | K25: 0.22369814 | L25: 0.22118023 | M25: 0.26636443 | N25: 0.28242683 | O25: 0.2798928 | P25: 0.27904059 | Q25: 0.27422745 | R25: 0.25028879 | S25: 0.21111563 | T25: 0.2088243 | U25: 0.21423122 | V25: 0.11058204 | W25: 0.079272223 | X25: 0.087397353 | Y25: 0 | Z25: 0 | AA25: 0 | AB25: 0 | AC25: 0 | AD25: 0 | AE25: 0 | AF25: 0 | AG25: 0 | AH25: 0 | AI25: 0 | AJ25: 0 | AK25: 0 | AL25: 0
A26: Gas CC CCS | B26: Mt CO2e | C26: 0 | D26: 0 | E26: 0 | F26: 0 | G26: 0 | H26: 0 | I26: 0 | J26: 0 | K26: 0 | L26: 0 | M26: 0 | N26: 0 | O26: 0 | P26: 0 | Q26: 0 | R26: 0 | S26: 0 | T26: 0 | U26: 0 | V26: 0 | W26: 0 | X26: 0 | Y26: 0 | Z26: 0 | AA26: 0 | AB26: 0 | AC26: 0 | AD26: 0 | AE26: 0 | AF26: 0 | AG26: 0 | AH26: 0 | AI26: 0 | AJ26: 0 | AK26: 0 | AL26: 0
A27: Gas Steam | B27: Mt CO2e | C27: 0 | D27: 0 | E27: 0 | F27: 0 | G27: 0 | H27: 0 | I27: 0 | J27: 0 | K27: 0 | L27: 0 | M27: 0 | N27: 0 | O27: 0 | P27: 0 | Q27: 0 | R27: 0 | S27: 0 | T27: 0 | U27: 0 | V27: 0 | W27: 0 | X27: 0 | Y27: 0 | Z27: 0 | AA27: 0 | AB27: 0 | AC27: 0 | AD27: 0 | AE27: 0 | AF27: 0 | AG27: 0 | AH27: 0 | AI27: 0 | AJ27: 0 | AK27: 0 | AL27: 0
A28: Distillate | B28: Mt CO2e | C28: 0 | D28: 0 | E28: 0 | F28: 0 | G28: 0 | H28: 0 | I28: 0 | J28: 0 | K28: 0 | L28: 0 | M28: 0 | N28: 0 | O28: 0 | P28: 0 | Q28: 0 | R28: 0 | S28: 0 | T28: 0 | U28: 0 | V28: 0 | W28: 0 | X28: 0 | Y28: 0 | Z28: 0 | AA28: 0 | AB28: 0 | AC28: 0 | AD28: 0 | AE28: 0 | AF28: 0 | AG28: 0 | AH28: 0 | AI28: 0 | AJ28: 0 | AK28: 0 | AL28: 0
A29: Hydro | B29: Mt CO2e | C29: 0 | D29: 0 | E29: 0 | F29: 0 | G29: 0 | H29: 0 | I29: 0 | J29: 0 | K29: 0 | L29: 0 | M29: 0 | N29: 0 | O29: 0 | P29: 0 | Q29: 0 | R29: 0 | S29: 0 | T29: 0 | U29: 0 | V29: 0 | W29: 0 | X29: 0 | Y29: 0 | Z29: 0 | AA29: 0 | AB29: 0 | AC29: 0 | AD29: 0 | AE29: 0 | AF29: 0 | AG29: 0 | AH29: 0 | AI29: 0 | AJ29: 0 | AK29: 0 | AL29: 0
A30: Wind | B30: Mt CO2e | C30: 0 | D30: 0 | E30: 0 | F30: 0 | G30: 0 | H30: 0 | I30: 0 | J30: 0 | K30: 0 | L30: 0 | M30: 0 | N30: 0 | O30: 0 | P30: 0 | Q30: 0 | R30: 0 | S30: 0 | T30: 0 | U30: 0 | V30: 0 | W30: 0 | X30: 0 | Y30: 0 | Z30: 0 | AA30: 0 | AB30: 0 | AC30: 0 | AD30: 0 | AE30: 0 | AF30: 0 | AG30: 0 | AH30: 0 | AI30: 0 | AJ30: 0 | AK30: 0 | AL30: 0
A31: Biomass | B31: Mt CO2e | C31: 0 | D31: 0 | E31: 0 | F31: 0 | G31: 0 | H31: 0 | I31: 0 | J31: 0 | K31: 0 | L31: 0 | M31: 0 | N31: 0 | O31: 0 | P31: 0 | Q31: 0 | R31: 0 | S31: 0 | T31: 0 | U31: 0 | V31: 0 | W31: 0 | X31: 0 | Y31: 0 | Z31: 0 | AA31: 0 | AB31: 0 | AC31: 0 | AD31: 0 | AE31: 0 | AF31: 0 | AG31: 0 | AH31: 0 | AI31: 0 | AJ31: 0 | AK31: 0 | AL31: 0
A32: Solar | B32: Mt CO2e | C32: 0 | D32: 0 | E32: 0 | F32: 0 | G32: 0 | H32: 0 | I32: 0 | J32: 0 | K32: 0 | L32: 0 | M32: 0 | N32: 0 | O32: 0 | P32: 0 | Q32: 0 | R32: 0 | S32: 0 | T32: 0 | U32: 0 | V32: 0 | W32: 0 | X32: 0 | Y32: 0 | Z32: 0 | AA32: 0 | AB32: 0 | AC32: 0 | AD32: 0 | AE32: 0 | AF32: 0 | AG32: 0 | AH32: 0 | AI32: 0 | AJ32: 0 | AK32: 0 | AL32: 0
... A36: Total | B36: Mt CO2e | C36: 0.065447829 | D36: 0.061085699 | E36: 0.066048229 | F36: 0.057658349 | G36: 0.044520681 | H36: 0.03627775 | I36: 0.10808616 | J36: 0.21267939 | K36: 0.23061763 | L36: 0.22774285 | M36: 0.27276592 | N36: 0.28911445 | O36: 0.28669238 | P36: 0.28564844 | Q36: 0.28071023 | R36: 0.2561775 | S36: 0.21779896 | T36: 0.21559431 | U36: 0.22035625 | V36: 0.11480077 | W36: 0.079272223 | X36: 0.087397353 | Y36: 0 | Z36: 0 | AA36: 0 | AB36: 0 | AC36: 0 | AD36: 0 | AE36: 0 | AF36: 0 | AG36: 0 | AH36: 0 | AI36: 0 | AJ36: 0 | AK36: 0 | AL36: 0
A37: Queensland Central
A38: Black Coal | B38: Mt CO2e | C38: 18.979612 | D38: 17.444775 | E38: 16.740052 | F38: 15.434955 | G38: 18.20938 | H38: 18.113799 | I38: 17.326745 | J38: 14.712963 | K38: 15.552034 | L38: 16.020845 | M38: 11.594345 | N38: 10.848711 | O38: 11.038346 | P38: 11.003555 | Q38: 10.071501 | R38: 10.312331 | S38: 8.9290277 | T38: 10.180698 | U38: 8.8066022 | V38: 7.9806072 | W38: 6.2209972 | X38: 5.0941439 | Y38: 4.683493 | Z38: 4.7392741 | AA38: 4.7085784 | AB38: 4.6839788 | AC38: 2.4743418 | AD38: 0 | AE38: 0 | AF38: 0 | AG38: 0 | AH38: 0 | AI38: 0 | AJ38: 0 | AK38: 0 | AL38: 0
A39: Brown Coal | B39: Mt CO2e | C39: 0 | D39: 0 | E39: 0 | F39: 0 | G39: 0 | H39: 0 | I39: 0 | J39: 0 | K39: 0 | L39: 0 | M39: 0 | N39: 0 | O39: 0 | P39: 0 | Q39: 0 | R39: 0 | S39: 0 | T39: 0 | U39: 0 | V39: 0 | W39: 0 | X39: 0 | Y39: 0 | Z39: 0 | AA39: 0 | AB39: 0 | AC39: 0 | AD39: 0 | AE39: 0 | AF39: 0 | AG39: 0 | AH39: 0 | AI39: 0 | AJ39: 0 | AK39: 0 | AL39: 0
A40: Coal CCS | B40: Mt CO2e | C40: 0 | D40: 0 | E40: 0 | F40: 0 | G40: 0 | H40: 0 | I40: 0 | J40: 0 | K40: 0 | L40: 0 | M40: 0 | N40: 0 | O40: 0 | P40: 0 | Q40: 0 | R40: 0 | S40: 0 | T40: 0 | U40: 0 | V40: 0 | W40: 0 | X40: 0 | Y40: 0 | Z40: 0 | AA40: 0 | AB40: 0 | AC40: 0 | AD40: 0 | AE40: 0 | AF40: 0 | AG40: 0 | AH40: 0 | AI40: 0 | AJ40: 0 | AK40: 0 | AL40: 0
A41: Gas GT | B41: Mt CO2e | C41: 0.00103598 | D41: 0.00021754 | E41: 0.00090033 | F41: 0.00072164999 | G41: 0.00070987997 | H41: 0.00041014001 | I41: 0.00370836 | J41: 0.0084795701 | K41: 0.01066681 | L41: 0.01417917 | M41: 0 | N41: 0 | O41: 0 | P41: 0 | Q41: 0 | R41: 0 | S41: 0 | T41: 0 | U41: 0 | V41: 0 | W41: 0 | X41: 0 | Y41: 0 | Z41: 0 | AA41: 0 | AB41: 0 | AC41: 0 | AD41: 0 | AE41: 0 | AF41: 0 | AG41: 0 | AH41: 0 | AI41: 0 | AJ41: 0 | AK41: 0 | AL41: 0
A42: Gas CCGT & Cogen | B42: Mt CO2e | C42: 0.22753513 | D42: 0.20891649 | E42: 0.20387366 | F42: 0.19060852 | G42: 0.19034096 | H42: 0.1879531 | I42: 0.20786268 | J42: 0.24033817 | K42: 0.26052672 | L42: 0.26735994 | M42: 0.33021892 | N42: 0.39002028 | O42: 0.58000005 | P42: 0.59178322 | Q42: 0.60277655 | R42: 0.59668736 | S42: 0.5634432 | T42: 0.50235668 | U42: 0.50157659 | V42: 0.53096663 | W42: 0.56631498 | X42: 0.60337986 | Y42: 0.60086621 | Z42: 0.60195893 | AA42: 0.61604169 | AB42: 0.56736871 | AC42: 0.28519648 | AD42: 0.30369868 | AE42: 0.30794768 | AF42: 0.29764566 | AG42: 0.28710533 | AH42: 0.29401329 | AI42: 0.3176331 | AJ42: 0.30165025 | AK42: 0.29365579 | AL42: 0.29454954
A43: Gas CC CCS | B43: Mt CO2e | C43: 0 | D43: 0 | E43: 0 | F43: 0 | G43: 0 | H43: 0 | I43: 0 | J43: 0 | K43: 0 | L43: 0 | M43: 0 | N43: 0 | O43: 0 | P43: 0 | Q43: 0 | R43: 0 | S43: 0 | T43: 0 | U43: 0 | V43: 0 | W43: 0 | X43: 0 | Y43: 0 | Z43: 0 | AA43: 0 | AB43: 0 | AC43: 0 | AD43: 0 | AE43: 0 | AF43: 0 | AG43: 0 | AH43: 0 | AI43: 0 | AJ43: 0 | AK43: 0 | AL43: 0
A44: Gas Steam | B44: Mt CO2e | C44: 0 | D44: 0 | E44: 0 | F44: 0 | G44: 0 | H44: 0 | I44: 0 | J44: 0 | K44: 0 | L44: 0 | M44: 0 | N44: 0 | O44: 0 | P44: 0 | Q44: 0 | R44: 0 | S44: 0 | T44: 0 | U44: 0 | V44: 0 | W44: 0 | X44: 0 | Y44: 0 | Z44: 0 | AA44: 0 | AB44: 0 | AC44: 0 | AD44: 0 | AE44: 0 | AF44: 0 | AG44: 0 | AH44: 0 | AI44: 0 | AJ44: 0 | AK44: 0 | AL44: 0
A45: Distillate | B45: Mt CO2e | C45: 0 | D45: 0 | E45: 0 | F45: 0 | G45: 0 | H45: 0 | I45: 0 | J45: 0 | K45: 0 | L45: 0 | M45: 0 | N45: 0 | O45: 0 | P45: 0 | Q45: 0 | R45: 0 | S45: 0 | T45: 0 | U45: 0 | V45: 0 | W45: 0 | X45: 0 | Y45: 0 | Z45: 0 | AA45: 0 | AB45: 0 | AC45: 0 | AD45: 0 | AE45: 0 | AF45: 0 | AG45: 0 | AH45: 0 | AI45: 0 | AJ45: 0 | AK45: 0 | AL45: 0
A46: Hydro | B46: Mt CO2e | C46: 0 | D46: 0 | E46: 0 | F46: 0 | G46: 0 | H46: 0 | I46: 0 | J46: 0 | K46: 0 | L46: 0 | M46: 0 | N46: 0 | O46: 0 | P46: 0 | Q46: 0 | R46: 0 | S46: 0 | T46: 0 | U46: 0 | V46: 0 | W46: 0 | X46: 0 | Y46: 0 | Z46: 0 | AA46: 0 | AB46: 0 | AC46: 0 | AD46: 0 | AE46: 0 | AF46: 0 | AG46: 0 | AH46: 0 | AI46: 0 | AJ46: 0 | AK46: 0 | AL46: 0
A47: Wind | B47: Mt CO2e | C47: 0 | D47: 0 | E47: 0 | F47: 0 | G47: 0 | H47: 0 | I47: 0 | J47: 0 | K47: 0 | L47: 0 | M47: 0 | N47: 0 | O47: 0 | P47: 0 | Q47: 0 | R47: 0 | S47: 0 | T47: 0 | U47: 0 | V47: 0 | W47: 0 | X47: 0 | Y47: 0 | Z47: 0 | AA47: 0 | AB47: 0 | AC47: 0 | AD47: 0 | AE47: 0 | AF47: 0 | AG47: 0 | AH47: 0 | AI47: 0 | AJ47: 0 | AK47: 0 | AL47: 0
A48: Biomass | B48: Mt CO2e | C48: 0 | D48: 0 | E48: 0 | F48: 0 | G48: 0 | H48: 0 | I48: 0 | J48: 0 | K48: 0 | L48: 0 | M48: 0 | N48: 0 | O48: 0 | P48: 0 | Q48: 0 | R48: 0 | S48: 0 | T48: 0 | U48: 0 | V48: 0 | W48: 0 | X48: 0 | Y48: 0 | Z48: 0 | AA48: 0 | AB48: 0 | AC48: 0 | AD48: 0 | AE48: 0 | AF48: 0 | AG48: 0 | AH48: 0 | AI48: 0 | AJ48: 0 | AK48: 0 | AL48: 0
A49: Solar | B49: Mt CO2e | C49: 0 | D49: 0 | E49: 0 | F49: 0 | G49: 0 | H49: 0 | I49: 0 | J49: 0 | K49: 0 | L49: 0 | M49: 0 | N49: 0 | O49: 0 | P49: 0 | Q49: 0 | R49: 0 | S49: 0 | T49: 0 | U49: 0 | V49: 0 | W49: 0 | X49: 0 | Y49: 0 | Z49: 0 | AA49: 0 | AB49: 0 | AC49: 0 | AD49: 0 | AE49: 0 | AF49: 0 | AG49: 0 | AH49: 0 | AI49: 0 | AJ49: 0 | AK49: 0 | AL49: 0
... A53: Total | B53: Mt CO2e | C53: 19.208183 | D53: 17.653909 | E53: 16.944826 | F53: 15.626286 | G53: 18.400431 | H53: 18.302162 | I53: 17.538316 | J53: 14.961781 | K53: 15.823228 | L53: 16.302384 | M53: 11.924564 | N53: 11.238732 | O53: 11.618346 | P53: 11.595338 | Q53: 10.674278 | R53: 10.909019 | S53: 9.4924708 | T53: 10.683055 | U53: 9.3081788 | V53: 8.5115738 | W53: 6.7873122 | X53: 5.6975238 | Y53: 5.2843592 | Z53: 5.341233 | AA53: 5.3246201 | AB53: 5.2513476 | AC53: 2.7595382 | AD53: 0.30369868 | AE53: 0.30794768 | AF53: 0.29764566 | AG53: 0.28710533 | AH53: 0.29401329 | AI53: 0.3176331 | AJ53: 0.30165025 | AK53: 0.29365579 | AL53: 0.29454954
A54: Queensland
A55: Black Coal | B55: Mt CO2e | C55: 35.708102 | D55: 34.44327 | E55: 33.022455 | F55: 30.719276 | G55: 32.651121 | H55: 32.488327 | I55: 32.789412 | J55: 31.118586 | K55: 32.942706 | L55: 33.549232 | M55: 29.254224 | N55: 26.904185 | O55: 22.722791 | P55: 19.578752 | Q55: 18.710028 | R55: 18.862685 | S55: 17.151095 | T55: 16.7405 | U55: 13.605724 | V55: 12.791927 | W55: 11.024735 | X55: 9.778125 | Y55: 9.2894552 | Z55: 9.4263489 | AA55: 9.4125428 | AB55: 9.345025 | AC55: 4.0769087 | AD55: 0 | AE55: 0 | AF55: 0 | AG55: 0 | AH55: 0 | AI55: 0 | AJ55: 0 | AK55: 0 | AL55: 0
A56: Brown Coal | B56: Mt CO2e | C56: 0 | D56: 0 | E56: 0 | F56: 0 | G56: 0 | H56: 0 | I56: 0 | J56: 0 | K56: 0 | L56: 0 | M56: 0 | N56: 0 | O56: 0 | P56: 0 | Q56: 0 | R56: 0 | S56: 0 | T56: 0 | U56: 0 | V56: 0 | W56: 0 | X56: 0 | Y56: 0 | Z56: 0 | AA56: 0 | AB56: 0 | AC56: 0 | AD56: 0 | AE56: 0 | AF56: 0 | AG56: 0 | AH56: 0 | AI56: 0 | AJ56: 0 | AK56: 0 | AL56: 0
A57: Coal CCS | B57: Mt CO2e | C57: 0 | D57: 0 | E57: 0 | F57: 0 | G57: 0.32325771 | H57: 0.29900237 | I57: 0.44941122 | J57: 0.63432289 | K57: 0.77503143 | L57: 0.87252998 | M57: 0 | N57: 0 | O57: 0 | P57: 0 | Q57: 0 | R57: 0 | S57: 0 | T57: 0 | U57: 0 | V57: 0 | W57: 0 | X57: 0 | Y57: 0 | Z57: 0 | AA57: 0 | AB57: 0 | AC57: 0 | AD57: 0 | AE57: 0 | AF57: 0 | AG57: 0 | AH57: 0 | AI57: 0 | AJ57: 0 | AK57: 0 | AL57: 0
A58: Gas GT | B58: Mt CO2e | C58: 0.0051677399 | D58: 0.00702703 | E58: 0.0143862 | F58: 0.01995312 | G58: 0.01098389 | H58: 0.0061637001 | I58: 0.01514343 | J58: 0.04083662 | K58: 0.057663161 | L58: 0.083376441 | M58: 0.30595118 | N58: 0.33807829 | O58: 0.37777023 | P58: 0.44423224 | Q58: 0.42254134 | R58: 0.46639169 | S58: 0.48185528 | T58: 0.52329311 | U58: 0.55519077 | V58: 0.60272655 | W58: 0.63188918 | X58: 0.82586599 | Y58: 0.41676543 | Z58: 0.44218766 | AA58: 0.47007 | AB58: 0.44609217 | AC58: 0.45640358 | AD58: 0.50721008 | AE58: 0.50253715 | AF58: 0.4935591 | AG58: 0.48504318 | AH58: 0.48875396 | AI58: 0 | AJ58: 0 | AK58: 0 | AL58: 0
A59: Gas CCGT & Cogen | B59: Mt CO2e | C59: 0.59296861 | D59: 0.73352959 | E59: 0.83095827 | F59: 0.54102848 | G59: 0.3489367 | H59: 0.32072895 | I59: 0.47823084 | J59: 0.7304652 | K59: 0.84688122 | L59: 0.9291494 | M59: 1.8030856 | N59: 1.9852991 | O59: 2.2924288 | P59: 2.4024494 | Q59: 2.3968302 | R59: 2.3271644 | S59: 1.9275831 | T59: 1.9059937 | U59: 1.9572825 | V59: 1.9042497 | W59: 1.9495177 | X59: 0.78711515 | Y59: 0.60086621 | Z59: 0.60195893 | AA59: 0.61604169 | AB59: 0.56736871 | AC59: 0.28519648 | AD59: 0.30369868 | AE59: 0.30794768 | AF59: 0.29764566 | AG59: 0.28710533 | AH59: 0.29401329 | AI59: 0.3176331 | AJ59: 0.30165025 | AK59: 0.29365579 | AL59: 0.29454954
A60: Gas CC CCS | B60: Mt CO2e | C60: 0 | D60: 0 | E60: 0 | F60: 0 | G60: 0 | H60: 0 | I60: 0 | J60: 0 | K60: 0 | L60: 0 | M60: 0 | N60: 0 | O60: 0 | P60: 0 | Q60: 0 | R60: 0 | S60: 0 | T60: 0 | U60: 0 | V60: 0 | W60: 0 | X60: 0 | Y60: 0 | Z60: 0 | AA60: 0 | AB60: 0 | AC60: 0 | AD60: 0 | AE60: 0 | AF60: 0 | AG60: 0 | AH60: 0 | AI60: 0 | AJ60: 0 | AK60: 0 | AL60: 0
A61: Gas Steam | B61: Mt CO2e | C61: 0 | D61: 0 | E61: 0 | F61: 0 | G61: 0 | H61: 0 | I61: 0 | J61: 0 | K61: 0 | L61: 0 | M61: 0 | N61: 0 | O61: 0 | P61: 0 | Q61: 0 | R61: 0 | S61: 0 | T61: 0 | U61: 0 | V61: 0 | W61: 0 | X61: 0 | Y61: 0 | Z61: 0 | AA61: 0 | AB61: 0 | AC61: 0 | AD61: 0 | AE61: 0 | AF61: 0 | AG61: 0 | AH61: 0 | AI61: 0 | AJ61: 0 | AK61: 0 | AL61: 0
A62: Distillate | B62: Mt CO2e | C62: 0 | D62: 0 | E62: 0 | F62: 0 | G62: 0 | H62: 0 | I62: 0 | J62: 0 | K62: 0 | L62: 0 | M62: 0 | N62: 0 | O62: 0 | P62: 0 | Q62: 0 | R62: 0 | S62: 0 | T62: 0 | U62: 0 | V62: 0 | W62: 0 | X62: 0 | Y62: 0 | Z62: 0 | AA62: 0 | AB62: 0 | AC62: 0 | AD62: 0 | AE62: 0 | AF62: 0 | AG62: 0 | AH62: 0 | AI62: 0 | AJ62: 0 | AK62: 0 | AL62: 0
A63: Hydro | B63: Mt CO2e | C63: 0 | D63: 0 | E63: 0 | F63: 0 | G63: 0 | H63: 0 | I63: 0 | J63: 0 | K63: 0 | L63: 0 | M63: 0 | N63: 0 | O63: 0 | P63: 0 | Q63: 0 | R63: 0 | S63: 0 | T63: 0 | U63: 0 | V63: 0 | W63: 0 | X63: 0 | Y63: 0 | Z63: 0 | AA63: 0 | AB63: 0 | AC63: 0 | AD63: 0 | AE63: 0 | AF63: 0 | AG63: 0 | AH63: 0 | AI63: 0 | AJ63: 0 | AK63: 0 | AL63: 0
A64: Wind | B64: Mt CO2e | C64: 0 | D64: 0 | E64: 0 | F64: 0 | G64: 0 | H64: 0 | I64: 0 | J64: 0 | K64: 0 | L64: 0 | M64: 0 | N64: 0 | O64: 0 | P64: 0 | Q64: 0 | R64: 0 | S64: 0 | T64: 0 | U64: 0 | V64: 0 | W64: 0 | X64: 0 | Y64: 0 | Z64: 0 | AA64: 0 | AB64: 0 | AC64: 0 | AD64: 0 | AE64: 0 | AF64: 0 | AG64: 0 | AH64: 0 | AI64: 0 | AJ64: 0 | AK64: 0 | AL64: 0
A65: Biomass | B65: Mt CO2e | C65: 0 | D65: 0 | E65: 0 | F65: 0 | G65: 0 | H65: 0 | I65: 0 | J65: 0 | K65: 0 | L65: 0 | M65: 0 | N65: 0 | O65: 0 | P65: 0 | Q65: 0 | R65: 0 | S65: 0 | T65: 0 | U65: 0 | V65: 0 | W65: 0 | X65: 0 | Y65: 0 | Z65: 0 | AA65: 0 | AB65: 0 | AC65: 0 | AD65: 0 | AE65: 0 | AF65: 0 | AG65: 0 | AH65: 0 | AI65: 0 | AJ65: 0 | AK65: 0 | AL65: 0
A66: Solar | B66: Mt CO2e | C66: 0 | D66: 0 | E66: 0 | F66: 0 | G66: 0 | H66: 0 | I66: 0 | J66: 0 | K66: 0 | L66: 0 | M66: 0 | N66: 0 | O66: 0 | P66: 0 | Q66: 0 | R66: 0 | S66: 0 | T66: 0 | U66: 0 | V66: 0 | W66: 0 | X66: 0 | Y66: 0 | Z66: 0 | AA66: 0 | AB66: 0 | AC66: 0 | AD66: 0 | AE66: 0 | AF66: 0 | AG66: 0 | AH66: 0 | AI66: 0 | AJ66: 0 | AK66: 0 | AL66: 0
... A70: Total | B70: Mt CO2e | C70: 36.306238 | D70: 35.183826 | E70: 33.8678 | F70: 31.280258 | G70: 33.334299 | H70: 33.114222 | I70: 33.732198 | J70: 32.524211 | K70: 34.622282 | L70: 35.434288 | M70: 31.363261 | N70: 29.227563 | O70: 25.39299 | P70: 22.425434 | Q70: 21.5294 | R70: 21.656242 | S70: 19.560533 | T70: 19.169786 | U70: 16.118198 | V70: 15.298903 | W70: 13.606142 | X70: 11.391106 | Y70: 10.307087 | Z70: 10.470495 | AA70: 10.498654 | AB70: 10.358486 | AC70: 4.8185088 | AD70: 0.81090876 | AE70: 0.81048482 | AF70: 0.79120476 | AG70: 0.77214851 | AH70: 0.78276724 | AI70: 0.3176331 | AJ70: 0.30165025 | AK70: 0.29365579 | AL70: 0.29454954
A71: New South Wales | H71: 0.30432306
A72: Black Coal | B72: Mt CO2e | C72: 32.3699 | D72: 29.524866 | E72: 28.478546 | F72: 27.026244 | G72: 23.148399 | H72: 22.487299 | I72: 17.092348 | J72: 15.152143 | K72: 9.4724007 | L72: 6.8555422 | M72: 6.9176409 | N72: 6.9769049 | O72: 6.9510228 | P72: 6.936596 | Q72: 7.0340711 | R72: 3.8821177 | S72: 0 | T72: 0 | U72: 0 | V72: 0 | W72: 0 | X72: 0 | Y72: 0 | Z72: 0 | AA72: 0 | AB72: 0 | AC72: 0 | AD72: 0 | AE72: 0 | AF72: 0 | AG72: 0 | AH72: 0 | AI72: 0 | AJ72: 0 | AK72: 0 | AL72: 0
A73: Brown Coal | B73: Mt CO2e | C73: 0 | D73: 0 | E73: 0 | F73: 0 | G73: 0 | H73: 0 | I73: 0 | J73: 0 | K73: 0 | L73: 0 | M73: 0 | N73: 0 | O73: 0 | P73: 0 | Q73: 0 | R73: 0 | S73: 0 | T73: 0 | U73: 0 | V73: 0 | W73: 0 | X73: 0 | Y73: 0 | Z73: 0 | AA73: 0 | AB73: 0 | AC73: 0 | AD73: 0 | AE73: 0 | AF73: 0 | AG73: 0 | AH73: 0 | AI73: 0 | AJ73: 0 | AK73: 0 | AL73: 0
A74: Coal CCS | B74: Mt CO2e | C74: 0 | D74: 0 | E74: 0 | F74: 0 | G74: 0 | H74: 0 | I74: 0 | J74: 0 | K74: 0 | L74: 0 | M74: 0 | N74: 0 | O74: 0 | P74: 0 | Q74: 0 | R74: 0 | S74: 0 | T74: 0 | U74: 0 | V74: 0 | W74: 0 | X74: 0 | Y74: 0 | Z74: 0 | AA74: 0 | AB74: 0 | AC74: 0 | AD74: 0 | AE74: 0 | AF74: 0 | AG74: 0 | AH74: 0 | AI74: 0 | AJ74: 0 | AK74: 0 | AL74: 0
A75: Gas GT | B75: Mt CO2e | C75: 0.15902951 | D75: 0.26418602 | E75: 0.14485942 | F75: 0.10509072 | G75: 0.15889552 | H75: 0.10971637 | I75: 0.14252818 | J75: 0.16319497 | K75: 0.24697752 | L75: 0.22839042 | M75: 0.04035103 | N75: 0.024721251 | O75: 0.03429247 | P75: 0.01529587 | Q75: 0.01728943 | R75: 0.045553041 | S75: 0.041805451 | T75: 0.085480091 | U75: 0.085275149 | V75: 0.11487645 | W75: 0.04592381 | X75: 0.00227022 | Y75: 0.023248011 | Z75: 1.2225076 | AA75: 1.2329169 | AB75: 1.1465138 | AC75: 1.2025795 | AD75: 1.2848288 | AE75: 1.2759659 | AF75: 1.01325 | AG75: 1.0241633 | AH75: 1.0156953 | AI75: 1.0423607 | AJ75: 1.0588068 | AK75: 1.0392883 | AL75: 1.8229935
A76: Gas CCGT & Cogen | B76: Mt CO2e | C76: 0.33206269 | D76: 0.33615334 | E76: 0.26840734 | F76: 0.13778034 | G76: 0.21440323 | H76: 0.18012619 | I76: 0.23306142 | J76: 0.85920657 | K76: 1.1758723 | L76: 1.3752635 | M76: 1.6617402 | N76: 1.7293809 | O76: 1.7815723 | P76: 1.5955385 | Q76: 2.7824474 | R76: 2.9569429 | S76: 3.0801192 | T76: 3.150339 | U76: 2.5840524 | V76: 2.4980366 | W76: 2.5555745 | X76: 2.4987237 | Y76: 2.4439685 | Z76: 2.6180258 | AA76: 2.6203954 | AB76: 2.5257712 | AC76: 2.5107159 | AD76: 2.7299641 | AE76: 2.7118729 | AF76: 2.6598632 | AG76: 2.5750787 | AH76: 2.6134016 | AI76: 2.6253858 | AJ76: 2.584698 | AK76: 2.5452339 | AL76: 2.6001406
A77: Gas CC CCS | B77: Mt CO2e | C77: 0 | D77: 0 | E77: 0 | F77: 0 | G77: 0 | H77: 0 | I77: 0 | J77: 0 | K77: 0 | L77: 0 | M77: 0 | N77: 0 | O77: 0 | P77: 0 | Q77: 0 | R77: 0 | S77: 0 | T77: 0 | U77: 0 | V77: 0 | W77: 0 | X77: 0 | Y77: 0 | Z77: 0 | AA77: 0 | AB77: 0 | AC77: 0 | AD77: 0 | AE77: 0 | AF77: 0 | AG77: 0 | AH77: 0 | AI77: 0 | AJ77: 0 | AK77: 0 | AL77: 0
A78: Gas Steam | B78: Mt CO2e | C78: 0 | D78: 0 | E78: 0 | F78: 0 | G78: 0 | H78: 0 | I78: 0 | J78: 0 | K78: 0 | L78: 0 | M78: 0 | N78: 0 | O78: 0 | P78: 0 | Q78: 0 | R78: 0 | S78: 0 | T78: 0 | U78: 0 | V78: 0 | W78: 0 | X78: 0 | Y78: 0 | Z78: 0 | AA78: 0 | AB78: 0 | AC78: 0 | AD78: 0 | AE78: 0 | AF78: 0 | AG78: 0 | AH78: 0 | AI78: 0 | AJ78: 0 | AK78: 0 | AL78: 0
A79: Distillate | B79: Mt CO2e | C79: 0 | D79: 0 | E79: 0 | F79: 0 | G79: 0 | H79: 0 | I79: 0 | J79: 0 | K79: 0 | L79: 0 | M79: 0 | N79: 0 | O79: 0 | P79: 0 | Q79: 0 | R79: 0 | S79: 0 | T79: 0 | U79: 0 | V79: 0 | W79: 0 | X79: 0 | Y79: 0 | Z79: 0 | AA79: 0 | AB79: 0 | AC79: 0 | AD79: 0 | AE79: 0 | AF79: 0 | AG79: 0 | AH79: 0 | AI79: 0 | AJ79: 0 | AK79: 0 | AL79: 0
A80: Hydro | B80: Mt CO2e | C80: 0 | D80: 0 | E80: 0 | F80: 0 | G80: 0 | H80: 0 | I80: 0 | J80: 0 | K80: 0 | L80: 0 | M80: 0 | N80: 0 | O80: 0 | P80: 0 | Q80: 0 | R80: 0 | S80: 0 | T80: 0 | U80: 0 | V80: 0 | W80: 0 | X80: 0 | Y80: 0 | Z80: 0 | AA80: 0 | AB80: 0 | AC80: 0 | AD80: 0 | AE80: 0 | AF80: 0 | AG80: 0 | AH80: 0 | AI80: 0 | AJ80: 0 | AK80: 0 | AL80: 0
A81: Wind | B81: Mt CO2e | C81: 0 | D81: 0 | E81: 0 | F81: 0 | G81: 0 | H81: 0 | I81: 0 | J81: 0 | K81: 0 | L81: 0 | M81: 0 | N81: 0 | O81: 0 | P81: 0 | Q81: 0 | R81: 0 | S81: 0 | T81: 0 | U81: 0 | V81: 0 | W81: 0 | X81: 0 | Y81: 0 | Z81: 0 | AA81: 0 | AB81: 0 | AC81: 0 | AD81: 0 | AE81: 0 | AF81: 0 | AG81: 0 | AH81: 0 | AI81: 0 | AJ81: 0 | AK81: 0 | AL81: 0
A82: Biomass | B82: Mt CO2e | C82: 0 | D82: 0 | E82: 0 | F82: 0 | G82: 0 | H82: 0 | I82: 0 | J82: 0 | K82: 0 | L82: 0 | M82: 0 | N82: 0 | O82: 0 | P82: 0 | Q82: 0 | R82: 0 | S82: 0 | T82: 0 | U82: 0 | V82: 0 | W82: 0 | X82: 0 | Y82: 0 | Z82: 0 | AA82: 0 | AB82: 0 | AC82: 0 | AD82: 0 | AE82: 0 | AF82: 0 | AG82: 0 | AH82: 0 | AI82: 0 | AJ82: 0 | AK82: 0 | AL82: 0
A83: Solar | B83: Mt CO2e | C83: 0 | D83: 0 | E83: 0 | F83: 0 | G83: 0 | H83: 0 | I83: 0 | J83: 0 | K83: 0 | L83: 0 | M83: 0 | N83: 0 | O83: 0 | P83: 0 | Q83: 0 | R83: 0 | S83: 0 | T83: 0 | U83: 0 | V83: 0 | W83: 0 | X83: 0 | Y83: 0 | Z83: 0 | AA83: 0 | AB83: 0 | AC83: 0 | AD83: 0 | AE83: 0 | AF83: 0 | AG83: 0 | AH83: 0 | AI83: 0 | AJ83: 0 | AK83: 0 | AL83: 0
... A87: Total | B87: Mt CO2e | C87: 32.860992 | D87: 30.125206 | E87: 28.891813 | F87: 27.269115 | G87: 23.521698 | H87: 22.777142 | I87: 17.467937 | J87: 16.174544 | K87: 10.895251 | L87: 8.4591961 | M87: 8.6197321 | N87: 8.7310071 | O87: 8.7668876 | P87: 8.5474304 | Q87: 9.8338079 | R87: 6.8846136 | S87: 3.1219247 | T87: 3.2358191 | U87: 2.6693276 | V87: 2.6129131 | W87: 2.6014983 | X87: 2.500994 | Y87: 2.4672165 | Z87: 3.8405334 | AA87: 3.8533123 | AB87: 3.6722849 | AC87: 3.7132954 | AD87: 4.0147929 | AE87: 3.9878388 | AF87: 3.6731132 | AG87: 3.599242 | AH87: 3.6290969 | AI87: 3.6677465 | AJ87: 3.6435049 | AK87: 3.5845222 | AL87: 4.4231341
A88: Victoria
A89: Black Coal | B89: Mt CO2e | C89: 0 | D89: 0 | E89: 0 | F89: 0 | G89: 0 | H89: 0 | I89: 0 | J89: 0 | K89: 0 | L89: 0 | M89: 0 | N89: 0 | O89: 0 | P89: 0 | Q89: 0 | R89: 0 | S89: 0 | T89: 0 | U89: 0 | V89: 0 | W89: 0 | X89: 0 | Y89: 0 | Z89: 0 | AA89: 0 | AB89: 0 | AC89: 0 | AD89: 0 | AE89: 0 | AF89: 0 | AG89: 0 | AH89: 0 | AI89: 0 | AJ89: 0 | AK89: 0 | AL89: 0
A90: Brown Coal | B90: Mt CO2e | C90: 33.721627 | D90: 33.264186 | E90: 32.960634 | F90: 32.910167 | G90: 22.695246 | H90: 23.036429 | I90: 23.422433 | J90: 24.231887 | K90: 24.281588 | L90: 21.384412 | M90: 10.387125 | N90: 7.9720361 | O90: 7.6039173 | P90: 7.674026 | Q90: 7.602409 | R90: 6.4669472 | S90: 6.8139818 | T90: 6.9996577 | U90: 6.5652332 | V90: 6.7342198 | W90: 6.8264607 | X90: 6.3319342 | Y90: 3.6151884 | Z90: 0 | AA90: 0 | AB90: 0 | AC90: 0 | AD90: 0 | AE90: 0 | AF90: 0 | AG90: 0 | AH90: 0 | AI90: 0 | AJ90: 0 | AK90: 0 | AL90: 0
A91: Coal CCS | B91: Mt CO2e | C91: 0 | D91: 0 | E91: 0 | F91: 0 | G91: 0 | H91: 0 | I91: 0 | J91: 0 | K91: 0 | L91: 0 | M91: 0 | N91: 0 | O91: 0 | P91: 0 | Q91: 0 | R91: 0 | S91: 0 | T91: 0 | U91: 0 | V91: 0 | W91: 0 | X91: 0 | Y91: 0 | Z91: 0 | AA91: 0 | AB91: 0 | AC91: 0 | AD91: 0 | AE91: 0 | AF91: 0 | AG91: 0 | AH91: 0 | AI91: 0 | AJ91: 0 | AK91: 0 | AL91: 0
A92: Gas GT | B92: Mt CO2e | C92: 1.4471287 | D92: 1.2716439 | E92: 1.3020892 | F92: 1.2183371 | G92: 1.3400723 | H92: 1.1806583 | I92: 1.3145119 | J92: 1.570543 | K92: 1.7773769 | L92: 1.6284598 | M92: 1.5324373 | N92: 1.6504445 | O92: 1.6696681 | P92: 1.6289954 | Q92: 1.2256443 | R92: 0.76946254 | S92: 0.64630627 | T92: 0.67824989 | U92: 0.58508221 | V92: 0.55200186 | W92: 0.55272706 | X92: 0.57861402 | Y92: 0.1330532 | Z92: 0.090198181 | AA92: 0.089962508 | AB92: 0.089627122 | AC92: 0.099109219 | AD92: 0.10610165 | AE92: 0.11055569 | AF92: 0.10462297 | AG92: 0.10383234 | AH92: 0.063364819 | AI92: 0.05852417 | AJ92: 0.06213525 | AK92: 0.063101501 | AL92: 0.17529257
A93: Gas CCGT & Cogen | B93: Mt CO2e | C93: 0.094260498 | D93: 0.089280328 | E93: 0.085727677 | F93: 0.086160808 | G93: 0.087138038 | H93: 0.087962061 | I93: 0.092427983 | J93: 0.095748619 | K93: 0.095939127 | L93: 0.094766113 | M93: 0.093159693 | N93: 0.099370287 | O93: 0.096468242 | P93: 0.093803484 | Q93: 0.091185743 | R93: 0.084552736 | S93: 0.080279703 | T93: 0.08208281 | U93: 0.076735389 | V93: 0.080018424 | W93: 0.079720463 | X93: 0.28260743 | Y93: 0.92254281 | Z93: 1.1210332 | AA93: 1.1257161 | AB93: 1.0761949 | AC93: 1.0634325 | AD93: 1.1610816 | AE93: 1.1590222 | AF93: 1.1253589 | AG93: 1.0926785 | AH93: 1.2099257 | AI93: 1.2509751 | AJ93: 1.2297432 | AK93: 1.2188287 | AL93: 1.2602417
A94: Gas CC CCS | B94: Mt CO2e | C94: 0 | D94: 0 | E94: 0 | F94: 0 | G94: 0 | H94: 0 | I94: 0 | J94: 0 | K94: 0 | L94: 0 | M94: 0 | N94: 0 | O94: 0 | P94: 0 | Q94: 0 | R94: 0 | S94: 0 | T94: 0 | U94: 0 | V94: 0 | W94: 0 | X94: 0 | Y94: 0 | Z94: 0 | AA94: 0 | AB94: 0 | AC94: 0 | AD94: 0 | AE94: 0 | AF94: 0 | AG94: 0 | AH94: 0 | AI94: 0 | AJ94: 0 | AK94: 0 | AL94: 0
A95: Gas Steam | B95: Mt CO2e | C95: 0.29033543 | D95: 0.31631855 | E95: 0.33553833 | F95: 0.28672469 | G95: 0.30823725 | H95: 0.27276578 | I95: 0.29498879 | J95: 0.38689784 | K95: 0.48219423 | L95: 0.41985483 | M95: 0.32346025 | N95: 0.36404028 | O95: 0.40472334 | P95: 0.36222182 | Q95: 0.041411029 | R95: 0 | S95: 0 | T95: 0 | U95: 0 | V95: 0 | W95: 0 | X95: 0 | Y95: 0 | Z95: 0 | AA95: 0 | AB95: 0 | AC95: 0 | AD95: 0 | AE95: 0 | AF95: 0 | AG95: 0 | AH95: 0 | AI95: 0 | AJ95: 0 | AK95: 0 | AL95: 0
A96: Distillate | B96: Mt CO2e | C96: 0 | D96: 0 | E96: 0 | F96: 0 | G96: 0 | H96: 0 | I96: 0 | J96: 0 | K96: 0 | L96: 0 | M96: 0 | N96: 0 | O96: 0 | P96: 0 | Q96: 0 | R96: 0 | S96: 0 | T96: 0 | U96: 0 | V96: 0 | W96: 0 | X96: 0 | Y96: 0 | Z96: 0 | AA96: 0 | AB96: 0 | AC96: 0 | AD96: 0 | AE96: 0 | AF96: 0 | AG96: 0 | AH96: 0 | AI96: 0 | AJ96: 0 | AK96: 0 | AL96: 0
A97: Hydro | B97: Mt CO2e | C97: 0 | D97: 0 | E97: 0 | F97: 0 | G97: 0 | H97: 0 | I97: 0 | J97: 0 | K97: 0 | L97: 0 | M97: 0 | N97: 0 | O97: 0 | P97: 0 | Q97: 0 | R97: 0 | S97: 0 | T97: 0 | U97: 0 | V97: 0 | W97: 0 | X97: 0 | Y97: 0 | Z97: 0 | AA97: 0 | AB97: 0 | AC97: 0 | AD97: 0 | AE97: 0 | AF97: 0 | AG97: 0 | AH97: 0 | AI97: 0 | AJ97: 0 | AK97: 0 | AL97: 0
A98: Wind | B98: Mt CO2e | C98: 0 | D98: 0 | E98: 0 | F98: 0 | G98: 0 | H98: 0 | I98: 0 | J98: 0 | K98: 0 | L98: 0 | M98: 0 | N98: 0 | O98: 0 | P98: 0 | Q98: 0 | R98: 0 | S98: 0 | T98: 0 | U98: 0 | V98: 0 | W98: 0 | X98: 0 | Y98: 0 | Z98: 0 | AA98: 0 | AB98: 0 | AC98: 0 | AD98: 0 | AE98: 0 | AF98: 0 | AG98: 0 | AH98: 0 | AI98: 0 | AJ98: 0 | AK98: 0 | AL98: 0
A99: Biomass | B99: Mt CO2e | C99: 0 | D99: 0 | E99: 0 | F99: 0 | G99: 0 | H99: 0 | I99: 0 | J99: 0 | K99: 0 | L99: 0 | M99: 0 | N99: 0 | O99: 0 | P99: 0 | Q99: 0 | R99: 0 | S99: 0 | T99: 0 | U99: 0 | V99: 0 | W99: 0 | X99: 0 | Y99: 0 | Z99: 0 | AA99: 0 | AB99: 0 | AC99: 0 | AD99: 0 | AE99: 0 | AF99: 0 | AG99: 0 | AH99: 0 | AI99: 0 | AJ99: 0 | AK99: 0 | AL99: 0
A100: Solar | B100: Mt CO2e | C100: 0 | D100: 0 | E100: 0 | F100: 0 | G100: 0 | H100: 0 | I100: 0 | J100: 0 | K100: 0 | L100: 0 | M100: 0 | N100: 0 | O100: 0 | P100: 0 | Q100: 0 | R100: 0 | S100: 0 | T100: 0 | U100: 0 | V100: 0 | W100: 0 | X100: 0 | Y100: 0 | Z100: 0 | AA100: 0 | AB100: 0 | AC100: 0 | AD100: 0 | AE100: 0 | AF100: 0 | AG100: 0 | AH100: 0 | AI100: 0 | AJ100: 0 | AK100: 0 | AL100: 0
... A104: Total | B104: Mt CO2e | C104: 35.553351 | D104: 34.941429 | E104: 34.683989 | F104: 34.50139 | G104: 24.430693 | H104: 24.577815 | I104: 25.124362 | J104: 26.285077 | K104: 26.637098 | L104: 23.527493 | M104: 12.336182 | N104: 10.085891 | O104: 9.774777 | P104: 9.7590467 | Q104: 8.9606501 | R104: 7.3209624 | S104: 7.5405678 | T104: 7.7599904 | U104: 7.2270508 | V104: 7.3662401 | W104: 7.4589082 | X104: 7.1931556 | Y104: 4.6707844 | Z104: 1.2112314 | AA104: 1.2156787 | AB104: 1.165822 | AC104: 1.1625417 | AD104: 1.2671833 | AE104: 1.2695779 | AF104: 1.2299819 | AG104: 1.1965109 | AH104: 1.2732905 | AI104: 1.3094993 | AJ104: 1.2918785 | AK104: 1.2819302 | AL104: 1.4355343
A105: Tasmania
A106: Black Coal | B106: Mt CO2e | C106: 0 | D106: 0 | E106: 0 | F106: 0 | G106: 0 | H106: 0 | I106: 0 | J106: 0 | K106: 0 | L106: 0 | M106: 0 | N106: 0 | O106: 0 | P106: 0 | Q106: 0 | R106: 0 | S106: 0 | T106: 0 | U106: 0 | V106: 0 | W106: 0 | X106: 0 | Y106: 0 | Z106: 0 | AA106: 0 | AB106: 0 | AC106: 0 | AD106: 0 | AE106: 0 | AF106: 0 | AG106: 0 | AH106: 0 | AI106: 0 | AJ106: 0 | AK106: 0 | AL106: 0
A107: Brown Coal | B107: Mt CO2e | C107: 0 | D107: 0 | E107: 0 | F107: 0 | G107: 0 | H107: 0 | I107: 0 | J107: 0 | K107: 0 | L107: 0 | M107: 0 | N107: 0 | O107: 0 | P107: 0 | Q107: 0 | R107: 0 | S107: 0 | T107: 0 | U107: 0 | V107: 0 | W107: 0 | X107: 0 | Y107: 0 | Z107: 0 | AA107: 0 | AB107: 0 | AC107: 0 | AD107: 0 | AE107: 0 | AF107: 0 | AG107: 0 | AH107: 0 | AI107: 0 | AJ107: 0 | AK107: 0 | AL107: 0
A108: Coal CCS | B108: Mt CO2e | C108: 0 | D108: 0 | E108: 0 | F108: 0 | G108: 0 | H108: 0 | I108: 0 | J108: 0 | K108: 0 | L108: 0 | M108: 0 | N108: 0 | O108: 0 | P108: 0 | Q108: 0 | R108: 0 | S108: 0 | T108: 0 | U108: 0 | V108: 0 | W108: 0 | X108: 0 | Y108: 0 | Z108: 0 | AA108: 0 | AB108: 0 | AC108: 0 | AD108: 0 | AE108: 0 | AF108: 0 | AG108: 0 | AH108: 0 | AI108: 0 | AJ108: 0 | AK108: 0 | AL108: 0
A109: Gas GT | B109: Mt CO2e | C109: 0.00355648 | D109: 0.0048535 | E109: 0.0058309801 | F109: 0.00312076 | G109: 0.00467839 | H109: 0.0044506 | I109: 0.00399367 | J109: 0.00530485 | K109: 0.0064694501 | L109: 0.0067906399 | M109: 0.00675905 | N109: 0.00827989 | O109: 0.03457037 | P109: 0.00513285 | Q109: 0.00092621 | R109: 0.03671729 | S109: 0.02115712 | T109: 0.03203242 | U109: 0.03144156 | V109: 0.033191991 | W109: 0.039374569 | X109: 0.03299754 | Y109: 0.061452972 | Z109: 0.046017959 | AA109: 0.03909781 | AB109: 0.03915187 | AC109: 0.04154416 | AD109: 0.04181472 | AE109: 0.05166225 | AF109: 0.03609122 | AG109: 0.04323148 | AH109: 0.0343382 | AI109: 0.044405412 | AJ109: 0.05145331 | AK109: 0.05175204 | AL109: 0.03873849
A110: Gas CCGT & Cogen | B110: Mt CO2e | C110: 0.074425169 | D110: 0.076330461 | E110: 0.093335801 | F110: 0.064105671 | G110: 0.10911161 | H110: 0.08653912 | I110: 0.093187662 | J110: 0.12269486 | K110: 0.16883756 | L110: 0.16894662 | M110: 0.17002988 | N110: 0.20572937 | O110: 0.026361061 | P110: 0 | Q110: 0 | R110: 0 | S110: 0 | T110: 0 | U110: 0 | V110: 0 | W110: 0 | X110: 0 | Y110: 0 | Z110: 0 | AA110: 0 | AB110: 0 | AC110: 0 | AD110: 0 | AE110: 0 | AF110: 0 | AG110: 0 | AH110: 0 | AI110: 0 | AJ110: 0 | AK110: 0 | AL110: 0
A111: Gas CC CCS | B111: Mt CO2e | C111: 0 | D111: 0 | E111: 0 | F111: 0 | G111: 0 | H111: 0 | I111: 0 | J111: 0 | K111: 0 | L111: 0 | M111: 0 | N111: 0 | O111: 0 | P111: 0 | Q111: 0 | R111: 0 | S111: 0 | T111: 0 | U111: 0 | V111: 0 | W111: 0 | X111: 0 | Y111: 0 | Z111: 0 | AA111: 0 | AB111: 0 | AC111: 0 | AD111: 0 | AE111: 0 | AF111: 0 | AG111: 0 | AH111: 0 | AI111: 0 | AJ111: 0 | AK111: 0 | AL111: 0
A112: Gas Steam | B112: Mt CO2e | C112: 0 | D112: 0 | E112: 0 | F112: 0 | G112: 0 | H112: 0 | I112: 0 | J112: 0 | K112: 0 | L112: 0 | M112: 0 | N112: 0 | O112: 0 | P112: 0 | Q112: 0 | R112: 0 | S112: 0 | T112: 0 | U112: 0 | V112: 0 | W112: 0 | X112: 0 | Y112: 0 | Z112: 0 | AA112: 0 | AB112: 0 | AC112: 0 | AD112: 0 | AE112: 0 | AF112: 0 | AG112: 0 | AH112: 0 | AI112: 0 | AJ112: 0 | AK112: 0 | AL112: 0
A113: Distillate | B113: Mt CO2e | C113: 0 | D113: 0 | E113: 0 | F113: 0 | G113: 0 | H113: 0 | I113: 0 | J113: 0 | K113: 0 | L113: 0 | M113: 0 | N113: 0 | O113: 0 | P113: 0 | Q113: 0 | R113: 0 | S113: 0 | T113: 0 | U113: 0 | V113: 0 | W113: 0 | X113: 0 | Y113: 0 | Z113: 0 | AA113: 0 | AB113: 0 | AC113: 0 | AD113: 0 | AE113: 0 | AF113: 0 | AG113: 0 | AH113: 0 | AI113: 0 | AJ113: 0 | AK113: 0 | AL113: 0
A114: Hydro | B114: Mt CO2e | C114: 0 | D114: 0 | E114: 0 | F114: 0 | G114: 0 | H114: 0 | I114: 0 | J114: 0 | K114: 0 | L114: 0 | M114: 0 | N114: 0 | O114: 0 | P114: 0 | Q114: 0 | R114: 0 | S114: 0 | T114: 0 | U114: 0 | V114: 0 | W114: 0 | X114: 0 | Y114: 0 | Z114: 0 | AA114: 0 | AB114: 0 | AC114: 0 | AD114: 0 | AE114: 0 | AF114: 0 | AG114: 0 | AH114: 0 | AI114: 0 | AJ114: 0 | AK114: 0 | AL114: 0
A115: Wind | B115: Mt CO2e | C115: 0 | D115: 0 | E115: 0 | F115: 0 | G115: 0 | H115: 0 | I115: 0 | J115: 0 | K115: 0 | L115: 0 | M115: 0 | N115: 0 | O115: 0 | P115: 0 | Q115: 0 | R115: 0 | S115: 0 | T115: 0 | U115: 0 | V115: 0 | W115: 0 | X115: 0 | Y115: 0 | Z115: 0 | AA115: 0 | AB115: 0 | AC115: 0 | AD115: 0 | AE115: 0 | AF115: 0 | AG115: 0 | AH115: 0 | AI115: 0 | AJ115: 0 | AK115: 0 | AL115: 0
A116: Biomass | B116: Mt CO2e | C116: 0 | D116: 0 | E116: 0 | F116: 0 | G116: 0 | H116: 0 | I116: 0 | J116: 0 | K116: 0 | L116: 0 | M116: 0 | N116: 0 | O116: 0 | P116: 0 | Q116: 0 | R116: 0 | S116: 0 | T116: 0 | U116: 0 | V116: 0 | W116: 0 | X116: 0 | Y116: 0 | Z116: 0 | AA116: 0 | AB116: 0 | AC116: 0 | AD116: 0 | AE116: 0 | AF116: 0 | AG116: 0 | AH116: 0 | AI116: 0 | AJ116: 0 | AK116: 0 | AL116: 0
A117: Solar | B117: Mt CO2e | C117: 0 | D117: 0 | E117: 0 | F117: 0 | G117: 0 | H117: 0 | I117: 0 | J117: 0 | K117: 0 | L117: 0 | M117: 0 | N117: 0 | O117: 0 | P117: 0 | Q117: 0 | R117: 0 | S117: 0 | T117: 0 | U117: 0 | V117: 0 | W117: 0 | X117: 0 | Y117: 0 | Z117: 0 | AA117: 0 | AB117: 0 | AC117: 0 | AD117: 0 | AE117: 0 | AF117: 0 | AG117: 0 | AH117: 0 | AI117: 0 | AJ117: 0 | AK117: 0 | AL117: 0
... A121: Total | B121: Mt CO2e | C121: 0.077981649 | D121: 0.081183961 | E121: 0.099166781 | F121: 0.067226431 | G121: 0.11379 | H121: 0.09098972 | I121: 0.097181332 | J121: 0.12799971 | K121: 0.17530701 | L121: 0.17573726 | M121: 0.17678893 | N121: 0.21400926 | O121: 0.06093143 | P121: 0.00513285 | Q121: 0.00092621 | R121: 0.03671729 | S121: 0.02115712 | T121: 0.03203242 | U121: 0.03144156 | V121: 0.033191991 | W121: 0.039374569 | X121: 0.03299754 | Y121: 0.061452972 | Z121: 0.046017959 | AA121: 0.03909781 | AB121: 0.03915187 | AC121: 0.04154416 | AD121: 0.04181472 | AE121: 0.05166225 | AF121: 0.03609122 | AG121: 0.04323148 | AH121: 0.0343382 | AI121: 0.044405412 | AJ121: 0.05145331 | AK121: 0.05175204 | AL121: 0.03873849
...

Sheet NEM Interconnector
A1: Interconnector
A2: Financial Year | C2: 2025 | D2: 2026 | E2: 2027 | F2: 2028 | G2: 2029 | H2: 2030 | I2: 2031 | J2: 2032 | K2: 2033 | L2: 2034 | M2: 2035 | N2: 2036 | O2: 2037 | P2: 2038 | Q2: 2039 | R2: 2040 | S2: 2041 | T2: 2042 | U2: 2043 | V2: 2044 | W2: 2045 | X2: 2046 | Y2: 2047 | Z2: 2048 | AA2: 2049 | AB2: 2050 | AC2: 2051 | AD2: 2052 | AE2: 2053 | AF2: 2054 | AG2: 2055 | AH2: 2056 | AI2: 2057 | AJ2: 2058 | AK2: 2059 | AL2: 2060
A3: TASMANIA-VICTORIA | B3: Basslink
A4: VIC to TAS Firm Capacity | B4: MW | C4: 478 | D4: 478 | E4: 478 | F4: 478 | G4: 478 | H4: 1228 | I4: 1228 | J4: 1228 | K4: 1228 | L4: 1228 | M4: 1978 | N4: 1978 | O4: 1978 | P4: 1978 | Q4: 1978 | R4: 1978 | S4: 1978 | T4: 1978 | U4: 1978 | V4: 1978 | W4: 1978 | X4: 1978 | Y4: 1978 | Z4: 1978 | AA4: 1978 | AB4: 1978 | AC4: 1978 | AD4: 1978 | AE4: 1978 | AF4: 1978 | AG4: 1978 | AH4: 1978 | AI4: 1978 | AJ4: 1978 | AK4: 1978 | AL4: 1978
A5: TAS Losses | B5: GWh | C5: 2.46 | D5: 10.01 | E5: 3.8699999 | F5: 8.1099997 | G5: 9.1599998 | H5: 0.85000002 | I5: 2.8499999 | J5: 4.5900002 | K5: 6.1399999 | L5: 12.57 | M5: 36.23 | N5: 3.23 | O5: 3.78 | P5: 9.6400003 | Q5: 26.6 | R5: 18.58 | S5: 15.57 | T5: 30.07 | U5: 15.15 | V5: 29.200001 | W5: 24.959999 | X5: 20.719999 | Y5: 20.940001 | Z5: 16.48 | AA5: 33.5 | AB5: 22.84 | AC5: 29.709999 | AD5: 17.49 | AE5: 15.71 | AF5: 19.629999 | AG5: 13.78 | AH5: 11.1 | AI5: 7.2800002 | AJ5: 6.9000001 | AK5: 6.23 | AL5: 6.5
A6: TAS Imports | B6: GWh | C6: 135.38 | D6: 39.349998 | E6: 344.42999 | F6: 333.04001 | G6: 19.440001 | H6: 338 | I6: 933.85999 | J6: 1251.87 | K6: 2249.28 | L6: 3580.8799 | M6: 1810.05 | N6: 1760.11 | O6: 3054.1201 | P6: 4889.6802 | Q6: 4173 | R6: 3911.99 | S6: 5140.9399 | T6: 3809.1201 | U6: 4689.8599 | V6: 4533.1099 | W6: 4154.8501 | X6: 3526.73 | Y6: 3684.28 | Z6: 5002.6001 | AA6: 4138.25 | AB6: 4899.8398 | AC6: 3919.99 | AD6: 3676.95 | AE6: 3360.7 | AF6: 3162.1399 | AG6: 3057.4399 | AH6: 2195.0601 | AI6: 2093.71 | AJ6: 1924.3 | AK6: 1975.9301 | AL6: 1900.12
A7: VIC Losses | B7: GWh | C7: 73.980003 | D7: 96.099998 | E7: 49.189999 | F7: 50.66 | G7: 98.790001 | H7: 29.4 | I7: 9.7399998 | J7: 6.8299999 | K7: 2.8499999 | L7: 0 | M7: 1.51 | N7: 0.69 | O7: 0 | P7: 0 | Q7: 0 | R7: 0 | S7: 0 | T7: 0 | U7: 0 | V7: 0 | W7: 0 | X7: 0 | Y7: 0 | Z7: 0 | AA7: 0 | AB7: 0 | AC7: 0 | AD7: 0 | AE7: 0 | AF7: 0 | AG7: 0 | AH7: 0.43000001 | AI7: 0.55000001 | AJ7: 0.55000001 | AK7: 0.51999998 | AL7: 0.85000002
A8: VIC Imports | B8: GWh | C8: 1082.83 | D8: 1335.71 | E8: 716.15997 | F8: 742.53003 | G8: 1356.75 | H8: 1060.3 | I8: 344.51001 | J8: 264.31 | K8: 82.349998 | L8: 0 | M8: 127.3 | N8: 54.169998 | O8: 0 | P8: 0 | Q8: 0 | R8: 0 | S8: 0 | T8: 0 | U8: 0 | V8: 0 | W8: 0 | X8: 0 | Y8: 0 | Z8: 0 | AA8: 0 | AB8: 0 | AC8: 0 | AD8: 0 | AE8: 0 | AF8: 0 | AG8: 0 | AH8: 25.549999 | AI8: 37.23 | AJ8: 42.279999 | AK8: 34.32 | AL8: 45.860001
A10: VICTORIA-SA
A11: SA-VIC Firm Capacity | B11: MW | C11: 750 | D11: 750 | E11: 750 | F11: 750 | G11: 750 | H11: 1050 | I11: 1050 | J11: 1050 | K11: 1050 | L11: 1050 | M11: 1050 | N11: 1050 | O11: 1050 | P11: 1050 | Q11: 1050 | R11: 1050 | S11: 1050 | T11: 1050 | U11: 1050 | V11: 1050 | W11: 1050 | X11: 1050 | Y11: 1050 | Z11: 1050 | AA11: 1050 | AB11: 1050 | AC11: 1050 | AD11: 1050 | AE11: 1050 | AF11: 1050 | AG11: 1050 | AH11: 1050 | AI11: 1050 | AJ11: 1050 | AK11: 1050 | AL11: 1050
A12: VIC Losses | B12: GWh | C12: 24.309999 | D12: 15.33 | E12: 12.18 | F12: 1.87 | G12: 7.6399999 | H12: 8.5200005 | I12: 7.5500002 | J12: 6.0100002 | K12: 7.4000001 | L12: 4.8600001 | M12: 5.5100002 | N12: 14.81 | O12: 17.98 | P12: 17.940001 | Q12: 14.82 | R12: 12.69 | S12: 9.9700003 | T12: 8.7600002 | U12: 13.78 | V12: 13.39 | W12: 17.370001 | X12: 28.209999 | Y12: 33.169998 | Z12: 34.580002 | AA12: 37.98 | AB12: 52.23 | AC12: 46.529999 | AD12: 40.560001 | AE12: 38.060001 | AF12: 46.470001 | AG12: 43.48 | AH12: 39.75 | AI12: 46.060001 | AJ12: 46.450001 | AK12: 57.040001 | AL12: 59.639999
A13: VIC Imports | B13: GWh | C13: 743.65002 | D13: 493.76999 | E13: 441.19 | F13: 81.089996 | G13: 357.17001 | H13: 384.19 | I13: 354.06 | J13: 276.32001 | K13: 264.53 | L13: 147.71001 | M13: 239.78999 | N13: 593.09003 | O13: 596.13 | P13: 565.65002 | Q13: 492.5 | R13: 441.20001 | S13: 408.51999 | T13: 334.56 | U13: 516.96002 | V13: 486.44 | W13: 611.64001 | X13: 856.19 | Y13: 1011.8 | Z13: 1184.98 | AA13: 1255.22 | AB13: 1650.72 | AC13: 1523.02 | AD13: 1332.11 | AE13: 1212.22 | AF13: 1412.24 | AG13: 1368.73 | AH13: 1204.62 | AI13: 1325.59 | AJ13: 1356.92 | AK13: 1530.89 | AL13: 1481.39
A14: SA Losses | B14: GWh | C14: 72.510002 | D14: 78.690002 | E14: 93.779999 | F14: 113.97 | G14: 27.629999 | H14: 32.93 | I14: 44.599998 | J14: 51.07 | K14: 62.990002 | L14: 107.18 | M14: 64.379997 | N14: 29.790001 | O14: 60.41 | P14: 81.309998 | Q14: 89.629997 | R14: 95.68 | S14: 89.709999 | T14: 144.42999 | U14: 105.93 | V14: 96.029999 | W14: 76.209999 | X14: 77.419998 | Y14: 56.369999 | Z14: 39.68 | AA14: 34.939999 | AB14: 28.790001 | AC14: 33.599998 | AD14: 37.939999 | AE14: 44.75 | AF14: 33.639999 | AG14: 31.620001 | AH14: 38.009998 | AI14: 36.150002 | AJ14: 37.5 | AK14: 34.779999 | AL14: 33.880001
A15: SA Imports | B15: GWh | C15: 1908.83 | D15: 2066.3501 | E15: 2319.45 | F15: 2946.1001 | G15: 1154.9301 | H15: 1538.89 | I15: 1972.8199 | J15: 2102.3 | K15: 2342.26 | L15: 3200.2 | M15: 2330.28 | N15: 1345.15 | O15: 2158.02 | P15: 2480.73 | Q15: 2598.53 | R15: 2667.54 | S15: 2562.4099 | T15: 3414.6499 | U15: 2658.72 | V15: 2562.46 | W15: 2146.2 | X15: 2052.1899 | Y15: 1665.91 | Z15: 1222.42 | AA15: 1180.9399 | AB15: 974.89001 | AC15: 1089.0601 | AD15: 1227.36 | AE15: 1362.22 | AF15: 1161.97 | AG15: 1102.89 | AH15: 1292.63 | AI15: 1231.6 | AJ15: 1258.6 | AK15: 1192.6 | AL15: 1181.92
A17: VICTORIA-SNOWY
A18: SNOWY-VIC Firm Capacity | B18: MW | C18: 1500 | D18: 1500 | E18: 1500 | F18: 1500 | G18: 3900 | H18: 3900 | I18: 3900 | J18: 3900 | K18: 3900 | L18: 3900 | M18: 3900 | N18: 5000 | O18: 5000 | P18: 5000 | Q18: 5000 | R18: 5000 | S18: 5000 | T18: 5000 | U18: 5000 | V18: 5000 | W18: 5000 | X18: 5000 | Y18: 5000 | Z18: 5000 | AA18: 5000 | AB18: 5000 | AC18: 5000 | AD18: 5000 | AE18: 5000 | AF18: 5000 | AG18: 5000 | AH18: 5000 | AI18: 5000 | AJ18: 5000 | AK18: 5000 | AL18: 5000
A19: VIC Losses | B19: GWh | C19: 48.189999 | D19: 37.080002 | E19: 39.470001 | F19: 29.709999 | G19: 48.16 | H19: 58.5 | I19: 35.119999 | J19: 21.530001 | K19: 13.68 | L19: 17.68 | M19: 16.690001 | N19: 13.82 | O19: 24.66 | P19: 30.82 | Q19: 36.330002 | R19: 47.619999 | S19: 60.970001 | T19: 47.18 | U19: 58.490002 | V19: 53.939999 | W19: 58.009998 | X19: 46.490002 | Y19: 57.98 | Z19: 78.489998 | AA19: 77.75 | AB19: 103.64 | AC19: 88.75 | AD19: 77.739998 | AE19: 77.550003 | AF19: 74.849998 | AG19: 78.190002 | AH19: 67.809998 | AI19: 60.529999 | AJ19: 70.419998 | AK19: 80.43 | AL19: 68.480003
A20: VIC Imports | B20: GWh | C20: 1306.9301 | D20: 1049.21 | E20: 1120.36 | F20: 1029.54 | G20: 2154.95 | H20: 2591.6499 | I20: 1975.72 | J20: 1430.04 | K20: 910.47998 | L20: 1113.37 | M20: 978.19 | N20: 822.95001 | O20: 1240.62 | P20: 1563.35 | Q20: 1830.11 | R20: 2079.96 | S20: 2510.78 | T20: 2193.24 | U20: 2540.9399 | V20: 2493.6499 | W20: 2472.71 | X20: 2101.6799 | Y20: 2386.24 | Z20: 2819.78 | AA20: 2629.3201 | AB20: 3244.24 | AC20: 2821.72 | AD20: 2531.7 | AE20: 2484.76 | AF20: 2394.3501 | AG20: 2463.1201 | AH20: 2181.4099 | AI20: 2052.3999 | AJ20: 2254.22 | AK20: 2457.3999 | AL20: 2131.8899
A21: SNOWY Losses | B21: GWh | C21: 250.82001 | D21: 284.69 | E21: 283.57001 | F21: 226.82001 | G21: 140.97 | H21: 194.37 | I21: 230.57001 | J21: 284.89001 | K21: 422.73999 | L21: 568.96997 | M21: 486.64999 | N21: 581.83002 | O21: 663.82001 | P21: 812.66998 | Q21: 865.66998 | R21: 932.60999 | S21: 792.67999 | T21: 701.45001 | U21: 613.46002 | V21: 560.64001 | W21: 535.85999 | X21: 567.08002 | Y21: 514.28003 | Z21: 329.06 | AA21: 373.39999 | AB21: 376.45999 | AC21: 407.70999 | AD21: 415.17999 | AE21: 387.14001 | AF21: 442.95999 | AG21: 444.01999 | AH21: 466.73001 | AI21: 473.88 | AJ21: 498.22 | AK21: 500.54999 | AL21: 512.21002
A22: SNOWY Imports | B22: GWh | C22: 4497.75 | D22: 5014 | E22: 4964.5698 | F22: 4152.4902 | G22: 3845.2 | H22: 4767.1802 | I22: 5344.2402 | J22: 6224.9199 | K22: 8339.9502 | L22: 9952.1797 | M22: 9096.2197 | N22: 9791.9199 | O22: 10597.78 | P22: 11699.99 | Q22: 12150.63 | R22: 12611.19 | S22: 11183.48 | T22: 10383.66 | U22: 9180.5898 | V22: 8677.2803 | W22: 8442.04 | X22: 8817.4404 | Y22: 8129.2002 | Z22: 6242.29 | AA22: 6736.27 | AB22: 6664.0098 | AC22: 7106.0298 | AD22: 7182.6499 | AE22: 6862.4102 | AF22: 7381 | AG22: 7383.9902 | AH22: 7733.6001 | AI22: 7880.0498 | AJ22: 8147.02 | AK22: 8198.6504 | AL22: 8369.3701
A24: REDCLIFF-SA
A25: SA-REDCLIFF Firm Capacity | B25: MW | C25: 200 | D25: 200 | E25: 200 | F25: 200 | G25: 200 | H25: 200 | I25: 200 | J25: 200 | K25: 200 | L25: 200 | M25: 200 | N25: 200 | O25: 200 | P25: 200 | Q25: 200 | R25: 200 | S25: 200 | T25: 200 | U25: 200 | V25: 200 | W25: 200 | X25: 200 | Y25: 200 | Z25: 200 | AA25: 200 | AB25: 200 | AC25: 201 | AD25: 202 | AE25: 203 | AF25: 204 | AG25: 205 | AH25: 201 | AI25: 202 | AJ25: 203 | AK25: 204 | AL25: 205
A26: REDCLIFF Losses | B26: GWh | C26: 102.9 | D26: 89.489998 | E26: 90.900002 | F26: 37.150002 | G26: 66.690002 | H26: 50.080002 | I26: 50.09 | J26: 35.889999 | K26: 22.75 | L26: 16.389999 | M26: 27.120001 | N26: 57.540001 | O26: 42.09 | P26: 43.279999 | Q26: 42.830002 | R26: 37.200001 | S26: 50.009998 | T26: 49.18 | U26: 52.709999 | V26: 51.349998 | W26: 58.889999 | X26: 78.690002 | Y26: 86.120003 | Z26: 101.56 | AA26: 127.83 | AB26: 136.81 | AC26: 141.39 | AD26: 132.08 | AE26: 116.5 | AF26: 146.99001 | AG26: 144.21001 | AH26: 123.67 | AI26: 125.11 | AJ26: 122.23 | AK26: 136.28 | AL26: 127.46
A27: REDCLIFF Imports | B27: GWh | C27: 218.75 | D27: 195.08 | E27: 207.86 | F27: 80.610001 | G27: 134.81 | H27: 89.029999 | I27: 83.269997 | J27: 62.540001 | K27: 35.66 | L27: 31.09 | M27: 48.700001 | N27: 104.65 | O27: 81.669998 | P27: 89.57 | Q27: 79.849998 | R27: 69.989998 | S27: 108.68 | T27: 111.44 | U27: 97.660004 | V27: 97.760002 | W27: 118.54 | X27: 178.97 | Y27: 187.58 | Z27: 206.46001 | AA27: 286.89999 | AB27: 298.39999 | AC27: 311.79999 | AD27: 295.73001 | AE27: 256.57999 | AF27: 337.35999 | AG27: 320.69 | AH27: 283.67999 | AI27: 278.53 | AJ27: 252.05 | AK27: 309.44 | AL27: 293.70001
A28: SA Losses | B28: GWh | C28: 50.029999 | D28: 51.110001 | E28: 44.09 | F28: 49.200001 | G28: 74.940002 | H28: 81.839996 | I28: 76.919998 | J28: 80.5 | K28: 81.669998 | L28: 72.860001 | M28: 83 | N28: 92.160004 | O28: 79.080002 | P28: 74.220001 | Q28: 72.980003 | R28: 72.239998 | S28: 74.529999 | T28: 66.610001 | U28: 65.809998 | V28: 66.809998 | W28: 72.260002 | X28: 68.150002 | Y28: 70.900002 | Z28: 73.580002 | AA28: 68.080002 | AB28: 64.559998 | AC28: 62.34 | AD28: 64.290001 | AE28: 65.269997 | AF28: 61.150002 | AG28: 59.369999 | AH28: 64.089996 | AI28: 62.43 | AJ28: 61.939999 | AK28: 61.240002 | AL28: 63.959999
A29: SA Imports | B29: GWh | C29: 681.94 | D29: 730.94 | E29: 789.96997 | F29: 933.47998 | G29: 491.5 | H29: 485.23999 | I29: 576.28998 | J29: 585.13 | K29: 660.15997 | L29: 817.87 | M29: 641.78003 | N29: 446.19 | O29: 626.63 | P29: 674.06 | Q29: 691.17999 | R29: 724.14001 | S29: 708.07001 | T29: 813.28003 | U29: 699.03998 | V29: 688.34003 | W29: 612.33002 | X29: 575.28998 | Y29: 519.03998 | Z29: 404.89001 | AA29: 386.91 | AB29: 336.94 | AC29: 351.20999 | AD29: 369.31 | AE29: 419.01001 | AF29: 370.07999 | AG29: 351.26999 | AH29: 409.12 | AI29: 387.35999 | AJ29: 390.03 | AK29: 372.70001 | AL29: 387.09
A31: SNOWY-NSW
A32: NSW-SNOWY Firm Capacity | B32: MW | C32: 1150 | D32: 1150 | E32: 1150 | F32: 1150 | G32: 4150 | H32: 4150 | I32: 4150 | J32: 4150 | K32: 4150 | L32: 4150 | M32: 4150 | N32: 4150 | O32: 4150 | P32: 4150 | Q32: 4150 | R32: 4150 | S32: 4150 | T32: 4150 | U32: 4150 | V32: 4150 | W32: 4150 | X32: 4150 | Y32: 4150 | Z32: 4150 | AA32: 4150 | AB32: 4150 | AC32: 4150 | AD32: 4150 | AE32: 4150 | AF32: 4150 | AG32: 4150 | AH32: 4150 | AI32: 4150 | AJ32: 4150 | AK32: 4150 | AL32: 4150
A33: SNOWY Losses | B33: GWh | C33: 1.14 | D33: 0.20999999 | E33: -0.31999999 | F33: -0.75999999 | G33: 55.709999 | H33: 191.22 | I33: 183.25999 | J33: 181.77 | K33: 99.449997 | L33: 128 | M33: 68.839996 | N33: 48.029999 | O33: 55.84 | P33: 89.519997 | Q33: 40.310001 | R33: 53.110001 | S33: 139.23 | T33: 145.78 | U33: 187.37 | V33: 181.08 | W33: 164.03999 | X33: 108.05 | Y33: 115.11 | Z33: 168.19 | AA33: 166.44 | AB33: 184.03999 | AC33: 134.92 | AD33: 167 | AE33: 184.08 | AF33: 190.3 | AG33: 165.91 | AH33: 189.33 | AI33: 166.34 | AJ33: 176 | AK33: 154.34 | AL33: 164.53999
A34: SNOWY Imports | B34: GWh | C34: 706.88 | D34: 752.01001 | E34: 814.71002 | F34: 651.03003 | G34: 953.60999 | H34: 1932.65 | I34: 1755.5 | J34: 1760.3 | K34: 959.19 | L34: 1037.6 | M34: 721.34003 | N34: 585.81 | O34: 672.01001 | P34: 879.71002 | Q34: 563.23999 | R34: 645.22998 | S34: 1118.5699 | T34: 1151.02 | U34: 1478.91 | V34: 1472.55 | W34: 1421.84 | X34: 1156.37 | Y34: 1198.14 | Z34: 1672.89 | AA34: 1626.12 | AB34: 1815.1 | AC34: 1508.42 | AD34: 1633.89 | AE34: 1723.45 | AF34: 1752.65 | AG34: 1607.6 | AH34: 1665.47 | AI34: 1509.89 | AJ34: 1551.3199 | AK34: 1493.3101 | AL34: 1526.0601
A35: NSW Losses | B35: GWh | C35: 173.83 | D35: 196.91 | E35: 194.27 | F35: 122.82 | G35: 110.71 | H35: 157.60001 | I35: 180.41 | J35: 239.22 | K35: 316 | L35: 410.95999 | M35: 349.20999 | N35: 413.01999 | O35: 451.73999 | P35: 509.62 | Q35: 491.73001 | R35: 483.10999 | S35: 415.09 | T35: 389.01999 | U35: 346.51999 | V35: 331.17999 | W35: 311.92001 | X35: 332.37 | Y35: 303.31 | Z35: 223.17999 | AA35: 255.87 | AB35: 232.32001 | AC35: 256.75 | AD35: 290.35999 | AE35: 279.17999 | AF35: 311.69 | AG35: 301.78 | AH35: 322.29001 | AI35: 343.39001 | AJ35: 337.85999 | AK35: 321.69 | AL35: 355.26999
A36: NSW Imports | B36: GWh | C36: 7305.6699 | D36: 8104.6602 | E36: 8011.7402 | F36: 7114.9502 | G36: 5921.29 | H36: 6714.8501 | I36: 7741.77 | J36: 8965.54 | K36: 10808.43 | L36: 12042.85 | M36: 11367.78 | N36: 12305.03 | O36: 12589.56 | P36: 13314.6 | Q36: 13150.03 | R36: 13272.61 | S36: 11945.15 | T36: 11565.77 | U36: 10442.96 | V36: 10044.03 | W36: 9816.4502 | X36: 10397.24 | Y36: 9607.7402 | Z36: 7998.71 | AA36: 8601 | AB36: 7995.02 | AC36: 8560.8701 | AD36: 9112.2598 | AE36: 8963.4297 | AF36: 9560.9004 | AG36: 9374.0498 | AH36: 9972.5498 | AI36: 10183.12 | AJ36: 10157.29 | AK36: 9859.0098 | AL36: 10477.58
A38: NSW-QLDSTH | B38: QNI
A39: QLDSTH-NSW Firm Capacity | B39: MW | C39: 1365 | D39: 1365 | E39: 1365 | F39: 1365 | G39: 1365 | H39: 1365 | I39: 1365 | J39: 1365 | K39: 1365 | L39: 3365 | M39: 3365 | N39: 3365 | O39: 3365 | P39: 3365 | Q39: 3365 | R39: 3365 | S39: 3365 | T39: 3365 | U39: 3365 | V39: 3365 | W39: 3365 | X39: 3365 | Y39: 3365 | Z39: 3365 | AA39: 3365 | AB39: 3365 | AC39: 3365 | AD39: 3365 | AE39: 3365 | AF39: 3365 | AG39: 3365 | AH39: 3365 | AI39: 3365 | AJ39: 3365 | AK39: 3365 | AL39: 3365
A40: NSW Losses | B40: GWh | C40: 602.56 | D40: 627.81 | E40: 680.59998 | F40: 493.94 | G40: 920.10999 | H40: 796.34003 | I40: 755.96002 | J40: 509.10001 | K40: 516.85999 | L40: 366.95001 | M40: 216.58 | N40: 82.650002 | O40: 61.41 | P40: 62.330002 | Q40: 26.32 | R40: 108.5 | S40: 283.73999 | T40: 238.23 | U40: 265.78 | V40: 240.75 | W40: 291.62 | X40: 132.41 | Y40: 186.77 | Z40: 264.17999 | AA40: 268.35999 | AB40: 360.14999 | AC40: 284.04001 | AD40: 264.12 | AE40: 256.10999 | AF40: 252.85001 | AG40: 276.35999 | AH40: 259.53 | AI40: 241.91 | AJ40: 313.14999 | AK40: 322.84 | AL40: 265.89001
A41: NSW Imports | B41: GWh | C41: 4377.2598 | D41: 4455.6201 | E41: 4473.96 | F41: 3253.51 | G41: 5469.1802 | H41: 4675.0801 | I41: 4603.8101 | J41: 3339 | K41: 3321.8601 | L41: 4486.6899 | M41: 2857.1001 | N41: 1414.75 | O41: 1139.4301 | P41: 984.83002 | Q41: 500.85001 | R41: 1512.04 | S41: 3385.4099 | T41: 3073.49 | U41: 3173.9399 | V41: 2971.48 | W41: 3314.97 | X41: 1839.9 | Y41: 2146.47 | Z41: 2753.25 | AA41: 2802.9199 | AB41: 3628.96 | AC41: 3106.28 | AD41: 2722.8799 | AE41: 2616.8401 | AF41: 2610.48 | AG41: 2740.1599 | AH41: 2640.0801 | AI41: 2487.05 | AJ41: 3122.0801 | AK41: 3163.4399 | AL41: 2749.96
A42: QLDSTH Losses | B42: GWh | C42: 2.8099999 | D42: 4.5599999 | E42: 7.0900002 | F42: 36.799999 | G42: 20.01 | H42: 46.360001 | I42: 30.870001 | J42: 58.43 | K42: 59.25 | L42: 29.76 | M42: 67.220001 | N42: 125.14 | O42: 140.60001 | P42: 161.06 | Q42: 218.77 | R42: 160.44 | S42: 89.559998 | T42: 93.160004 | U42: 95.269997 | V42: 110.09 | W42: 107.38 | X42: 164.72 | Y42: 160.82001 | Z42: 137.92999 | AA42: 144.07001 | AB42: 113.78 | AC42: 126.83 | AD42: 173.02 | AE42: 187.21001 | AF42: 199.72 | AG42: 208.13 | AH42: 225.13 | AI42: 248.53 | AJ42: 208.78999 | AK42: 205.78 | AL42: 224.5
A43: QLDSTH Imports | B43: GWh | C43: 217.07001 | D43: 299.38 | E43: 463.64999 | F43: 1487.02 | G43: 772.78998 | H43: 1548.21 | I43: 1132.1801 | J43: 1886.21 | K43: 1874.22 | L43: 1974.89 | M43: 3694.04 | N43: 5306.3398 | O43: 5695.7202 | P43: 6363.0898 | Q43: 8387.7402 | R43: 6187.3198 | S43: 3766.5801 | T43: 3953.0801 | U43: 4043.3401 | V43: 4486.1099 | W43: 4344.8101 | X43: 6499.29 | Y43: 6198.8398 | Z43: 5581.5601 | AA43: 5705.4902 | AB43: 4729.4199 | AC43: 5146.3901 | AD43: 6592.6201 | AE43: 6932.3901 | AF43: 7095.71 | AG43: 7183.9502 | AH43: 7632.48 | AI43: 8196 | AJ43: 7027.1299 | AK43: 6959.4902 | AL43: 7675.5601
A45: QLDSTH-QLDCEN
A46: QLDCEN-QLDSTH Firm Capacity | B46: MW | C46: 1899.53 | D46: 1899.53 | E46: 1899.53 | F46: 1899.53 | G46: 1899.53 | H46: 1899.53 | I46: 2499.53 | J46: 2499.53 | K46: 2499.53 | L46: 2499.53 | M46: 2499.53 | N46: 2499.53 | O46: 2999.53 | P46: 2999.53 | Q46: 2999.53 | R46: 2999.53 | S46: 2999.53 | T46: 2999.53 | U46: 2999.53 | V46: 2999.53 | W46: 4000 | X46: 4000 | Y46: 4000 | Z46: 4000 | AA46: 5000 | AB46: 5000 | AC46: 5000 | AD46: 5000 | AE46: 5000 | AF46: 5000 | AG46: 5000 | AH46: 5000 | AI46: 5000 | AJ46: 5000 | AK46: 5000 | AL46: 5000
A47: QLDSTH Losses | B47: GWh | C47: 72.040001 | D47: 30.9 | E47: 30.040001 | F47: 39.860001 | G47: 142.85001 | H47: 114.88 | I47: 66.419998 | J47: 30.959999 | K47: 35.540001 | L47: 86.160004 | M47: 48.32 | N47: 39.209999 | O47: 50.290001 | P47: 57.459999 | Q47: 30.950001 | R47: 81.089996 | S47: 282.09 | T47: 560.46002 | U47: 607.72998 | V47: 587.71002 | W47: 422 | X47: 341.87 | Y47: 402.13 | Z47: 433.5 | AA47: 439.26999 | AB47: 495.60999 | AC47: 509.04999 | AD47: 456.54001 | AE47: 508.48999 | AF47: 588.59003 | AG47: 712.57001 | AH47: 709.16998 | AI47: 739.90002 | AJ47: 977.90002 | AK47: 952.33002 | AL47: 922.21997
A48: QLDSTH Imports | B48: GWh | C48: 5176.8799 | D48: 2989.79 | E48: 2328.23 | F48: 2649.1499 | G48: 5752.0801 | H48: 5265.2202 | I48: 4686.7002 | J48: 2715.3501 | K48: 2716.8301 | L48: 3877.1599 | M48: 2400.23 | N48: 2231.51 | O48: 2988.1101 | P48: 3747.1399 | Q48: 2690.23 | R48: 4220.2002 | S48: 8015.75 | T48: 11435.2 | U48: 12144.44 | V48: 11948.6 | W48: 12001.86 | X48: 10934.64 | Y48: 11440.6 | Z48: 11903.16 | AA48: 12729.65 | AB48: 13298.27 | AC48: 13386.91 | AD48: 12864.57 | AE48: 13639.08 | AF48: 14687.99 | AG48: 15981.97 | AH48: 15985.51 | AI48: 16265.48 | AJ48: 18543.92 | AK48: 18094.75 | AL48: 17854.039
A49: QLDCEN Losses | B49: GWh | C49: 2.4000001 | D49: 26.959999 | E49: 73.400002 | F49: 96.040001 | G49: 8.3599997 | H49: 14.34 | I49: 24.08 | J49: 102.07 | K49: 114.89 | L49: 90.849998 | M49: 257.38 | N49: 248.53999 | O49: 112.53 | P49: 82.400002 | Q49: 131.05 | R49: 91.339996 | S49: 17.16 | T49: 11.16 | U49: 6.9400001 | V49: 7.4000001 | W49: 4.8400002 | X49: 5.4099998 | Y49: 6.8200002 | Z49: 6.1199999 | AA49: 0.83999997 | AB49: 0.69 | AC49: 0.33000001 | AD49: 0.27000001 | AE49: 0.25999999 | AF49: 0.22 | AG49: 0.2 | AH49: 0.25 | AI49: 0.2 | AJ49: 0.25 | AK49: 0.20999999 | AL49: 0.02
A50: QLDCEN Imports | B50: GWh | C50: 11.77 | D50: 164.38 | E50: 499.42001 | F50: 691.82001 | G50: 52.150002 | H50: 83.959999 | I50: 232.25999 | J50: 1093.7 | K50: 1214.7 | L50: 949.87 | M50: 2457.45 | N50: 2400.6799 | O50: 1521.4 | P50: 1111.52 | Q50: 1729.49 | R50: 1208.84 | S50: 222.05 | T50: 141.73 | U50: 89.459999 | V50: 95.120003 | W50: 83.480003 | X50: 93.169998 | Y50: 116.56 | Z50: 101.23 | AA50: 60.619999 | AB50: 65.599998 | AC50: 26.24 | AD50: 28.09 | AE50: 28.950001 | AF50: 25.1 | AG50: 24.049999 | AH50: 23.219999 | AI50: 20.290001 | AJ50: 3.74 | AK50: 8.8000002 | AL50: 0
A52: QLDCEN-QLDNTH
A53: QLDNTH-QLDCEN Firm Capacity | B53: MW | C53: 2225 | D53: 2225 | E53: 2225 | F53: 2225 | G53: 2225 | H53: 2225 | I53: 2225 | J53: 2225 | K53: 2225 | L53: 2225 | M53: 2225 | N53: 2225 | O53: 2225 | P53: 2225 | Q53: 2225 | R53: 2225 | S53: 2225 | T53: 2225 | U53: 2225 | V53: 2225 | W53: 2999.53 | X53: 2999.53 | Y53: 4000 | Z53: 4000 | AA53: 4000 | AB53: 4000 | AC53: 4000 | AD53: 4000 | AE53: 4000 | AF53: 4000 | AG53: 4000 | AH53: 4000 | AI53: 4000 | AJ53: 4000 | AK53: 4000 | AL53: 4000
A54: QLDCEN Losses | B54: GWh | C54: 1.9 | D54: 0 | E54: 0 | F54: 1.98 | G54: 9.1400003 | H54: 11.51 | I54: 10.58 | J54: 0 | K54: 0 | L54: 0 | M54: 18.33 | N54: 35.59 | O54: 26.57 | P54: 83.220001 | Q54: 63.220001 | R54: 116.05 | S54: 313.35999 | T54: 258.07999 | U54: 413.70999 | V54: 346.47 | W54: 50.84 | X54: 65.290001 | Y54: 53.18 | Z54: 53.57 | AA54: 46.98 | AB54: 54.77 | AC54: 67.440002 | AD54: 58.900002 | AE54: 67.660004 | AF54: 94.339996 | AG54: 126.02 | AH54: 123.37 | AI54: 116.2 | AJ54: 236.27 | AK54: 276.63 | AL54: 263.39999
A55: QLDCEN Imports | B55: GWh | C55: 7.6199999 | D55: 0 | E55: 0 | F55: 1.6900001 | G55: 41.080002 | H55: 67.220001 | I55: 74.519997 | J55: 0 | K55: 0 | L55: 0 | M55: 126.45 | N55: 231.61 | O55: 189.32001 | P55: 701.62 | Q55: 505.69 | R55: 1082.46 | S55: 2762.73 | T55: 2299.8301 | U55: 3466.29 | V55: 2904.1599 | W55: 3403.9299 | X55: 3835.8601 | Y55: 3996.3301 | Z55: 4004.9199 | AA55: 3618.6899 | AB55: 3937.6201 | AC55: 4468.8901 | AD55: 4136.8198 | AE55: 4358.3301 | AF55: 5254.5098 | AG55: 5973.6699 | AH55: 5917.2798 | AI55: 5726.7998 | AJ55: 7879.8398 | AK55: 8393.3604 | AL55: 8194.3896
A56: QLDNTH Losses | B56: GWh | C56: 36.09 | D56: 26.969999 | E56: 33.59 | F56: 20.98 | G56: 7.5799999 | H56: 8.5100002 | I56: 13.91 | J56: 11.12 | K56: 15.88 | L56: 10.94 | M56: 23.49 | N56: 18.629999 | O56: 18.950001 | P56: 13.74 | Q56: 15.92 | R56: 16.110001 | S56: 10.29 | T56: 13.87 | U56: 8.1499996 | V56: 10.42 | W56: 12.87 | X56: 7.3699999 | Y56: 0 | Z56: 0.47999999 | AA56: 2.1300001 | AB56: 0 | AC56: 2.1700001 | AD56: 2.48 | AE56: 0 | AF56: 1.8099999 | AG56: 0.090000004 | AH56: 0 | AI56: 0 | AJ56: 0 | AK56: 0.85000002 | AL56: 1.24
A57: QLDNTH Imports | B57: GWh | C57: 3876.72 | D57: 4159.4502 | E57: 4311.6602 | F57: 3788.01 | G57: 2478.8799 | H57: 2798.8799 | I57: 2962.1499 | J57: 3250.8799 | K57: 3666.0701 | L57: 2652.6001 | M57: 1145.3199 | N57: 927.45001 | O57: 1136.62 | P57: 542.27002 | Q57: 644.39001 | R57: 440.39001 | S57: 93.419998 | T57: 136.89999 | U57: 78.809998 | V57: 99.82 | W57: 60.389999 | X57: 36.439999 | Y57: 0 | Z57: 0.02 | AA57: 0.89999998 | AB57: 0 | AC57: 0.75 | AD57: 0.63 | AE57: 0 | AF57: 0.33000001 | AG57: 0.02 | AH57: 0 | AI57: 0 | AJ57: 0 | AK57: 0.039999999 | AL57: 0.34999999
A59: SA-NSW | B59: EnergyConnect
A60: NSW- SA Firm Capacity | B60: MW | C60: 0 | D60: 0 | E60: 0 | F60: 800 | G60: 800 | H60: 800 | I60: 800 | J60: 800 | K60: 800 | L60: 800 | M60: 800 | N60: 800 | O60: 800 | P60: 800 | Q60: 800 | R60: 800 | S60: 800 | T60: 1000 | U60: 1000 | V60: 1000 | W60: 1000 | X60: 1000 | Y60: 1000 | Z60: 1000 | AA60: 1000 | AB60: 1000 | AC60: 1000 | AD60: 1000 | AE60: 1000 | AF60: 1000 | AG60: 1000 | AH60: 1000 | AI60: 1000 | AJ60: 1000 | AK60: 1000 | AL60: 1000
A61: SA Losses | B61: GWh | C61: 0 | D61: 0 | E61: 0 | F61: 36.939999 | G61: 36.82 | H61: 37.580002 | I61: 21.559999 | J61: 12.83 | K61: 7.8000002 | L61: 7.1900001 | M61: 5.02 | N61: 4.2800002 | O61: 5.1199999 | P61: 6.3899999 | Q61: 6.4000001 | R61: 7.6399999 | S61: 9.4899998 | T61: 8.5500002 | U61: 10.33 | V61: 12.25 | W61: 12.04 | X61: 9.1700001 | Y61: 12.89 | Z61: 20.9 | AA61: 19.57 | AB61: 29.309999 | AC61: 24.35 | AD61: 15.54 | AE61: 20.360001 | AF61: 17.23 | AG61: 19.01 | AH61: 14.58 | AI61: 12.66 | AJ61: 14.11 | AK61: 17.950001 | AL61: 16.41
A62: SA Imports | B62: GWh | C62: 0 | D62: 0 | E62: 0 | F62: 777.09998 | G62: 772.98999 | H62: 788.06 | I62: 451.5 | J62: 265.01999 | K62: 161.23 | L62: 149.25999 | M62: 103.14 | N62: 88 | O62: 105.68 | P62: 134.08 | Q62: 134.81 | R62: 161.22 | S62: 200.66 | T62: 192.3 | U62: 231.83 | V62: 276.48999 | W62: 271.48001 | X62: 203.46001 | Y62: 287.39001 | Z62: 463.72 | AA62: 434.57999 | AB62: 642.03003 | AC62: 535.19 | AD62: 346.07999 | AE62: 451.79001 | AF62: 380.67999 | AG62: 419.88 | AH62: 320 | AI62: 280.37 | AJ62: 311.41 | AK62: 394.01001 | AL62: 359.82001
A63: NSW Losses | B63: GWh | C63: 0 | D63: 0 | E63: 0 | F63: 104.92 | G63: 75.489998 | H63: 76.559998 | I63: 85.449997 | J63: 103.37 | K63: 174.13 | L63: 193.97 | M63: 202.44 | N63: 236.14999 | O63: 199.31 | P63: 193.50999 | Q63: 186.63 | R63: 191.2 | S63: 181.83 | T63: 210.00999 | U63: 226.85001 | V63: 206.37 | W63: 210.97 | X63: 237.21001 | Y63: 224.75 | Z63: 202.92 | AA63: 221.05 | AB63: 201.85001 | AC63: 208.42 | AD63: 219.92999 | AE63: 216.82001 | AF63: 247.33 | AG63: 238.50999 | AH63: 248.28999 | AI63: 253.57001 | AJ63: 253.95 | AK63: 244.17999 | AL63: 259
A64: NSW Imports | B64: GWh | C64: 0 | D64: 0 | E64: 0 | F64: 2138.49 | G64: 1552.38 | H64: 1561.36 | I64: 1761.41 | J64: 2115.8601 | K64: 3524.6499 | L64: 3893.1299 | M64: 4078.1499 | N64: 4723.1499 | O64: 3992.0601 | P64: 3873.8301 | Q64: 3728.9299 | R64: 3807.1101 | S64: 3631.28 | T64: 4338.1099 | U64: 4647.1401 | V64: 4250.7598 | W64: 4334.3599 | X64: 4837.73 | Y64: 4575.73 | Z64: 4137.2998 | AA64: 4483.0298 | AB64: 4085.21 | AC64: 4239.7998 | AD64: 4479.5898 | AE64: 4416 | AF64: 5018.0601 | AG64: 4841.4302 | AH64: 5041.8799 | AI64: 5138.2202 | AJ64: 5150.2202 | AK64: 4953.3501 | AL64: 5249.6699
A66: VICTORIA-REDCLIFF
A67: REDCLIFF-VIC Firm Capacity | B67: MW | C67: 220 | D67: 220 | E67: 220 | F67: 220 | G67: 220 | H67: 220 | I67: 220 | J67: 220 | K67: 220 | L67: 220 | M67: 220 | N67: 220 | O67: 220 | P67: 220 | Q67: 220 | R67: 220 | S67: 220 | T67: 220 | U67: 220 | V67: 220 | W67: 220 | X67: 220 | Y67: 220 | Z67: 220 | AA67: 220 | AB67: 220 | AC67: 220 | AD67: 220 | AE67: 220 | AF67: 220 | AG67: 220 | AH67: 220 | AI67: 220 | AJ67: 220 | AK67: 220 | AL67: 220
A68: VIC Losses | B68: GWh | C68: -32.990002 | D68: -29.42 | E68: -31.35 | F68: -12.16 | G68: -20.33 | H68: -13.43 | I68: -12.56 | J68: -9.4300003 | K68: -5.3800001 | L68: -4.6900001 | M68: -7.3400002 | N68: -15.78 | O68: -12.32 | P68: -13.51 | Q68: -12.04 | R68: -10.55 | S68: -16.389999 | T68: -16.799999 | U68: -14.73 | V68: -14.74 | W68: -17.879999 | X68: -26.99 | Y68: -28.290001 | Z68: -31.129999 | AA68: -43.259998 | AB68: -45 | AC68: -47.02 | AD68: -44.599998 | AE68: -38.689999 | AF68: -50.869999 | AG68: -48.360001 | AH68: -42.779999 | AI68: -42 | AJ68: -38.009998 | AK68: -46.66 | AL68: -44.290001
A69: VIC Imports | B69: GWh | C69: 218.75 | D69: 195.08 | E69: 207.86 | F69: 80.610001 | G69: 134.81 | H69: 89.029999 | I69: 83.269997 | J69: 62.540001 | K69: 35.66 | L69: 31.09 | M69: 48.700001 | N69: 104.65 | O69: 81.669998 | P69: 89.57 | Q69: 79.849998 | R69: 69.989998 | S69: 108.68 | T69: 111.44 | U69: 97.660004 | V69: 97.760002 | W69: 118.54 | X69: 178.97 | Y69: 187.58 | Z69: 206.46001 | AA69: 286.89999 | AB69: 298.39999 | AC69: 311.79999 | AD69: 295.73001 | AE69: 256.57999 | AF69: 337.35999 | AG69: 320.69 | AH69: 283.67999 | AI69: 278.53 | AJ69: 252.05 | AK69: 309.44 | AL69: 293.70001
A70: REDCLIFF Losses | B70: GWh | C70: 102.84 | D70: 110.23 | E70: 119.13 | F70: 140.77 | G70: 74.120003 | H70: 73.169998 | I70: 86.900002 | J70: 88.239998 | K70: 99.550003 | L70: 123.34 | M70: 96.779999 | N70: 67.290001 | O70: 94.5 | P70: 101.65 | Q70: 104.23 | R70: 109.2 | S70: 106.78 | T70: 122.64 | U70: 105.42 | V70: 103.8 | W70: 92.339996 | X70: 86.75 | Y70: 78.269997 | Z70: 61.060001 | AA70: 58.349998 | AB70: 50.810001 | AC70: 52.959999 | AD70: 55.689999 | AE70: 63.189999 | AF70: 55.810001 | AG70: 52.970001 | AH70: 61.700001 | AI70: 58.41 | AJ70: 58.82 | AK70: 56.200001 | AL70: 58.369999
A71: REDCLIFF Imports | B71: GWh | C71: 681.94 | D71: 730.94 | E71: 789.96997 | F71: 933.47998 | G71: 491.5 | H71: 485.23999 | I71: 576.28998 | J71: 585.13 | K71: 660.15997 | L71: 817.87 | M71: 641.78003 | N71: 446.19 | O71: 626.63 | P71: 674.06 | Q71: 691.17999 | R71: 724.14001 | S71: 708.07001 | T71: 813.28003 | U71: 699.03998 | V71: 688.34003 | W71: 612.33002 | X71: 575.28998 | Y71: 519.03998 | Z71: 404.89001 | AA71: 386.91 | AB71: 336.94 | AC71: 351.20999 | AD71: 369.31 | AE71: 419.01001 | AF71: 370.07999 | AG71: 351.26999 | AH71: 409.12 | AI71: 387.35999 | AJ71: 390.03 | AK71: 372.70001 | AL71: 387.09
A74: Net imports
A75: Financial Year | C75: 2025 | D75: 2026 | E75: 2027 | F75: 2028 | G75: 2029 | H75: 2030 | I75: 2031 | J75: 2032 | K75: 2033 | L75: 2034 | M75: 2035 | N75: 2036 | O75: 2037 | P75: 2038 | Q75: 2039 | R75: 2040 | S75: 2041 | T75: 2042 | U75: 2043 | V75: 2044 | W75: 2045 | X75: 2046 | Y75: 2047 | Z75: 2048 | AA75: 2049 | AB75: 2050 | AC75: 2051 | AD75: 2052 | AE75: 2053 | AF75: 2054 | AG75: 2055 | AH75: 2056 | AI75: 2057 | AJ75: 2058 | AK75: 2059 | AL75: 2060
A76: Tas | B76: GWh | C76: -875.92995 | D76: -1210.27 | E76: -326.40998 | F76: -366.94002 | G76: -1247.68 | H76: -693.75005 | I76: 596.23998 | J76: 989.8 | K76: 2163.64 | L76: 3568.3099 | M76: 1648.03 | N76: 1703.4 | O76: 3050.3401 | P76: 4880.0402 | Q76: 4146.4 | R76: 3893.41 | S76: 5125.3699 | T76: 3779.0501 | U76: 4674.7099 | V76: 4503.9099 | W76: 4129.8901 | X76: 3506.01 | Y76: 3663.34 | Z76: 4986.1201 | AA76: 4104.75 | AB76: 4876.9998 | AC76: 3890.28 | AD76: 3659.46 | AE76: 3344.99 | AF76: 3142.5099 | AG76: 3043.6599 | AH76: 2158.8401 | AI76: 2049.75 | AJ76: 1875.67 | AK76: 1935.9001 | AL76: 1848.61
A77: Vic | B77: GWh | C77: -1084.47 | D77: -1269.4001 | E77: -2530.7999 | F77: -3926.73 | G77: -140.77004 | H77: -1110.6 | I77: -3037.6999 | J77: -3673.62 | K77: -5270.93 | L77: -7907.5398 | M77: -4705.8101 | N77: -3005.87 | O77: -5515.9101 | P77: -7754.6301 | Q77: -7253.86 | R77: -7190.2701 | S77: -8250.6099 | T77: -7970.2801 | U77: -7793.8298 | V77: -7544.4499 | W77: -6469.6001 | X77: -5342.2399 | Y77: -4865.83 | Z77: -5351.1102 | AA77: -4191.67 | AB77: -4278.1299 | AC77: -3527.14 | AD77: -3671.9899 | AE77: -3762.51 | AF77: -2949.6699 | AG77: -2834.35 | AH77: -2454.5701 | AI77: -2145.5999 | AJ77: -2025.72 | AK77: -1718.57 | AL77: -1722.52
A78: SA | B78: GWh | C78: 1960.3999 | D78: 2479.6701 | E78: 2857.2099 | F78: 3000.26 | G78: 647.73003 | H78: 1070.03 | I78: 1195.4399 | J78: 923.51994 | K78: -89.799947 | L78: 782.14005 | M78: -719.8098 | N78: -3100.8099 | O78: -1226.62 | P78: -678.04013 | Q78: -306.42991 | R78: -165.47004 | S78: -133.04008 | T78: 246.8801 | U78: -1079.6702 | V78: -739.60977 | W78: -1524.2399 | X78: -2570.0001 | Y78: -2873.99 | Z78: -3126.5697 | AA78: -3760.0498 | AB78: -3869.5099 | AC78: -3883.6798 | AD78: -3916.5899 | AE78: -3350.2299 | AF78: -4600.1201 | AG78: -4411.3602 | AH78: -4192.4399 | AI78: -4521.0902 | AJ78: -4448.9203 | AK78: -4550.4401 | AL78: -4773.3499
A79: NSW | B79: GWh | C79: 9986.5397 | D79: 10688.94 | E79: 10339.24 | F79: 8943.1002 | G79: 9449.6903 | H79: 7927.0302 | I79: 9981.68 | J79: 9910.2101 | K79: 13819.81 | L79: 16453.989 | M79: 13157.36 | N79: 11908.41 | O79: 10736.739 | P79: 10287.89 | Q79: 7854.82 | R79: 11036.371 | S79: 13233.65 | T79: 13091.199 | U79: 11963.78 | V79: 10556.24 | W79: 10896.6 | X79: 8795.7002 | Y79: 8219.5603 | Z79: 6807.8297 | AA79: 7705.5595 | AB79: 8055.45 | AC79: 8253.8398 | AD79: 7323.2894 | AE79: 6528.1797 | AF79: 7555.7804 | AG79: 7320.6097 | AH79: 7635.4898 | AI79: 7410.7903 | AJ79: 9033.6705 | AK79: 8618.3495 | AL79: 8441.0598
A80: Qld | B80: GWh | C80: -3560.4398 | D80: -3532.9901 | E80: -3336.8 | F80: -1309.35 | G80: -3796.2902 | H80: -2376.8901 | I80: -2746.54 | J80: -1002.12 | K80: -990.03015 | L80: -2174.6099 | M80: 986.29994 | N80: 3849.0998 | O80: 4477.1002 | P80: 5279.5298 | Q80: 7694.4402 | R80: 4623.3398 | S80: 575.35016 | T80: 1024.6601 | U80: 1039.9101 | V80: 1645.2899 | W80: 1214.0801 | X80: 4627.08 | Y80: 4078.3199 | Z80: 2954.5601 | AA80: 3026.8603 | AB80: 1346.83 | AC80: 2197.3201 | AD80: 3960.8402 | AE80: 4384.45 | AF80: 4538.36 | AG80: 4512.0203 | AH80: 5026.7999 | AI80: 5702.33 | AJ80: 4009.4098 | AK80: 3913.1103 | AL80: 4966.9901
A81: Net | B81: GWh | C81: 6426.0999 | D81: 7155.9501 | E81: 7002.4402 | F81: 6340.3402 | G81: 4912.6801 | H81: 4815.8201 | I81: 5989.12 | J81: 7147.79 | K81: 9632.6897 | L81: 10722.29 | M81: 10366.07 | N81: 11354.23 | O81: 11521.65 | P81: 12014.79 | Q81: 12135.37 | R81: 12197.38 | S81: 10550.72 | T81: 10171.51 | U81: 8804.8999 | V81: 8421.3802 | W81: 8246.7302 | X81: 9016.5502 | Y81: 8221.4002 | Z81: 6270.83 | AA81: 6885.45 | AB81: 6131.64 | AC81: 6930.6201 | AD81: 7355.0098 | AE81: 7144.8797 | AF81: 7686.8604 | AG81: 7630.5798 | AH81: 8174.1198 | AI81: 8496.1801 | AJ81: 8444.1101 | AK81: 8198.3497 | AL81: 8760.79

Sheet Gas Prices
A1: Gas Price per Region, ($/GJ, $Dec 2024 Dollars)
A2: Financial Year | C2: 2025 | D2: 2026 | E2: 2027 | F2: 2028 | G2: 2029 | H2: 2030 | I2: 2031 | J2: 2032 | K2: 2033 | L2: 2034 | M2: 2035 | N2: 2036 | O2: 2037 | P2: 2038 | Q2: 2039 | R2: 2040 | S2: 2041 | T2: 2042 | U2: 2043 | V2: 2044 | W2: 2045 | X2: 2046 | Y2: 2047 | Z2: 2048 | AA2: 2049 | AB2: 2050 | AC2: 2051 | AD2: 2052 | AE2: 2053 | AF2: 2054 | AG2: 2055 | AH2: 2056 | AI2: 2057 | AJ2: 2058 | AK2: 2059 | AL2: 2060
A3: Melbourne | B3: $/GJ | C3: 13.837595 | D3: 14.267779 | E3: 12.178555 | F3: 11.635716 | G3: 11.092877 | H3: 10.550038 | I3: 10.0072 | J3: 9.4643609 | K3: 9.5165228 | L3: 9.6369149 | M3: 9.8472767 | N3: 9.9611075 | O3: 9.9153639 | P3: 10.035269 | Q3: 10.209674 | R3: 10.304992 | S3: 10.498219 | T3: 10.823279 | U3: 11.136442 | V3: 11.356088 | W3: 11.582439 | X3: 11.874025 | Y3: 12.040135 | Z3: 12.058338 | AA3: 12.14835 | AB3: 12.156107 | AC3: 12.156107 | AD3: 12.156107 | AE3: 12.156107 | AF3: 12.156107 | AG3: 12.156107 | AH3: 12.156107 | AI3: 12.156107 | AJ3: 12.156107 | AK3: 12.156107 | AL3: 12.156107
A4: Nth QLD | B4: $/GJ | C4: 15.356814 | D4: 15.834228 | E4: 13.515629 | F4: 12.922311 | G4: 12.328992 | H4: 11.735674 | I4: 11.142356 | J4: 10.549038 | K4: 10.688943 | L4: 10.823391 | M4: 10.819272 | N4: 10.787329 | O4: 10.723445 | P4: 10.817712 | Q4: 10.948041 | R4: 10.948041 | S4: 11.114123 | T4: 11.271782 | U4: 11.263359 | V4: 11.295302 | W4: 11.361995 | X4: 11.557183 | Y4: 11.90034 | Z4: 12.102673 | AA4: 12.123596 | AB4: 12.208149 | AC4: 12.208149 | AD4: 12.208149 | AE4: 12.208149 | AF4: 12.208149 | AG4: 12.208149 | AH4: 12.208149 | AI4: 12.208149 | AJ4: 12.208149 | AK4: 12.208149 | AL4: 12.208149
A5: NSW | B5: $/GJ | C5: 14.330772 | D5: 14.776288 | E5: 12.612603 | F5: 12.122735 | G5: 11.632867 | H5: 11.142999 | I5: 10.653131 | J5: 10.163263 | K5: 10.320302 | L5: 10.500335 | M5: 10.681973 | N5: 10.819223 | O5: 10.874661 | P5: 11.00872 | Q5: 11.167691 | R5: 11.111668 | S5: 10.885471 | T5: 10.836601 | U5: 10.971335 | V5: 11.046271 | W5: 11.175481 | X5: 11.371845 | Y5: 11.469423 | Z5: 11.471421 | AA5: 11.561433 | AB5: 11.562227 | AC5: 11.562227 | AD5: 11.562227 | AE5: 11.562227 | AF5: 11.562227 | AG5: 11.562227 | AH5: 11.562227 | AI5: 11.562227 | AJ5: 11.562227 | AK5: 11.562227 | AL5: 11.562227
A6: Tasmania | B6: $/GJ | C6: 16.047896 | D6: 16.546794 | E6: 14.123854 | F6: 13.498079 | G6: 12.872303 | H6: 12.246527 | I6: 11.620752 | J6: 10.994976 | K6: 11.041922 | L6: 11.150275 | M6: 11.3396 | N6: 11.442048 | O6: 11.400879 | P6: 11.508794 | Q6: 11.665757 | R6: 11.695247 | S6: 11.809319 | T6: 12.098337 | U6: 12.380184 | V6: 12.577865 | W6: 12.781581 | X6: 13.044008 | Y6: 13.169663 | Z6: 13.138949 | AA6: 13.174045 | AB6: 13.117643 | AC6: 13.117643 | AD6: 13.117643 | AE6: 13.117643 | AF6: 13.117643 | AG6: 13.117643 | AH6: 13.117643 | AI6: 13.117643 | AJ6: 13.117643 | AK6: 13.117643 | AL6: 13.117643
A7: SE Qld | B7: $/GJ | C7: 14.196889 | D7: 14.638243 | E7: 12.494771 | F7: 11.99407 | G7: 11.493368 | H7: 10.992666 | I7: 10.491965 | J7: 9.991263 | K7: 10.131167 | L7: 10.265616 | M7: 10.261496 | N7: 10.229554 | O7: 10.165669 | P7: 10.259937 | Q7: 10.390266 | R7: 10.390266 | S7: 10.556347 | T7: 10.714006 | U7: 10.705584 | V7: 10.737526 | W7: 10.80422 | X7: 10.999408 | Y7: 11.342564 | Z7: 11.544898 | AA7: 11.565821 | AB7: 11.650374 | AC7: 11.650374 | AD7: 11.650374 | AE7: 11.650374 | AF7: 11.650374 | AG7: 11.650374 | AH7: 11.650374 | AI7: 11.650374 | AJ7: 11.650374 | AK7: 11.650374 | AL7: 11.650374
A8: Tarong | B8: $/GJ | C8: 13.856458 | D8: 14.287229 | E8: 12.195156 | F8: 11.557246 | G8: 10.919336 | H8: 10.281426 | I8: 9.6435164 | J8: 9.0056064 | K8: 9.1455108 | L8: 9.2799591 | M8: 9.2758399 | N8: 9.2438975 | O8: 9.1800127 | P8: 9.2742803 | Q8: 9.4046094 | R8: 9.4046094 | S8: 9.5706908 | T8: 9.7283498 | U8: 9.7199274 | V8: 9.7518698 | W8: 9.8185637 | X8: 10.013751 | Y8: 10.356908 | Z8: 10.559241 | AA8: 10.580164 | AB8: 10.664718 | AC8: 10.664718 | AD8: 10.664718 | AE8: 10.664718 | AF8: 10.664718 | AG8: 10.664718 | AH8: 10.664718 | AI8: 10.664718 | AJ8: 10.664718 | AK8: 10.664718 | AL8: 10.664718
A9: Cen Qld | B9: $/GJ | C9: 15.670094 | D9: 16.157248 | E9: 13.791349 | F9: 13.207342 | G9: 12.623335 | H9: 12.039328 | I9: 11.455321 | J9: 10.871313 | K9: 11.011218 | L9: 11.145666 | M9: 11.141547 | N9: 11.109605 | O9: 11.04572 | P9: 11.139987 | Q9: 11.270316 | R9: 11.270316 | S9: 11.436398 | T9: 11.594057 | U9: 11.585635 | V9: 11.617577 | W9: 11.684271 | X9: 11.879458 | Y9: 12.222615 | Z9: 12.424949 | AA9: 12.445871 | AB9: 12.530425 | AC9: 12.530425 | AD9: 12.530425 | AE9: 12.530425 | AF9: 12.530425 | AG9: 12.530425 | AH9: 12.530425 | AI9: 12.530425 | AJ9: 12.530425 | AK9: 12.530425 | AL9: 12.530425
A10: SA | B10: $/GJ | C10: 14.597935 | D10: 15.051756 | E10: 12.847734 | F10: 12.272016 | G10: 11.696297 | H10: 11.120579 | I10: 10.54486 | J10: 9.9691413 | K10: 10.04278 | L10: 10.153085 | M10: 10.319191 | N10: 10.408841 | O10: 10.386199 | P10: 10.526149 | Q10: 10.715143 | R10: 10.734671 | S10: 10.689198 | T10: 10.77457 | U10: 10.924922 | V10: 11.022515 | W10: 11.204941 | X10: 11.476159 | Y10: 11.620597 | Z10: 11.616524 | AA10: 11.658136 | AB10: 11.622552 | AC10: 11.622552 | AD10: 11.622552 | AE10: 11.622552 | AF10: 11.622552 | AG10: 11.622552 | AH10: 11.622552 | AI10: 11.622552 | AJ10: 11.622552 | AK10: 11.622552 | AL10: 11.622552
A11: West Qld | B11: $/GJ | C11: 13.575122 | D11: 14.016476 | E11: 11.873005 | F11: 11.372303 | G11: 10.871602 | H11: 10.3709 | I11: 9.8701984 | J11: 9.3694967 | K11: 9.5094011 | L11: 9.6438494 | M11: 9.6397302 | N11: 9.6077878 | O11: 9.543903 | P11: 9.6381706 | Q11: 9.7684997 | R11: 9.7684997 | S11: 9.9345811 | T11: 10.09224 | U11: 10.083818 | V11: 10.11576 | W11: 10.182454 | X11: 10.377641 | Y11: 10.720798 | Z11: 10.923132 | AA11: 10.944055 | AB11: 11.028608 | AC11: 11.028608 | AD11: 11.028608 | AE11: 11.028608 | AF11: 11.028608 | AG11: 11.028608 | AH11: 11.028608 | AI11: 11.028608 | AJ11: 11.028608 | AK11: 11.028608 | AL11: 11.028608
A12: NEM Region Average | B12: $/GJ | C12: 14.60773 | D12: 15.064005 | E12: 12.848073 | F12: 12.286869 | G12: 11.725664 | H12: 11.16446 | I12: 10.603255 | J12: 10.042051 | K12: 10.156418 | L12: 10.288788 | M12: 10.369547 | N12: 10.401044 | O12: 10.359539 | P12: 10.467669 | Q12: 10.615555 | R12: 10.625368 | S12: 10.721594 | T12: 10.881469 | U12: 10.974578 | V12: 11.057864 | W12: 11.177327 | X12: 11.399275 | Y12: 11.649227 | Z12: 11.760014 | AA12: 11.800163 | AB12: 11.837867 | AC12: 11.837867 | AD12: 11.837867 | AE12: 11.837867 | AF12: 11.837867 | AG12: 11.837867 | AH12: 11.837867 | AI12: 11.837867 | AJ12: 11.837867 | AK12: 11.837867 | AL12: 11.837867

Sheet Coal Prices
A1: Coal Price Thermal Generators,($/GJ, $Dec 2024 Dollars)
A2: Financial Year | D2: 2025 | E2: 2026 | F2: 2027 | G2: 2028 | H2: 2029 | I2: 2030 | J2: 2031 | K2: 2032 | L2: 2033 | M2: 2034 | N2: 2035 | O2: 2036 | P2: 2037 | Q2: 2038 | R2: 2039 | S2: 2040 | T2: 2041 | U2: 2042 | V2: 2043 | W2: 2044 | X2: 2045 | Y2: 2046 | Z2: 2047 | AA2: 2048 | AB2: 2049 | AC2: 2050 | AD2: 2051 | AE2: 2052 | AF2: 2053 | AG2: 2054 | AH2: 2055 | AI2: 2056 | AJ2: 2057 | AK2: 2058 | AL2: 2059 | AM2: 2060
A3: Thermal Plant | B3: State | C3: Coal Type
A4: Bayswater | B4: New South Wales | C4: Black Coal | D4: 3.3594778 | E4: 4.6543281 | F4: 4.3210552 | G4: 4.2291179 | H4: 3.7210641 | I4: 3.7416159 | J4: 3.7335369 | K4: 3.722765 | L4: 3.7144412 | M4: 3.7062831 | N4: 3.6835397 | O4: 3.6572287 | P4: 3.6215528 | Q4: 3.5901134 | R4: 3.5588969 | S4: 3.5588969 | T4: 3.5588969 | U4: 3.5588969 | V4: 3.5588969 | W4: 3.5588969 | X4: 3.5588969 | Y4: 3.5588969 | Z4: 3.5588969 | AA4: 3.5588969 | AB4: 3.5588969 | AC4: 3.5588969 | AD4: 3.5588969 | AE4: 3.5588969 | AF4: 3.5588969 | AG4: 3.5588969 | AH4: 3.5588969 | AI4: 3.5588969 | AJ4: 3.5588969 | AK4: 3.5588969 | AL4: 3.5588969 | AM4: 3.5588969
A5: Eraring | B5: New South Wales | C5: Black Coal | D5: 6.0520162 | E5: 7.9181039 | F5: 7.1711129 | G5: 6.424122 | H5: 5.2256838 | I5: 4.0272457 | J5: 4.0189211 | K5: 4.0078217 | L5: 3.9992449 | M5: 3.9901636 | N5: 3.9644332 | O5: 3.9346667 | P5: 3.8943053 | Q5: 3.8587368 | R5: 3.8234206 | S5: 3.7666624 | T5: 3.7384094 | U5: 3.7384094 | V5: 3.7384094 | W5: 3.7384094 | X5: 3.7384094 | Y5: 3.7384094 | Z5: 3.7384094 | AA5: 3.7384094 | AB5: 3.7384094 | AC5: 3.7384094 | AD5: 3.7384094 | AE5: 3.7384094 | AF5: 3.7384094 | AG5: 3.7384094 | AH5: 3.7384094 | AI5: 3.7384094 | AJ5: 3.7384094 | AK5: 3.7384094 | AL5: 3.7384094 | AM5: 3.7384094
A6: Liddell | B6: New South Wales | C6: Black Coal | D6: 2.0183247 | E6: 1.9720219 | F6: 1.9449064 | G6: 2.8076754 | H6: 3.7210641 | I6: 3.7416159 | J6: 3.7335369 | K6: 3.722765 | L6: 3.7144412 | M6: 3.7062831 | N6: 3.6835397 | O6: 3.6572287 | P6: 3.6215528 | Q6: 3.5901134 | R6: 3.5588969 | S6: 3.5588969 | T6: 3.5588969 | U6: 3.5588969 | V6: 3.5588969 | W6: 3.5588969 | X6: 3.5588969 | Y6: 3.5588969 | Z6: 3.5588969 | AA6: 3.5588969 | AB6: 3.5588969 | AC6: 3.5588969 | AD6: 3.5588969 | AE6: 3.5588969 | AF6: 3.5588969 | AG6: 3.5588969 | AH6: 3.5588969 | AI6: 3.5588969 | AJ6: 3.5588969 | AK6: 3.5588969 | AL6: 3.5588969 | AM6: 3.5588969
A7: Mt Piper | B7: New South Wales | C7: Black Coal | D7: 6.1669379 | E7: 8.1479472 | F7: 7.4124485 | G7: 6.6654575 | H7: 4.0224528 | I7: 4.0272457 | J7: 4.0189211 | K7: 4.0078217 | L7: 3.9992449 | M7: 3.9901636 | N7: 3.9644332 | O7: 3.9346667 | P7: 3.8943053 | Q7: 3.8587368 | R7: 3.8234206 | S7: 3.7666624 | T7: 3.7384094 | U7: 3.7384094 | V7: 3.7384094 | W7: 3.7384094 | X7: 3.7384094 | Y7: 3.7384094 | Z7: 3.7384094 | AA7: 3.7384094 | AB7: 3.7384094 | AC7: 3.7384094 | AD7: 3.7384094 | AE7: 3.7384094 | AF7: 3.7384094 | AG7: 3.7384094 | AH7: 3.7384094 | AI7: 3.7384094 | AJ7: 3.7384094 | AK7: 3.7384094 | AL7: 3.7384094 | AM7: 3.7384094
